Workbook

Sheet 2019
A1: Sr No | B1: Name of the Employee | C1: Salary | D1: Bonus amount | E1: Reporting manager | F1: March | G1: April | H1: May | I1: June | J1: July | K1: August | L1: Sept | M1: Oct | N1: Nov | O1: Dec | P1: TOTAL | Q1: Paid Amount | R1: hold bonus
A2: 1 | B2: Mariyam | C2: 15000 | D2: 5000 | E2: Kaniz Fatema | F2: 5000 | G2: 5000 | H2: 5000 | I2: 5000 | J2: 4000 | K2: 2000 | L2: 4000 | M2: 2500 | N2: 5000 | O2: 5000 | P2: =SUM(F2:O2) -> 42500 | R2: =SUM(F2:O2) -> 42500
A3: 2 | B3: Nagma Khan | C3: 17000 | D3: 5000 | E3: Akbar sir | F3: 5000 | G3: 5000 | H3: 5000 | I3: 5000 | J3: 5000 | K3: 4500 | L3: 5000 | M3: 5000 | N3: 5000 | O3: 5000 | P3: =SUM(F3:O3) -> 49500 | R3: =SUM(F3:O3) -> 49500
A4: 3 | B4: Kaniz Fatema | C4: 25000 | D4: 5000 | E4: Avesh | F4: 5000 | G4: 5000 | H4: 5000 | I4: 5000 | J4: 5000 | K4: 5000 | L4: 5000 | M4: 5000 | N4: 5000 | O4: 5000 | P4: =SUM(F4:O4) -> 50000 | R4: =SUM(F4:O4) -> 50000
A5: 4 | B5: Shaikh Mohd Salman | C5: 10000 | D5: 5000 | E5: Kaniz Fatema | F5: 4000 | G5: 4000 | H5: 4000 | I5: 5000 | J5: 4000 | K5: 3000 | L5: 3000 | M5: 3200 | N5: 2500 | O5: 3500 | P5: =SUM(F5:O5) -> 36200 | R5: =SUM(F5:O5) -> 36200
A6: 5 | B6: Shahrukh Siddiqui | C6: 6000 | D6: 4000 | E6: Kaniz Fatema | F6: 0 | G6: 0 | H6: 0 | I6: 0 | J6: 3200 | K6: 3000 | L6: 0 | M6: 3500 | N6: 3500 | O6: 3000 | P6: =SUM(F6:O6) -> 16200 | R6: =SUM(F6:O6) -> 16200
A7: 6 | B7: Musharraf Siddiqui | C7: 25000 | D7: 5000 | E7: Akbar sir | F7: 4000 | G7: 4000 | H7: 4000 | I7: 5000 | J7: 5000 | K7: 5000 | L7: 5000 | M7: 5000 | N7: 5000 | O7: 5000 | P7: =SUM(F7:O7) -> 47000 | R7: =SUM(F7:O7) -> 47000
A8: 7 | B8: Nabeela Khan | C8: 25000 | D8: 4000 | E8: Akbar sir | F8: 4000 | G8: 4000 | H8: 4000 | I8: 4000 | J8: 4500 | K8: 5000 | L8: 5000 | M8: 5000 | N8: 5000 | O8: 5000 | P8: =SUM(F8:O8) -> 45500 | R8: =SUM(F8:O8) -> 45500
A9: 8 | B9: Rehanuddin Mohd | C9: 15000 | D9: 5000 | E9: Kaniz Fatema | F9: 4000 | G9: 4000 | H9: 4000 | I9: 4000 | J9: 3500 | K9: 3000 | L9: 4000 | M9: 5000 | N9: 4000 | O9: 5000 | P9: =SUM(F9:O9) -> 40500 | R9: =SUM(F9:O9) -> 40500
A10: 9 | B10: Shaikh Sameer | C10: 10000 | D10: 5000 | E10: Kaniz Fatema | F10: 5000 | G10: 5000 | H10: 5000 | I10: 5000 | J10: 4000 | K10: 3000 | L10: 3000 | M10: 2500 | N10: 3500 | O10: NA | P10: =SUM(F10:O10) -> 36000 | Q10: Not paid | R10: =SUM(F10:O10) -> 36000
A11: 10 | B11: Shaihk Fares | C11: 10000 | D11: 5000 | E11: Kaniz Fatema | F11: 5000 | G11: 5000 | H11: 5000 | I11: 5000 | J11: 4000 | K11: 3000 | L11: 4000 | M11: 0 | N11: 3500 | O11: 5000 | P11: =SUM(F11:O11)-Q11 -> 14500 | Q11: 25000 | R11: =SUM(F11:O11)-Q11 -> 14500
A12: 11 | B12: Aameruddin | C12: 10000 | D12: 4000 | E12: Akbar sir | F12: NA | G12: NA | H12: NA | I12: NA | J12: 4000 | K12: 4000 | L12: 2600 | M12: 3000 | N12: 0 | O12: 0 | P12: =SUM(F12:O12) -> 13600 | R12: =SUM(F12:O12) -> 13600
A13: 12 | B13: shahid quadri | C13: 16000 | D13: 4000 | E13: Kaniz Fatema | F13: 4000 | G13: 4000 | H13: 4000 | I13: 4000 | J13: 3200 | K13: 3000 | L13: 2000 | M13: 5000 | N13: 5000 | O13: 5000 | P13: =SUM(F13:O13)-Q13 -> 23200 | Q13: 16000 | R13: =SUM(F13:O13)-Q13 -> 23200
A14: 13 | B14: Sayyed Amjad | C14: 16000 | D14: 4000 | E14: Kaniz Fatema | F14: 4000 | G14: 4000 | H14: 4000 | I14: 4000 | J14: 3500 | K14: 3500 | L14: 3500 | M14: 0 | P14: =SUM(F14:O14) -> 26500 | Q14: =P14 -> 26500 | R14: =SUM(F14:O14)-Q14 -> 0
A15: 14 | B15: Mustaqueem | C15: 16000 | D15: 4000 | E15: Akbar sir | F15: NA | G15: NA | H15: NA | I15: NA | J15: 4000 | K15: 4000 | L15: 4000 | M15: 4000 | N15: 4000 | O15: 4000 | P15: =SUM(F15:O15) -> 24000 | R15: =SUM(F15:O15) -> 24000
A16: 15 | B16: Irteqaz ahmed | C16: 12000 | D16: 4000 | E16: Akbar sir | F16: NA | G16: NA | H16: NA | I16: NA | J16: 4000 | K16: 3000 | L16: 2800 | M16: 0 | P16: =SUM(F16:O16) -> 9800 | Q16: =P16 -> 9800 | R16: =SUM(F16:O16)-Q16 -> 0
A17: 16 | B17: Shaikh Saifullah | C17: 10000 | D17: 4000 | E17: Kaniz Fatema | F17: NA | G17: NA | H17: NA | I17: 4000 | J17: 4000 | K17: 3000 | L17: 3500 | M17: 3500 | N17: 3000 | O17: 4000 | P17: =SUM(F17:O17) -> 25000 | R17: =SUM(F17:O17) -> 25000
A18: 17 | B18: Shah Alam | C18: 6000 | D18: 6000 | E18: Akbar sir | F18: NA | G18: NA | H18: NA | I18: 6000 | J18: 6000 | K18: 6000 | L18: 6000 | M18: 6000 | N18: 6000 | O18: 6000 | P18: =SUM(F18:O18)-Q18 -> 0 | Q18: =SUM(I18:O18) -> 42000 | R18: =SUM(F18:O18)-Q18 -> 0
A19: 18 | B19: Shamshad | C19: 6000 | D19: 3000 | E19: Akbar sir | F19: NA | G19: NA | H19: NA | I19: NA | J19: NA | K19: NA | L19: NA | M19: NA | N19: 2000 | O19: 2000 | P19: =SUM(F19:O19) -> 4000 | R19: =SUM(F19:O19) -> 4000
A20: 19 | B20: Shaikh Tareq | C20: 6000 | D20: 5000 | E20: Akbar sir | L20: 2000 | M20: 2500 | N20: 3000 | O20: 3000 | P20: =SUM(F20:O20) -> 10500 | R20: =SUM(F20:O20) -> 10500
A21: 20 | B21: Vasim Shaikh | C21: 6000 | D21: 4000 | E21: Akbar sir | M21: 3000 | N21: 2500 | O21: 0 | P21: =SUM(F21:O21) -> 5500 | R21: =SUM(F21:O21) -> 5500
J23: =P13-Q13 -> 7200 | N23: TOTAL | P23: =SUM(P2:P21) -> 520000
C25: Paid with salary
C26: Paid in advance
C27: Paid Total amount
B28: Not applicable for this month | C28: NA

Sheet 2020
A1: Sr No | C1: Technology | D1: Salary | E1: Bonus amount | F1: Reporting manager | G1: Jan | H1: Feb | I1: Mar | J1: Apr | K1: May | L1: Jun | M1: Jul | N1: Aug | O1: Sep | P1: Oct | Q1: Nov | R1: Dec | S1: This year 2020 | T1: Previous year 2019 total | U1: TOTAL | V1: 2 Months salary | W1: Yearly Permissible Bonus amount | X1: Paid Amount | Y1: To be Paid with Salary in May | Z1: To be Paid with Salary in June | AA1: To be Paid with Salary in July | AB1: To be Paid with Salary in August | AC1: To be Paid with Salary in September | AD1: To be Paid with Salary in October | AE1: To be Paid with Salary in November | AF1: To be Paid with Salary in December | AG1: Total bonus given in 2020 amount | AH1: Remaining Bonus amount in dec 2020
A2: 1 | B2: Mariyam | C2: Salesforce | D2: 20000 | E2: 10000 | F2: Kaniz Fatema | G2: 5000 | H2: 5000 | I2: 4500 | J2: 4000 | K2: 3000 | L2: 0 | M2: 3000 | N2: 3500 | O2: 0 | P2: 7000 | Q2: 7000 | R2: 7000 | S2: =SUM(G2:R2) -> 49000 | T2: ='2019'!P2 -> 42500 | U2: =S2+T2 -> 91500 | V2: =D2*2 -> 40000 | W2: =U2-V2 -> 51500 | Y2: 3000 | Z2: 0 | AA2: 3000 | AB2: =N2 -> 3500 | AC2: =O2 -> 0 | AD2: =P2 -> 7000 | AE2: =Q2 -> 7000 | AF2: =R2 -> 7000 | AG2: =SUM(Y2:AF2) -> 30500 | AH2: =W2-AG2 -> 21000
A3: 2 | B3: Kaniz Fatema | C3: Salesforce | D3: 30000 | E3: 5000 | F3: Akbar sir | G3: 5000 | H3: 5000 | I3: 5000 | J3: 5000 | K3: 5000 | L3: 5000 | M3: 5000 | N3: 5000 | O3: 2500 | P3: 5000 | Q3: 5000 | R3: 5000 | S3: =SUM(G3:R3) -> 57500 | T3: ='2019'!P4 -> 50000 | U3: =S3+T3 -> 107500 | V3: =D3*2 -> 60000 | W3: =U3-V3 -> 47500 | Y3: 5000 | Z3: 5000 | AA3: 5000 | AB3: =N3 -> 5000 | AC3: =O3 -> 2500 | AD3: =P3 -> 5000 | AE3: =Q3 -> 5000 | AF3: =R3 -> 5000 | AG3: =SUM(Y3:AF3) -> 37500 | AH3: =W3-AG3 -> 10000
A4: 3 | B4: Sayyed Manzar Ali | C4: Uipath | D4: 20000 | E4: 10000 | F4: Akbar sir | G4: NA | H4: NA | I4: 4000 | J4: 4000 | K4: 4000 | L4: 4000 | M4: 4000 | N4: 4000 | O4: 4000 | P4: 4000 | Q4: 10000 | R4: 10000 | S4: =SUM(G4:R4) -> 52000 | T4: 0 | U4: =S4+T4 -> 52000 | V4: =D4*2 -> 40000 | W4: =U4-V4 -> 12000 | Y4: NA | Z4: 0 | AA4: 0 | AB4: 0 | AC4: 0 | AF4: =R4 -> 10000 | AG4: =SUM(Y4:AF4) -> 10000 | AH4: =W4-AG4 -> 2000
A5: 4 | B5: Zeeshan Sayyed | C5: OIC | D5: 10000 | E5: 2000 | F5: Akbar sir | G5: NA | H5: 0 | I5: 0 | J5: 0 | L5: 2000 | M5: 2000 | N5: 2000 | O5: 0 | P5: 2000 | Q5: 2000 | R5: 2000 | S5: =SUM(G5:R5) -> 12000 | T5: 0 | U5: =S5+T5 -> 12000 | V5: =D5*2 -> 20000 | W5: =U5-V5 -> -8000 | Y5: NA | Z5: 0 | AA5: 0 | AB5: 0 | AC5: =O5 -> 0 | AG5: =SUM(Y5:AF5) -> 0 | AH5: =S5 -> 12000
A6: 5 | B6: Shah Alam | C6: Web development | D6: 15000 | E6: 10000 | F6: Akbar sir | G6: 6000 | H6: 6000 | I6: 6000 | J6: 3000 | K6: 3000 | L6: 3000 | M6: 5000 | N6: 5000 | O6: 5000 | P6: 5000 | Q6: 8000 | R6: 8000 | S6: =SUM(G6:R6) -> 63000 | T6: 0 | U6: =S6+T6 -> 63000 | V6: =D6*2 -> 30000 | W6: =U6-V6 -> 33000 | X6: =SUM(G6:H6)+J6+K6 -> 18000 | Y6: 3000 | Z6: 0 | AA6: 0 | AB6: =N6 -> 5000 | AC6: =O6 -> 5000 | AD6: =P6 -> 5000 | AE6: =Q6 -> 8000 | AF6: =R6 -> 8000 | AG6: =SUM(Y6:AF6) -> 34000 | AH6: =W6-AG6 -> -1000
A7: 6 | B7: Sayyed Haider | C7: SharePoint | D7: 10000 | E7: 10000 | F7: Akbar sir | G7: NA | H7: 4000 | I7: 4000 | J7: 2000 | K7: 4000 | L7: 4000 | M7: 4000 | N7: 4000 | O7: 2000 | P7: 3000 | Q7: 10000 | R7: 10000 | S7: =SUM(G7:R7) -> 51000 | T7: 0 | U7: =S7+T7 -> 51000 | V7: =D7*2 -> 20000 | W7: =U7-V7 -> 31000 | Y7: NA | Z7: 0 | AA7: 0 | AB7: =N7 -> 4000 | AC7: =O7 -> 2000 | AD7: =P7 -> 3000 | AE7: =Q7 -> 10000 | AF7: =R7 -> 10000 | AG7: =SUM(Y7:AF7) -> 29000 | AH7: =W7-AG7 -> 2000
A8: 7 | B8: Saba Shaikh | C8: SharePoint | D8: 10000 | E8: 10000 | F8: Akbar sir | G8: NA | H8: 4000 | I8: 4000 | J8: 2000 | K8: 4000 | L8: 4000 | M8: 4000 | N8: 4000 | O8: 4000 | P8: 4000 | Q8: 10000 | R8: 5000 | S8: =SUM(G8:R8) -> 49000 | T8: 0 | U8: =S8+T8 -> 49000 | V8: =D8*2 -> 20000 | W8: =U8-V8 -> 29000 | Y8: NA | Z8: 0 | AA8: 0 | AB8: 0 | AC8: =O8 -> 4000 | AD8: =P8 -> 4000 | AE8: =Q8 -> 10000 | AF8: =R8 -> 5000 | AG8: =SUM(Y8:AF8) -> 23000 | AH8: =W8-AG8 -> 6000
A9: 8 | B9: Shahrukh Siddiqui | C9: Salesforce | D9: 15000 | E9: 10000 | F9: Kaniz Fatema | G9: 4000 | H9: 3000 | I9: 3000 | J9: 4000 | K9: 3000 | L9: 3000 | M9: 3000 | N9: 2000 | O9: 7500 | P9: 6000 | Q9: 7000 | R9: 7000 | S9: =SUM(G9:R9) -> 52500 | T9: ='2019'!P6 -> 16200 | U9: =S9+T9 -> 68700 | V9: =D9*2 -> 30000 | W9: =U9-V9 -> 38700 | Y9: 3000 | Z9: 3000 | AA9: 3000 | AB9: =N9 -> 2000 | AC9: =O9 -> 7500 | AD9: =P9 -> 6000 | AE9: =Q9 -> 7000 | AF9: =R9 -> 7000 | AG9: =SUM(Y9:AF9) -> 38500 | AH9: =W9-AG9 -> 200
A10: 9 | B10: Shamshad Ahmed | C10: Qliksense | D10: 16000 | E10: 5000 | F10: Akbar sir | G10: 4000 | H10: 0 | I10: 0 | J10: 3000 | K10: 3000 | L10: 4000 | M10: 3000 | N10: =4000+5000 -> 9000 | O10: 4000 | P10: 5000 | Q10: 5000 | R10: 5000 | S10: =SUM(G10:R10) -> 45000 | T10: ='2019'!P19 -> 4000 | U10: =S10+T10 -> 49000 | V10: =D10*2 -> 32000 | W10: =U10-V10 -> 17000 | Y10: NA | Z10: 0 | AA10: 0 | AB10: 4000 | AC10: =O10 -> 4000 | AD10: =P10 -> 5000 | AE10: =Q10 -> 5000 | AF10: =R10 -> 5000 | AG10: =SUM(Y10:AF10) -> 23000 | AH10: =W10-AG10 -> -6000
A11: 10 | B11: Musharrafuddin Siddiqui | C11: Web development | D11: 25000 | E11: 10000 | F11: Akbar sir | G11: 5000 | H11: 2000 | I11: 2000 | J11: 5000 | K11: 5000 | L11: 5000 | M11: 5000 | N11: 5000 | O11: 5000 | P11: 5000 | Q11: 4000 | R11: 0 | S11: =SUM(G11:R11) -> 48000 | T11: ='2019'!P7 -> 47000 | U11: =S11+T11 -> 95000 | V11: =D11*2 -> 50000 | W11: =U11-V11 -> 45000 | Y11: 5000 | Z11: 5000 | AA11: 5000 | AB11: =N11 -> 5000 | AC11: =O11 -> 5000 | AD11: =P11 -> 5000 | AE11: =Q11 -> 4000 | AG11: =SUM(Y11:AF11) -> 34000 | AH11: =W11-AG11 -> 11000
A12: 11 | B12: Shahid Qadri | C12: Salesforce | D12: 25000 | E12: 10000 | F12: Kaniz Fatema | G12: 5000 | H12: 5000 | I12: 4500 | J12: 5000 | K12: 5000 | L12: 1000 | M12: 4000 | N12: 5000 | O12: 8500 | P12: 9000 | Q12: 10000 | R12: 10000 | S12: =SUM(G12:R12) -> 72000 | T12: ='2019'!P13 -> 23200 | U12: =S12+T12 -> 95200 | V12: =D12*2 -> 50000 | W12: =U12-V12 -> 45200 | X12: 16000 | Y12: 5000 | Z12: 1000 | AA12: 4000 | AB12: =N12 -> 5000 | AC12: =O12 -> 8500 | AD12: =P12 -> 9000 | AE12: =Q12 -> 10000 | AF12: =R12 -> 10000 | AG12: =SUM(Y12:AF12) -> 52500 | AH12: =W12-AG12 -> -7300
A13: 12 | B13: Nabeela khan | C13: Microsoft CRM | D13: 25000 | E13: 10000 | F13: Akbar sir | G13: 3000 | H13: 0 | I13: 0 | J13: 3000 | K13: 5000 | L13: 5000 | M13: 5000 | N13: 5000 | O13: 5000 | P13: 5000 | Q13: 10000 | R13: 10000 | S13: =SUM(G13:R13) -> 56000 | T13: ='2019'!P8 -> 45500 | U13: =S13+T13 -> 101500 | V13: =D13*2 -> 50000 | W13: =U13-V13 -> 51500 | Y13: 5000 | Z13: 5000 | AA13: 5000 | AB13: =N13 -> 5000 | AC13: =O13 -> 5000 | AD13: =P13 -> 5000 | AE13: =Q13 -> 10000 | AF13: =R13 -> 10000 | AG13: =SUM(Y13:AF13) -> 50000 | AH13: =W13-AG13 -> 1500
A14: 13 | B14: Mohammad Rehanuddin | C14: Salesforce | D14: 25000 | E14: 10000 | F14: Kaniz Fatema | G14: 5000 | H14: 5000 | I14: 4500 | J14: 5000 | K14: 5000 | L14: 4000 | M14: 5000 | N14: 5000 | O14: 5000 | P14: 9000 | Q14: 8000 | R14: 9000 | S14: =SUM(G14:R14) -> 69500 | T14: ='2019'!P9 -> 40500 | U14: =S14+T14 -> 110000 | V14: =D14*2 -> 50000 | W14: =U14-V14 -> 60000 | Y14: 5000 | Z14: 4000 | AA14: 5000 | AB14: =N14 -> 5000 | AC14: =O14 -> 5000 | AD14: =P14 -> 9000 | AE14: =Q14 -> 8000 | AF14: =R14 -> 9000 | AG14: =SUM(Y14:AF14) -> 50000 | AH14: =W14-AG14 -> 10000
A15: 14 | B15: Shaikh Tareq | C15: Eautomate | D15: 15000 | E15: 5000 | F15: Akbar sir | G15: 3000 | H15: 3000 | I15: 3000 | J15: 3000 | K15: 3000 | L15: 5000 | M15: =5000+0 -> 5000 | N15: 2000 | O15: 2000 | P15: 5000 | Q15: 5000 | R15: 5000 | S15: =SUM(G15:R15) -> 44000 | T15: ='2019'!P20 -> 10500 | U15: =S15+T15 -> 54500 | V15: =D15*2 -> 30000 | W15: =U15-V15 -> 24500 | Y15: 3000 | Z15: 5000 | AA15: =M15 -> 5000 | AB15: =N15 -> 2000 | AC15: =O15 -> 2000 | AD15: =P15 -> 5000 | AE15: =Q15 -> 5000 | AF15: =R15 -> 5000 | AG15: =SUM(Y15:AF15) -> 32000 | AH15: =W15-AG15 -> -7500
A16: 15 | B16: Sohel Shaikh | C16: Microsoft CRM | D16: 6000 | E16: 10000 | F16: Akbar sir | G16: 0 | H16: 0 | I16: 0 | J16: 0 | K16: 0 | L16: 4000 | M16: 10000 | N16: 10000 | O16: 10000 | P16: 10000 | Q16: 10000 | R16: 10000 | S16: =SUM(G16:R16) -> 64000 | T16: 0 | U16: =S16+T16 -> 64000 | V16: =D16*2 -> 12000 | W16: =U16-V16 -> 52000 | Y16: NA | Z16: 0 | AA16: =M16 -> 10000 | AB16: =N16 -> 10000 | AC16: =O16 -> 10000 | AD16: =P16 -> 10000 | AE16: =Q16 -> 10000 | AF16: =R16 -> 10000 | AG16: =SUM(Y16:AF16) -> 60000 | AH16: =W16-AG16 -> -8000
A17: 16 | B17: Irfan Shaikh | C17: Microsoft CRM | D17: 10000 | E17: 4000 | F17: Akbar sir | G17: NA | H17: NA | I17: 4000 | J17: 4000 | K17: 0 | L17: 4000 | M17: 4000 | N17: 2000 | O17: 4000 | P17: 2000 | Q17: 2000 | R17: 4000 | S17: =SUM(G17:R17) -> 30000 | T17: 0 | U17: =S17+T17 -> 30000 | V17: =D17*2 -> 20000 | W17: =U17-V17 -> 10000 | Z17: 4000 | AA17: 20000 | AB17: 0 | AC17: 0 | AF17: =R17 -> 4000 | AG17: =SUM(Y17:AF17) -> 28000 | AH17: =N17+P17+Q17 -> 6000
A18: 17 | B18: Waseem Mohammad | C18: Web development | D18: 6000 | E18: 6000 | F18: Akbar sir | G18: NA | H18: NA | I18: NA | J18: NA | K18: NA | L18: NA | M18: 6000 | N18: 6000 | O18: 5000 | P18: 6000 | Q18: 6000 | R18: 6000 | S18: =SUM(G18:R18) -> 35000 | T18: 0 | U18: =S18+T18 -> 35000 | V18: =D18*2 -> 12000 | W18: =U18-V18 -> 23000 | Z18: 0 | AA18: 0 | AB18: 0 | AC18: =O18 -> 5000 | AD18: =P18 -> 6000 | AE18: =Q18 -> 6000 | AF18: =R18 -> 6000 | AG18: =SUM(Y18:AF18) -> 23000 | AH18: =W18-AG18 -> 0
A19: 18 | B19: Nagma Khan | C19: SharePoint | D19: 17000 | E19: 10000 | F19: Akbar sir | G19: NA | H19: NA | I19: NA | J19: NA | K19: NA | L19: NA | M19: 5000 | N19: 5000 | O19: 5000 | P19: 5000 | Q19: 10000 | R19: 10000 | S19: =SUM(M19:R19) -> 40000 | T19: ='2019'!P3 -> 49500 | U19: =S19+T19 -> 89500 | V19: =D19*2 -> 34000 | W19: =U19-V19 -> 55500 | Z19: 0 | AA19: 0 | AB19: 0 | AC19: =O19 -> 5000 | AG19: =SUM(Y19:AF19) -> 5000 | AH19: =W19-AG19 -> 50500
A20: 19 | B20: Shaikh Mudassir | C20: E-automate | D20: 6000 | E20: 6000 | F20: Akbar sir | G20: NA | H20: NA | I20: NA | J20: NA | K20: NA | L20: NA | M20: =3000+1650 -> 4650 | N20: =3000+3000 -> 6000 | O20: =6000+3000 -> 9000 | P20: =3000+3000 -> 6000 | Q20: 6000 | R20: 6000 | S20: =SUM(G20:R20) -> 37650 | T20: 0 | U20: =S20+T20 -> 37650 | V20: =D20*2 -> 12000 | W20: =U20-V20 -> 25650 | Z20: 0 | AA20: 0 | AB20: 0 | AC20: =O20 -> 9000 | AD20: 3000 | AE20: =Q20 -> 6000 | AF20: =R20 -> 6000 | AG20: =SUM(Y20:AF20) -> 24000 | AH20: =S20-AG20 -> 13650 | AI20: =V20+AH20 -> 25650
A21: 20 | B21: Shaikh Javed | C21: E-automate | D21: 6000 | E21: 6000 | F21: Akbar sir | G21: NA | H21: NA | I21: NA | J21: NA | K21: NA | L21: NA | M21: =3000+1800 -> 4800 | N21: =3000+3000 -> 6000 | O21: =6000+3000 -> 9000 | P21: =3000+3000 -> 6000 | Q21: 6000 | R21: 6000 | S21: =SUM(G21:R21) -> 37800 | T21: 0 | U21: =S21+T21 -> 37800 | V21: =D21*2 -> 12000 | W21: =U21-V21 -> 25800 | Z21: 0 | AA21: 0 | AC21: =O21 -> 9000 | AD21: 3000 | AE21: =E21 -> 6000 | AF21: =R21 -> 6000 | AG21: =SUM(Y21:AF21) -> 24000 | AH21: =S21-AG21 -> 13800 | AI21: =V21-AH21 -> -1800
A22: 21 | B22: Mustaqeem | C22: Salesforce | D22: 20000 | E22: 5000 | F22: Akbar sir | G22: NA | H22: NA | I22: NA | J22: NA | K22: NA | L22: NA | M22: NA | N22: 3000 | O22: 4000 | P22: 5000 | Q22: 5000 | R22: 5000 | S22: =SUM(G22:R22) -> 22000 | T22: ='2019'!P15 -> 24000 | U22: =S22+T22 -> 46000 | V22: =D22*2 -> 40000 | W22: =U22-V22 -> 6000 | Z22: 0 | AA22: 0 | AB22: 0 | AC22: 0 | AG22: =SUM(Y22:AF22) -> 0 | AH22: =W22-AG22 -> 6000
A23: 22 | B23: Maaz Shaokat Choughle | C23: Salesforce | D23: 12000 | E23: 4000 | F23: Akbar sir | G23: NA | H23: NA | I23: NA | J23: NA | K23: NA | L23: NA | M23: NA | N23: NA | O23: 2500 | P23: 4000 | Q23: 3000 | R23: 4000 | S23: =SUM(G23:R23) -> 13500 | T23: 0 | U23: =S23+T23 -> 13500 | V23: =D23*2 -> 24000 | W23: =U23-V23 -> -10500 | Z23: 0 | AA23: 0 | AC23: 0 | AG23: =SUM(Y23:AF23) -> 0 | AH23: =W23-AG23 -> -10500
A24: 23 | B24: Sohail Inamdar | C24: Salesforce | D24: 12000 | E24: 4000 | F24: Akbar sir | G24: NA | H24: NA | I24: NA | J24: NA | K24: NA | L24: NA | M24: NA | N24: NA | O24: 3000 | P24: 2500 | Q24: 3000 | R24: 3000 | S24: =SUM(G24:R24) -> 11500 | T24: 0 | U24: =S24+T24 -> 11500 | V24: =D24*2 -> 24000 | W24: =U24-V24 -> -12500 | Z24: 0 | AA24: 0 | AC24: 0 | AG24: =SUM(Y24:AF24) -> 0 | AH24: =S24 -> 11500
A25: 24 | B25: Ansari Mohd Ateef | C25: Salesforce | D25: 12000 | E25: 4000 | F25: Akbar sir | G25: NA | H25: NA | I25: NA | J25: NA | K25: NA | L25: NA | M25: NA | N25: NA | O25: 2500 | P25: 1500 | Q25: 2600 | R25: 3000 | S25: =SUM(G25:R25) -> 9600 | T25: 0 | U25: =S25+T25 -> 9600 | V25: =D25*2 -> 24000 | W25: =U25-V25 -> -14400 | Z25: 0 | AA25: 0 | AC25: 0 | AG25: =SUM(Y25:AF25) -> 0 | AH25: =S25 -> 9600
A26: 25 | B26: Tarekh Shaikh | C26: Salesforce | D26: 6000 | E26: 4000 | F26: Akbar sir | G26: NA | H26: NA | I26: NA | J26: NA | K26: NA | L26: NA | M26: NA | N26: NA | O26: 1000 | P26: 0 | Q26: 1500 | R26: 2000 | S26: =SUM(G26:R26) -> 4500 | T26: 0 | U26: =S26+T26 -> 4500 | V26: =D26*2 -> 12000 | W26: =U26-V26 -> -7500 | Z26: 0 | AA26: 0 | AC26: =O26 -> 1000 | AG26: =SUM(Y26:AF26) -> 1000 | AH26: =W26-AG26 -> -8500
A27: 26 | B27: Zubair Shaikh | C27: E- Commerce | D27: 6000 | E27: 6000 | F27: Akbar sir | G27: NA | H27: NA | I27: NA | J27: NA | K27: NA | L27: NA | M27: NA | N27: NA | O27: NA | P27: 6000 | Q27: 4000 | S27: =SUM(G27:R27) -> 10000 | T27: 0 | U27: =S27+T27 -> 10000 | V27: =D27*2 -> 12000 | W27: =U27-V27 -> -2000 | Z27: 0 | AA27: 0 | AG27: =SUM(Y27:AF27) -> 0 | AH27: =W27-AG27 -> -2000
A28: 27 | B28: Muqtadir Khan | C28: Qliksense | D28: 6000 | E28: 6000 | F28: Akbar sir | G28: NA | H28: NA | I28: NA | J28: NA | K28: NA | L28: NA | M28: NA | N28: NA | O28: NA | P28: 6000 | Q28: 6000 | R28: 6000 | S28: =SUM(G28:R28) -> 18000 | T28: 0 | U28: =S28+T28 -> 18000 | V28: =D28*2 -> 12000 | W28: =U28-V28 -> 6000 | Z28: 0 | AA28: 0 | AF28: =R28 -> 6000 | AG28: =SUM(Y28:AF28) -> 6000 | AH28: =W28-AG28 -> 0
A29: 28 | B29: Adil Khan | C29: Salesforce | D29: 12000 | E29: 4000 | F29: Kaniz Fatema | G29: NA | H29: NA | I29: NA | J29: NA | K29: NA | L29: NA | M29: NA | N29: NA | O29: NA | P29: NA | Q29: 2500 | R29: 2000 | S29: =SUM(G29:R29) -> 4500 | T29: 0 | U29: =S29+T29 -> 4500 | V29: =D29*2 -> 24000 | W29: =U29-V29 -> -19500 | AG29: =SUM(Y29:AF29) -> 0 | AH29: =W29-AG29 -> -19500
A30: 29 | B30: Mohsin Mohd | C30: OIC | D30: 12000 | E30: 8000 | F30: Akbar sir | G30: NA | H30: NA | I30: NA | J30: NA | K30: NA | L30: NA | M30: NA | N30: NA | O30: NA | P30: NA | Q30: 8000 | R30: 8000 | S30: =SUM(G30:R30) -> 16000 | T30: 0 | U30: =S30+T30 -> 16000 | V30: =D30*2 -> 24000 | W30: =U30-V30 -> -8000 | AG30: =SUM(Y30:AF30) -> 0 | AH30: =S30 -> 16000
A31: 30 | B31: Faizan | C31: Salesforce | D31: 20000 | E31: 5000 | F31: kaniz Fatema | G31: NA | H31: NA | I31: NA | J31: NA | K31: NA | L31: NA | M31: NA | N31: NA | O31: NA | P31: NA | Q31: NA | R31: 3000 | S31: =SUM(G31:R31) -> 3000 | T31: 0 | U31: =S31+T31 -> 3000 | V31: =D31*2 -> 40000 | W31: =U31-V31 -> -37000 | AG31: =SUM(Y31:AF31) -> 0 | AH31: =W31-AG31 -> -37000
D32: =SUM(D2:D31) -> 430000 | E32: =SUM(E2:E31) -> 209000 | F32: =SUM(F2:F30) -> 0 | G32: =SUM(G2:G30) -> 45000 | H32: =SUM(H2:H30) -> 42000 | I32: =SUM(I2:I30) -> 48500 | J32: =SUM(J2:J30) -> 52000 | K32: =SUM(K2:K30) -> 52000 | L32: =SUM(L2:L30) -> 57000 | M32: =SUM(M2:M30) -> 91450 | ... Q32: =SUM(Q2:Q30) -> 176600 | R32: =SUM(R2:R31) -> 171000 | S32: =SUM(S2:S30) -> 1074550 | T32: =SUM(T2:T30) -> 352900 | U32: =SUM(U2:U30) -> 1427450 | V32: =SUM(V2:V31) -> 860000 | W32: =SUM(W2:W30) -> 607450 | X32: =SUM(X2:X30) -> 34000 | Y32: =SUM(Y2:Y30) -> 37000 | Z32: =SUM(Z2:Z30) -> 32000 | AA32: =SUM(AA2:AA30) -> 65000 | AB32: =SUM(AB2:AB30) -> 55500 | AC32: =SUM(AC2:AC30) -> 89500 | AD32: =SUM(AD2:AD30) -> 90000 | ... AH32: =SUM(AH2:AH30) -> 132450
D33: Paid with salary
D34: Paid in advance
D35: Paid Total amount
F42: 69500 | G42: 108000
F43: 25000 | G43: =F42+F43-(G42) -> -13500
F44: 40500

Sheet 2021
A1: Sr No | B1: Name of the Employee | C1: Technology | D1: Salary | E1: Bonus amount | F1: Reporting manager | G1: Jan | H1: Feb | I1: Mar | J1: Apr | K1: May | L1: Jun | M1: Jul | N1: Aug | O1: Sep | P1: Oct | Q1: Nov | R1: Dec | S1: This year 2021 bonus amount | T1: Previous year 2020 total bonus amount | U1: Total Bonus Amount | V1: 2 Months salary on hold | W1: Total bonus amount pay after notice period | Y1: To be Paid with Salary in Jan 2021 | Z1: To be Paid with Salary in Feb 2021 | AA1: To be Paid with Salary in Mar 2021 | AB1: To be Paid with Salary in Apr 2021 | AC1: To be Paid with Salary in May 2021 | AD1: To be Paid with Salary in Jun 2021 | AE1: To be Paid with Salary in July 2021 | AF1: To be Paid with Salary in Aug 2021 | AG1: To be Paid with Salary in Sep 2021 | AH1: To be Paid with Salary in Oct 2021 | AI1: To be Paid with Salary in Nov 2021 | AJ1: To be Paid with Salary in Dec 2021 | AK1: Total bonus given in 2021 amount | AL1: Remaining Bonus amount in dec 2021
A2: 1 | B2: Yasmeen | C2: Accountant | D2: 10000 | E2: 5000 | F2: Akbar sir | G2: 3000 | H2: 4000 | I2: 4000 | J2: 4000 | K2: 5000 | L2: 4000 | M2: 3000 | N2: 0 | O2: 4000 | P2: 4000 | Q2: 2000 | R2: 4000 | S2: =SUM(G2:R2) -> 41000 | T2: 0 | U2: 30500 | V2: 20000 | W2: 20000 | Y2: 0 | Z2: 0 | AA2: 0 | AB2: 0 | AC2: 0 | AD2: 4000 | AE2: 3000 | AF2: 0 | AG2: =O2 -> 4000 | AH2: =P2 -> 4000 | AI2: =Q2 -> 2000 | AJ2: =R2 -> 4000 | AK2: =SUM(Y2:AJ2) -> 21000 | AL2: 23500
A3: 2 | B3: Sherkhan Misbah ismail | C3: Accountant | D3: 10000 | E3: 5000 | F3: Akbar sir | G3: NA | H3: NA | I3: NA | J3: NA | K3: NA | L3: NA | M3: NA | N3: NA | O3: 4000 | P3: 5000 | Q3: 4000 | R3: =E3/22*9 -> 2045.4545 | S3: =SUM(G3:R3) -> 15045.455 | AG3: 0 | AH3: 0 | AI3: 0 | AJ3: 0 | AK3: =SUM(Y3:AJ3) -> 0
A4: 3 | B4: Imran | C4: Angular | D4: 12000 | E4: 6000 | F4: Akbar sir | G4: NA | H4: NA | I4: NA | J4: NA | K4: NA | L4: 6000 | M4: 6000 | N4: 6000 | O4: 6000 | P4: 6000 | Q4: 6000 | R4: 6000 | S4: =SUM(G4:R4) -> 42000 | V4: 12000 | AD4: 0 | AE4: 0 | AF4: 6000 | AG4: =O4 -> 6000 | AH4: 0 | AI4: 0 | AJ4: =R4 -> 6000 | AK4: =SUM(Y4:AJ4) -> 18000
A5: 4 | B5: Younus | C5: Angular | D5: 12000 | E5: 4000 | F5: Akbar sir | G5: NA | H5: NA | I5: NA | J5: NA | K5: NA | L5: NA | M5: NA | N5: NA | O5: 4000 | P5: 4000 | Q5: 0 | R5: 4000 | S5: =SUM(G5:R5) -> 12000 | AG5: 0 | AH5: 0 | AI5: 0 | AJ5: 0
A6: 6 | B6: Shaikh Tareq | C6: Dot Net | D6: 25000 | E6: 5000 | F6: Akbar sir | G6: 5000 | H6: 5000 | I6: 5000 | J6: 5000 | K6: 5000 | L6: 5000 | M6: 5000 | N6: 5000 | O6: 5000 | P6: 5000 | Q6: 5000 | R6: =E6/22*7 -> 1590.9091 | S6: =SUM(G6:R6) -> 56590.909 | T6: 0 | U6: 45000 | V6: 50000 | W6: 50000 | Y6: 5000 | Z6: 5000 | AA6: 5000 | AB6: 5000 | AC6: 0 | AD6: 0 | AE6: 5000 | AF6: 5000 | AI6: 0 | AJ6: 0 | AK6: 30000 | AL6: 15000
A7: 7 | B7: Osama | C7: Dot Net | D7: 18000 | E7: 6000 | F7: Akbar sir | G7: NA | H7: 6000 | I7: 6000 | J7: 6000 | K7: 6000 | L7: 6000 | M7: 6000 | N7: 6000 | O7: 6000 | P7: 6000 | Q7: 6000 | R7: =E7/22*7 -> 1909.0909 | S7: =SUM(G7:R7) -> 61909.091 | T7: 0 | U7: =S7+T7 -> 61909.091 | V7: =D7*2 -> 36000 | W7: =U7-V7 -> 25909.091 | Y7: 0 | Z7: 0 | AA7: 0 | AB7: 6000 | AC7: 6000 | AD7: 6000 | AE7: 6000 | AF7: 6000 | AG7: 0 | AH7: 0 | AI7: 0 | AJ7: 10000 | AK7: =SUM(Y7:AJ7) -> 40000 | AL7: =S7-AK7 -> 21909.091
A8: 8 | B8: Salman | C8: Dot Net | D8: 12000 | E8: 6000 | F8: Akbar sir | G8: 6000 | H8: 4000 | I8: 4000 | J8: 6000 | K8: 5000 | L8: 6000 | M8: 6000 | N8: 6000 | O8: 6000 | P8: 6000 | Q8: 6000 | R8: 6000 | S8: =SUM(G8:R8) -> 67000 | T8: 0 | U8: =S8+T8 -> 67000 | V8: =D8*2 -> 24000 | W8: =U8-V8 -> 43000 | Z8: 0 | AA8: 0 | AB8: 6000 | AC8: 5000 | AD8: 6000 | AE8: 6000 | AF8: 6000 | AG8: 0 | AH8: 0 | AI8: =Q8 -> 6000 | AJ8: =R8 -> 6000
A9: 9 | B9: Arshaduddin | C9: Dot Net | D9: 12000 | E9: 6000 | F9: Akbar sir | G9: NA | H9: NA | I9: 3000 | J9: 4000 | K9: 5000 | L9: 6000 | M9: 6000 | N9: 6000 | O9: 6000 | P9: =E9/20*15 -> 4500 | Q9: 6000 | R9: 6000 | S9: =SUM(G9:R9) -> 52500 | T9: 0 | U9: =S9+T9 -> 52500 | V9: =D9*2 -> 24000 | W9: =U9-V9 -> 28500 | Z9: 0 | AA9: 0 | AB9: 0 | AC9: 0 | AD9: 6000 | AE9: 6000 | AF9: 6000 | AG9: 0 | AH9: 0 | AI9: 0 | AJ9: 6000
A10: 10 | B10: Nagma Khan | C10: Dot Net | D10: 17000 | E10: 10000 | F10: Akbar sir | G10: 10000 | H10: 10000 | I10: 4000 | J10: 0 | K10: 0 | L10: 0 | M10: 0 | N10: 0 | O10: =E10/23*11 -> 4782.6087 | P10: =E10/21*6 -> 2857.1429 | Q10: 10000 | R10: 10000 | S10: 29000 | T10: -6000 | U10: 23000 | V10: 34000 | W10: 28000 | Y10: 10000 | Z10: 10000 | AA10: 4000 | AB10: 0 | AC10: 0 | AD10: 0 | AH10: =P10 -> 2857.1429 | AI10: =Q10 -> 10000 | AJ10: =R10 -> 10000 | AK10: 24000 | AL10: -1000
A11: 11 | B11: Muzafar | C11: Dot Net | D11: 12000 | E11: 6000 | F11: Akbar sir | G11: NA | H11: NA | I11: NA | J11: 6000 | K11: 6000 | L11: 6000 | M11: 6000 | N11: 6000 | O11: 6000 | P11: 6000 | Q11: 6000 | R11: 6000 | S11: =SUM(G11:R11) -> 54000 | U11: 0 | V11: 24000 | AB11: 0 | AC11: 0 | AD11: 0 | AE11: 0 | AF11: 6000 | AG11: =O11 -> 6000 | AH11: =P11 -> 6000 | AI11: =Q11 -> 6000 | AJ11: =R11 -> 6000
A12: 12 | B12: Shaikh Mudassir | C12: E-automate | D12: 18000 | E12: 6000 | F12: Akbar sir | G12: 6000 | H12: 6000 | I12: 6000 | J12: 6000 | K12: 5000 | L12: 5000 | M12: 5000 | N12: 6000 | O12: 6000 | P12: 6000 | Q12: 6000 | R12: 6000 | S12: =SUM(G12:R12) -> 69000 | T12: 10650 | U12: =S12+T12 -> 79650 | V12: =D12*2 -> 36000 | W12: =U12-V12 -> 43650 | Y12: 6000 | Z12: 0 | AA12: 6000 | AB12: 6000 | AC12: 0 | AD12: 0 | AE12: 5000 | AF12: 6000 | AG12: =O12 -> 6000 | AH12: =P12 -> 6000 | AI12: =Q12 -> 6000 | AJ12: =R12 -> 6000 | AK12: =SUM(Y12:AJ12) -> 53000 | AL12: =S12-AK12 -> 16000
A13: 13 | B13: Shaikh Javed | C13: E-automate | D13: 12000 | E13: 6000 | F13: Akbar sir | G13: 6000 | H13: 6000 | I13: 6000 | J13: 6000 | K13: 5000 | L13: 5000 | M13: 5000 | N13: 6000 | O13: 6000 | P13: 6000 | Q13: 6000 | R13: 6000 | S13: =SUM(G13:R13) -> 69000 | T13: 0 | U13: 51000 | V13: 24000 | W13: 24000 | Y13: 6000 | Z13: 0 | AA13: 6000 | AB13: 6000 | AC13: 0 | AD13: 0 | AE13: 5000 | AF13: 6000 | AG13: =O13 -> 6000 | AH13: =P13 -> 6000 | AI13: =Q13 -> 6000 | AJ13: =R13 -> 6000 | AK13: =SUM(Y13:AJ13) -> 53000 | AL13: =S13-AK13 -> 16000
A14: 14 | B14: Noorul Khan | C14: E-automate | D14: 6000 | E14: 6000 | F14: Akbar sir | G14: NA | H14: NA | I14: NA | J14: NA | K14: 6000 | L14: 6000 | M14: 6000 | N14: 6000 | O14: 6000 | P14: 6000 | Q14: 6000 | R14: 6000 | S14: =SUM(G14:R14) -> 48000 | T14: 0 | U14: =S14+T14 -> 48000 | V14: 12000 | W14: =U14-V14 -> 36000 | AC14: 0 | AD14: 0 | AE14: 6000 | AF14: 6000 | AG14: =O14 -> 6000 | AH14: =P14 -> 6000 | AI14: =Q14 -> 6000 | AJ14: =R14 -> 6000 | AK14: 12000 | AL14: -12000
A15: 15 | B15: Shazeena | C15: Financial Force | D15: 16000 | E15: 6000 | F15: Akbar sir | G15: 6000 | H15: 6000 | I15: 6000 | J15: 5000 | K15: 6000 | L15: 6000 | M15: 6000 | N15: 6000 | O15: 6000 | P15: 6000 | Q15: 6000 | R15: 6000 | S15: =SUM(G15:R15) -> 71000 | T15: 0 | U15: =S15+T15 -> 71000 | V15: =D15*2 -> 32000 | W15: =U15-V15 -> 39000 | Y15: 0 | Z15: 0 | AA15: 6000 | AB15: 5000 | AC15: 6000 | AD15: 0 | AE15: 0 | AF15: 0 | AG15: 0 | AH15: =P15 -> 6000 | AI15: =Q15 -> 6000 | AJ15: =R15 -> 6000 | AK15: 17000 | AL15: 36000
A16: 17 | B16: Amir Dalvi | C16: Financial Force | D16: 12000 | E16: 4000 | F16: Akbar sir | G16: NA | H16: NA | I16: NA | J16: NA | K16: NA | L16: NA | M16: NA | N16: NA | O16: 4000 | P16: 4000 | Q16: 4000 | R16: 4000 | AG16: 0 | AH16: 0 | AI16: 0 | AJ16: 0
A17: 18 | B17: Maaz Shaokat Choughle | C17: Financial Force | D17: 30000 | E17: 5000 | F17: Akbar sir | G17: 4000 | H17: 3000 | I17: 3000 | J17: 7000 | K17: 10000 | L17: 10000 | M17: 8000 | N17: 8000 | O17: 5000 | P17: 5000 | Q17: 5000 | R17: =E17/22*13 -> 2954.5455 | S17: 58000 | T17: #REF! | U17: ####### | V17: 60000 | W17: ####### | Y17: 0 | Z17: 0 | AA17: 0 | AB17: 7000 | AD17: 10000 | AE17: 8000 | AF17: 8000 | AG17: 0 | AH17: 0 | AI17: 0 | AJ17: 0
A18: 19 | B18: Najeeb | C18: Financial Force | D18: 20000 | E18: 5000 | F18: Akbar sir | G18: NA | H18: NA | I18: NA | J18: 4000 | K18: 4000 | L18: 4000 | M18: 4000 | N18: 3000 | O18: 4000 | P18: =E18/20*5 -> 1250 | Q18: 5000 | R18: 4000 | S18: =SUM(G18:R18) -> 33250 | T18: 0 | U18: =S18+T18 -> 33250 | V18: =D18*2 -> 40000 | AB18: 0 | AD18: 0 | AF18: 0 | AG18: 0 | AH18: 0 | AI18: 0 | AJ18: 0
A19: 20 | B19: Nabeela khan | C19: Microsoft CRM | D19: 40000 | E19: 10000 | F19: Akbar sir | G19: 10000 | H19: 10000 | I19: 10000 | J19: 10000 | K19: 10000 | L19: 10000 | M19: 7000 | N19: 10000 | O19: 10000 | P19: 10000 | Q19: =E19/23*13 -> 5652.1739 | R19: 10000 | S19: 87000 | T19: 0 | U19: 87000 | V19: 80000 | W19: 80000 | Y19: 10000 | Z19: 10000 | AA19: 10000 | AB19: 10000 | AC19: 10000 | AD19: 8250 | AE19: 7000 | AF19: 10000 | AG19: =O19 -> 10000 | AH19: =P19 -> 10000 | AJ19: =R19 -> 10000 | AK19: 75250 | AL19: 11750
A20: 21 | B20: Irfan Shaikh | C20: Microsoft CRM | D20: 25000 | E20: 5000 | F20: Akbar sir | G20: 6000 | H20: 6000 | I20: 6000 | J20: 4000 | K20: 6000 | L20: 6000 | M20: 4000 | N20: 6000 | O20: 6000 | P20: 0 | Q20: 3000 | R20: =G20/22*7 -> 1909.0909 | S20: 50000 | T20: 0 | U20: 50000 | V20: 28000 | W20: 28000 | Y20: 6000 | Z20: 6000 | AA20: 6000 | AB20: 4000 | AC20: 0 | AD20: 0 | AE20: 0 | AF20: 0 | AG20: =O20 -> 6000 | AH20: 0 | AJ20: 0 | AK20: 22000 | AL20: 28000
A21: 22 | B21: Neha Shaikh | C21: Microsoft CRM | D21: 12000 | E21: 4000 | F21: Akbar sir | G21: NA | H21: NA | I21: NA | J21: NA | K21: NA | L21: NA | M21: NA | N21: NA | O21: 4000 | P21: 4000 | Q21: =E21/23*20 -> 3478.2609 | R21: 4000 | S21: =SUM(H21:R21) -> 15478.261 | AG21: 0 | AH21: 0 | AJ21: 0 | AL21: =S21 -> 15478.261
A22: 23 | B22: Mohsin Mohd | C22: OIC | D22: 25000 | E22: 5000 | F22: Akbar sir | G22: 8000 | H22: 8000 | I22: 8000 | J22: 8000 | K22: 8000 | L22: 5000 | M22: 5000 | N22: 5000 | O22: 5000 | P22: 5000 | Q22: 5000 | R22: 5000 | S22: =SUM(G22:R22) -> 75000 | T22: 0 | U22: 60000 | V22: 50000 | W22: 50000 | Y22: 0 | Z22: 8000 | AA22: 8000 | AB22: 8000 | AC22: 8000 | AD22: 5000 | AE22: 5000 | AF22: 5000 | AG22: 0 | AH22: 0 | AJ22: 0 | AK22: 47000 | AL22: =S22-AK22 -> 28000
A23: 24 | B23: Shamshad Ahmed | C23: Qliksense | D23: 22000 | E23: 8000 | F23: Akbar sir | G23: 8000 | H23: 8000 | I23: 8000 | J23: 8000 | K23: 8000 | L23: 8000 | M23: 8000 | N23: 8000 | O23: 8000 | P23: =E23/20*15 -> 6000 | Q23: =E23/23*18 -> 6260.8696 | R23: 8000 | S23: 72000 | T23: 0 | U23: 72000 | V23: 44000 | W23: 44000 | Y23: 8000 | Z23: 8000 | AA23: 8000 | AB23: 8000 | AC23: 0 | AD23: 0 | AE23: 0 | AF23: 8000 | AG23: =O23 -> 8000 | AH23: =P23 -> 6000 | AI23: =Q23 -> 6260.8696 | AJ23: =R23 -> 8000 | AK23: 40000 | AL23: 32000
A24: 25 | B24: Ahtesham | C24: Qliksense | D24: 6000 | E24: 6000 | F24: Akbar sir | G24: NA | H24: NA | I24: 6000 | J24: 6000 | K24: 5000 | L24: 6000 | M24: 6000 | N24: 6000 | O24: 6000 | P24: 6000 | Q24: 6000 | R24: 6000 | S24: =SUM(G24:R24) -> 59000 | U24: 41000 | V24: 12000 | W24: 12000 | Y24: NA | Z24: 0 | AA24: 0 | AB24: 0 | AC24: 5000 | AD24: 6000 | AE24: 6000 | AF24: 6000 | AG24: =O24 -> 6000 | AH24: =P24 -> 6000 | AI24: =Q24 -> 6000 | AJ24: =R24 -> 6000 | AK24: =SUM(AC24:AJ24) -> 47000 | AL24: =S24-AK24 -> 12000
A25: 26 | B25: Tauseef | C25: Qliksense | D25: 14000 | E25: 6000 | F25: Akbar sir | G25: NA | H25: NA | I25: NA | J25: NA | K25: NA | L25: NA | M25: 6000 | N25: 6000 | O25: 6000 | P25: 6000 | Q25: 6000 | R25: 6000 | S25: =SUM(L25:R25) -> 36000 | V25: 12000 | AE25: 0 | AF25: 0 | AG25: =O25 -> 6000 | AH25: =P25 -> 6000 | AI25: =Q25 -> 6000 | AJ25: 0 | AK25: =SUM(Y25:AJ25) -> 18000 | AL25: =S25-AK25 -> 18000
A26: 27 | B26: Warfan | C26: Qliksense | D26: 14000 | E26: 6000 | F26: Akbar sir | G26: NA | H26: NA | I26: NA | J26: NA | K26: NA | L26: NA | M26: 6000 | N26: 6000 | O26: 6000 | P26: 6000 | Q26: 5000 | R26: 6000 | S26: =SUM(G26:R26) -> 35000 | T26: 0 | U26: =S26+T26 -> 35000 | V26: =D26*2 -> 28000 | W26: =U26-V26 -> 7000 | AE26: 0 | AF26: 0 | AG26: =O26 -> 6000 | AH26: 0 | AJ26: 6000 | AK26: 0 | AL26: 0
A27: 28 | B27: Fahmida | C27: Sales | D27: 10000 | E27: 5000 | F27: Akbar sir | G27: NA | H27: NA | I27: NA | J27: NA | K27: NA | L27: NA | M27: 5000 | N27: 5000 | O27: 5000 | P27: 5000 | Q27: =E27/23*20 -> 4347.8261 | R27: =E27/22*10 -> 2272.7273 | V27: 20000 | W27: 20000 | AE27: 0 | AF27: 0 | AG27: 0 | AH27: 0 | AI27: =Q27 -> 4347.8261 | AJ27: =R27 -> 2272.7273 | AK27: 0 | AL27: 0
A28: 29 | B28: Ibrahim | C28: Sales | D28: 18000 | E28: 7000 | F28: Akbar sir | G28: 7000 | H28: 7000 | I28: 7000 | J28: 7000 | K28: 7000 | L28: 7000 | M28: 7000 | N28: 7000 | O28: 7000 | P28: 0 | Q28: =E28/23*14 -> 4260.8696 | R28: 7000 | S28: 63000 | U28: 63000 | V28: 36000 | W28: 36000 | Y28: 7000 | Z28: 7000 | AA28: 7000 | AB28: 7000 | AC28: 7000 | AD28: 7000 | AE28: 7000 | AF28: 7000 | AG28: =O28 -> 7000 | AH28: =P28 -> 0 | AI28: =Q28 -> 4260.8696 | AJ28: =R28 -> 7000 | AK28: 56000 | AL28: 7000
A29: 30 | B29: Sana | C29: Sales | D29: 10000 | E29: 5000 | F29: Akbar sir | G29: NA | H29: NA | I29: NA | J29: NA | K29: NA | L29: NA | M29: NA | N29: NA | O29: NA | P29: 5000 | Q29: =E29-2000 -> 3000 | R29: =E29/22*12 -> 2727.2727 | S29: =SUM(P29:R29) -> 10727.273 | AH29: 0 | AL29: =S29 -> 10727.273
A30: 31 | B30: Mohammad Rehanuddin | C30: Salesforce | D30: 47000 | E30: 5000 | F30: Akbar sir | G30: 5000 | H30: 10000 | I30: 10000 | J30: 10000 | K30: 10000 | L30: 10000 | M30: 10000 | N30: 10000 | O30: 10000 | P30: 10000 | Q30: 5000 | R30: 5000 | S30: 85000 | T30: 0 | U30: 85000 | V30: 70000 | W30: 70000 | Y30: 5000 | Z30: 10000 | AA30: 10000 | AB30: 10000 | AC30: 0 | AD30: 10000 | AE30: 10000 | AF30: 10000 | AG30: 0 | AH30: =P30 -> 10000 | AI30: =Q30 -> 5000
A31: 33 | B31: Gaus | C31: Salesforce | D31: 15000 | E31: 10000 | F31: Akbar sir | G31: NA | H31: NA | I31: NA | J31: NA | K31: 3000 | L31: 8000 | M31: 8500 | N31: 5000 | O31: 10000 | P31: 10000 | Q31: 10000 | R31: 8000 | V31: 30000 | AD31: 0 | AF31: 0 | AG31: 0 | AH31: =P31 -> 10000 | AI31: =Q31 -> 10000 | AJ31: =R31 -> 8000
A32: 34 | B32: Zafar | C32: Salesforce | D32: 12000 | E32: 4000 | F32: Akbar sir | G32: NA | H32: NA | I32: NA | J32: NA | K32: NA | L32: NA | M32: NA | N32: NA | O32: 4000 | P32: 3000 | Q32: 4000 | R32: 2000 | AG32: 0 | AH32: 0 | AJ32: 0
A33: 35 | B33: Shahzad | C33: Salesforce | D33: 12000 | E33: 4000 | F33: Akbar sir | G33: NA | H33: NA | I33: NA | J33: NA | K33: NA | L33: 4000 | M33: 4000 | N33: 4000 | O33: 4000 | P33: 3000 | Q33: 2000 | R33: 4000 | V33: 24000 | AD33: 0 | AE33: 0 | AF33: 0 | AG33: 0 | AH33: 0 | AJ33: 0 | AK33: 0 | AL33: 0
A34: 36 | B34: Mustaqeem | C34: Salesforce | D34: 25000 | E34: 10000 | F34: Akbar sir | G34: 3000 | H34: 5000 | I34: 5000 | J34: 5000 | K34: 10000 | L34: 10000 | M34: 10000 | N34: 10000 | O34: 10000 | P34: 10000 | Q34: 10000 | R34: =E34/22*7 -> 3181.8182 | S34: 68000 | T34: 0 | U34: 68000 | V34: 50000 | W34: 50000 | Y34: 0 | Z34: 5000 | AA34: 5000 | AB34: 5000 | AC34: 0 | AD34: 10000 | AE34: 10000 | AF34: 10000 | AG34: =O34 -> 10000 | AH34: =P34 -> 10000 | AI34: =Q34 -> 10000 | AJ34: =R34 -> 3181.8182
A35: 38 | B35: Saba Shaikh | C35: SharePoint | D35: 30000 | E35: 10000 | F35: Akbar sir | G35: 10000 | H35: 5000 | I35: 9000 | J35: 10000 | K35: 9000 | L35: 10000 | M35: 10000 | N35: 10000 | O35: =E35/23*19 -> 8260.8696 | P35: 10000 | Q35: 10000 | R35: 10000 | S35: =SUM(G35:R35) -> 111260.87 | T35: 22000 | U35: =S35+T35 -> 133260.87 | V35: 60000 | W35: =U35-V35 -> 73260.87 | Y35: 10000 | Z35: 5000 | AA35: 9000 | AB35: 0 | AC35: 0 | AD35: 10000 | AE35: 10000 | AF35: 10000 | AG35: 0 | AH35: =P35 -> 10000 | AI35: =Q35 -> 10000 | AJ35: =R35 -> 10000 | AK35: =SUM(Y35:AJ35) -> 84000 | AL35: =AK35-W35 -> 10739.13
A36: 40 | B36: Rahmath | C36: SharePoint | D36: 12000 | E36: 4000 | F36: Akbar sir | G36: NA | H36: NA | I36: NA | J36: NA | K36: NA | L36: NA | M36: 4000 | N36: 4000 | O36: 4000 | P36: 4000 | Q36: 4000 | R36: 4000 | V36: 24000 | AE36: 0 | AF36: 0 | AG36: 0 | AH36: 0 | AJ36: 0
A37: 42 | B37: Khizer | C37: Uipath | D37: 6000 | E37: 6000 | F37: Akbar sir | G37: NA | H37: 6000 | I37: 3000 | J37: 6000 | K37: 6000 | L37: 6000 | M37: 6000 | N37: 15062 | O37: 15250 | P37: 17250 | Q37: 6000 | R37: 6000 | S37: =SUM(G37:R37) -> 92562 | U37: 48062 | V37: 12000 | Z37: 0 | AA37: 0 | AB37: 0 | AC37: 6000 | AD37: 6000 | AE37: 6000 | AF37: 18000 | AG37: =O37 -> 15250 | AH37: =P37 -> 17250 | AI37: =Q37 -> 6000 | AJ37: =R37 -> 6000 | AK37: =SUM(Y37:AJ37) -> 80500 | AL37: =S37-AK37 -> 12062
A38: 43 | B38: Rameez | C38: Uipath | D38: 6000 | E38: 6000 | F38: Akbar sir | G38: NA | H38: NA | I38: NA | J38: NA | K38: NA | L38: 6000 | M38: 6000 | N38: 16571 | O38: 17250 | P38: 17250 | Q38: 6000 | R38: 6000 | S38: =SUM(G38:R38) -> 75071 | V38: 12000 | AD38: 0 | AE38: 0 | AF38: 20000 | AG38: =O38 -> 17250 | AH38: =P38 -> 17250 | AI38: =Q38 -> 6000 | AJ38: =R38 -> 6000 | AK38: =SUM(AD38:AJ38) -> 66500 | AL38: =S38-AK38 -> 8571
A39: 47 | B39: Ahad | C39: wordpresss | D39: 10000 | E39: 6000 | F39: Akbar sir | G39: NA | H39: NA | I39: NA | J39: NA | K39: NA | L39: NA | M39: NA | N39: NA | O39: NA | P39: 6000 | Q39: 0 | R39: 0 | AH39: 0 | AJ39: =R39 -> 0
A40: 48 | B40: Amir Shaikh | C40: wordpresss | D40: 6000 | E40: 6000 | F40: Akbar sir | G40: NA | H40: NA | I40: NA | J40: NA | K40: NA | L40: NA | M40: NA | N40: NA | O40: 6000 | P40: 6000 | Q40: 6000 | R40: 6000 | S40: =SUM(O40:R40) -> 24000 | AG40: 0 | AH40: 0 | AI40: 6000 | AJ40: =R40 -> 6000 | AK40: =SUM(AG40:AJ40) -> 12000 | AL40: =S40-AK40 -> 12000
A41: 49 | B41: Zeeshan Shaikh | C41: Eienstein | D41: 20000 | E41: 5000 | F41: Rehan | G41: NA | H41: NA | I41: NA | J41: NA | K41: 6000 | L41: 6000 | M41: 6000 | N41: 6000 | O41: 5000 | P41: 5000 | Q41: =E41/23*13 -> 2826.087 | R41: 5000 | S41: =SUM(G41:R41) -> 41826.087 | T41: 0 | U41: =S41+T41 -> 41826.087 | V41: =D41*2 -> 40000 | W41: =U41-V41 -> 1826.087 | AC41: 0 | AD41: 0 | AE41: 6000 | AF41: 6000 | AG41: 0 | AH41: 0 | AJ41: 0 | AL41: =U41-AE41-AF41 -> 29826.087
A42: 51 | B42: Samee | C42: Eienstein | D42: 12000 | E42: 4000 | F42: Rehan | G42: NA | H42: NA | I42: NA | J42: NA | K42: NA | L42: NA | M42: NA | N42: 4000 | O42: =E42/23*16 -> 2782.6087 | P42: 2000 | Q42: 4000 | R42: 4000 | S42: =SUM(K42:R42) -> 16782.609 | T42: 0 | U42: =S42+T42 -> 16782.609 | V42: 24000 | AF42: 0 | AG42: 0 | AH42: 0 | AJ42: 0 | AL42: =S42 -> 16782.609
A43: 52 | B43: Sufyan Aquib | C43: Salesforce | D43: 20000 | E43: 5000 | F43: Rehan | G43: NA | H43: NA | I43: NA | J43: 4000 | K43: 4000 | L43: 4000 | M43: 4000 | N43: 5000 | O43: 5000 | P43: 5000 | Q43: =E43/23*20 -> 4347.8261 | R43: 5000 | V43: 40000 | AB43: 0 | AD43: 0 | AE43: 0 | AF43: 0 | AG43: 0 | AH43: 0 | AJ43: 0 | AK43: 0 | AL43: 0
A44: 55 | B44: Zeeshan Sayyed | C44: Salesforce | D44: 15000 | E44: 10000 | F44: Shahid | G44: 2000 | H44: 2000 | I44: 2000 | J44: 2000 | K44: 0 | L44: 6000 | M44: 0 | N44: 0 | O44: 9000 | P44: 5000 | Q44: 6000 | R44: 8000 | S44: =SUM(G44:R44) -> 42000 | T44: 12000 | U44: =S44+T44 -> 54000 | V44: 30000 | W44: =U44-V44 -> 24000 | Y44: 0 | Z44: 0 | AA44: 0 | AB44: 0 | AC44: 0 | AD44: 6000 | AE44: 0 | AF44: 0 | AG44: 0 | AH44: 0 | AI44: =Q44 -> 6000 | AJ44: =R44 -> 8000 | AK44: =SUM(Y44:AJ44) -> 20000 | AL44: =S44-AK44 -> 22000
A45: 56 | B45: Sohail Inamdar | C45: Salesforce | D45: 15000 | E45: 10000 | F45: Shahid | G45: 4000 | H45: 0 | I45: 3000 | J45: 7000 | K45: 10000 | L45: 9000 | M45: 9000 | N45: 8000 | O45: 9000 | P45: 9000 | Q45: 7000 | R45: 9000 | S45: =SUM(G45:R45) -> 84000 | T45: ='2020'!S24 -> 11500 | U45: =S45+T45 -> 95500 | V45: 30000 | W45: =U45-V45 -> 65500 | Z45: 0 | AA45: 0 | AB45: 0 | AD45: 9000 | AE45: 9000 | AF45: 8000 | AG45: =O45 -> 9000 | AH45: =P45 -> 9000 | AI45: =Q45 -> 7000 | AJ45: =R45 -> 9000 | AK45: =SUM(Y45:AJ45) -> 60000 | AL45: =24000+11500-30000 -> 5500
A46: 57 | B46: Ansari Mohd Ateef | C46: Salesforce | D46: 30000 | E46: 5000 | F46: Shahid | G46: 2500 | H46: 3000 | I46: 3000 | J46: 4000 | K46: 8000 | L46: 9000 | M46: 8000 | N46: 9000 | O46: 5000 | P46: 0 | Q46: =E46/23*8 -> 1739.1304 | R46: 4000 | S46: =SUM(G46:R46) -> 57239.13 | T46: ='2020'!U25 -> 9600 | U46: =S46+T46 -> 66839.13 | V46: 60000 | W46: =U46-V46 -> 6839.1304 | Y46: 0 | Z46: 0 | AA46: 0 | AB46: 0 | AD46: 9000 | AE46: 8000 | AF46: 9000 | AG46: 0 | AH46: 0 | AJ46: 0 | AK46: =SUM(Y46:AJ46) -> 26000 | AL46: =S46-AK46 -> 31239.13
A47: 58 | B47: Priya Sharma | C47: Salesforce | D47: 12000 | E47: 4000 | F47: Shahid | G47: NA | H47: NA | I47: NA | J47: NA | K47: NA | L47: NA | M47: 3000 | N47: 3000 | O47: 4000 | P47: 2000 | Q47: 4000 | R47: 3000 | V47: 24000 | AF47: 0 | AG47: 0 | AH47: 0 | AJ47: 0
A48: 59 | B48: Swati | C48: Salesforce | D48: 12000 | E48: 4000 | F48: Shahid | G48: NA | H48: NA | I48: NA | J48: NA | K48: NA | L48: NA | M48: NA | N48: NA | O48: 4000 | P48: 4000 | Q48: 4000 | R48: 3000 | AG48: 0 | AH48: 0 | AJ48: 0
A49: 60 | B49: Muzafar Khan | C49: Salesforce | D49: 12000 | E49: 4000 | F49: Shahid | G49: NA | H49: NA | I49: NA | J49: NA | K49: NA | L49: NA | M49: NA | N49: NA | O49: 4000 | P49: 4000 | Q49: 4000 | R49: 4000 | AG49: 0 | AH49: 0 | AJ49: 0
A50: 61 | B50: Samad | C50: Microsoft CRM | D50: 12000 | E50: 4000 | F50: Akbar sir | G50: NA | H50: NA | I50: NA | J50: NA | K50: NA | L50: NA | M50: NA | N50: NA | O50: NA | P50: NA | Q50: 4000 | R50: 4000 | S50: =SUM(Q50:R50) -> 8000 | AH50: 0 | AJ50: 0
A51: 62 | B51: Saeed | C51: Financial Force-Salesforce | D51: 12000 | E51: 4000 | F51: Akbar sir | G51: NA | H51: NA | I51: NA | J51: NA | K51: NA | L51: NA | M51: NA | N51: NA | O51: NA | P51: NA | Q51: NA | R51: 0 | AJ51: 0
A52: 63 | B52: Sajed | C52: Financial Force-Salesforce | D52: 12000 | E52: 4000 | F52: Akbar sir | G52: NA | H52: NA | I52: NA | J52: NA | K52: NA | L52: NA | M52: NA | N52: NA | O52: NA | P52: NA | Q52: NA | R52: 4000 | AJ52: 0
A53: 64 | B53: Batul | C53: Sales | D53: 6000 | E53: 6000 | F53: Akbar sir | G53: NA | H53: NA | I53: NA | J53: NA | K53: NA | L53: NA | M53: NA | N53: NA | O53: NA | P53: NA | Q53: NA | R53: 6000
A54: 65 | B54: Shaikh Asmina Mohd Aslam | C54: Salesforce | D54: 12000 | E54: 4000 | F54: Shahid | G54: NA | H54: NA | I54: NA | J54: NA | K54: NA | L54: NA | M54: 3000 | N54: 4000 | O54: 4000 | P54: 4000 | Q54: 4000 | R54: 4000 | S54: =SUM(G54:R54) -> 23000 | T54: 0 | U54: =S54+T54 -> 23000 | V54: 24000 | AF54: 0 | AG54: 0 | AH54: 0 | AJ54: 0 | AL54: =S54 -> 23000
B55: Total | D55: =SUM(D2:D54) -> 833000 | E55: =SUM(E2:E54) -> 308000 | F55: =SUM(F2:F54) -> 0 | G55: =SUM(G2:G54) -> 111500 | H55: =SUM(H2:H54) -> 120000 | I55: =SUM(I2:I54) -> 127000 | J55: =SUM(J2:J54) -> 150000 | K55: =SUM(K2:K54) -> 178000 | ... AJ55: =SUM(AJ2:AJ54) -> 167454.55 | AK55: 630312 | AL55: 273250
AI56: 5000
AI57: =AI55 -> 140869.57 | AJ57: =AI10+AI27+AI31+'To beDeleted'!AI35+'To beDeleted'!AI36+AI38+AI44 -> 47347.826
AJ58: 10000
M60: =22309+O48 -> 26309
N62: 5000
G73: Aug 2021 to feb2022

Sheet 2022
A1: Sr No | B1: Name of the Employee | C1: Technology | D1: Salary | E1: Bonus amount | F1: Reporting manager | G1: Jan | H1: Feb | I1: Mar | J1: Apr | K1: May | L1: Jun | M1: Jul | N1: Aug | O1: Sep | P1: Oct | Q1: Nov | R1: Dec | S1: This year 2022 bonus amount | T1: as per rule 2 month hold bonus amount should be | U1: Deposit bonus Amount along with us till 2022 paid after notice period /Contract | V1: Hold Bonus paid amount 2022 | W1: To be Paid with Salary in Jan 2022 | X1: To be Paid with Salary in Feb 2022 | Y1: To be Paid with Salary in Mar 2022 | Z1: To be Paid with Salary in Apr 2022 | AA1: To be Paid with Salary in May 2022 | AB1: To be Paid with Salary in Jun 2022 | AC1: To be Paid with Salary in July 2022 | AD1: To be Paid with Salary in Aug 2022 | AE1: To be Paid with Salary in Sep 2022 | AF1: To be Paid with Salary in Oct 2022 | AG1: To be Paid with Salary in Nov 2022 | AH1: To be Paid with Salary in Dec 2022 | AJ1: Total bonus given in 2022 amount | AK1: remaining 2022 | AL1: remaining 2021 | AM1: remaining 2020 | AN1: Total Balance need to pay after notice period
A2: 1 | B2: Ansari Yasmeen | C2: Accounts | D2: 10000 | E2: 8000 | F2: Akbar sir | G2: 5000 | H2: 4000 | I2: 5000 | J2: 5000 | K2: 5000 | L2: =E2/23*14 -> 4869.5652 | M2: 4000 | N2: 5000 | O2: 11000 | P2: 8000 | Q2: =8000/23*18 -> 6260.8696 | R2: 6000 | S2: =SUM(G2:R2) -> 69130.435 | T2: =D2*2 -> 20000 | U2: ='2021'!S2-'2021'!AK2 -> 20000 | V2: =0 -> 0 | W2: =G2 -> 5000 | X2: =H2 -> 4000 | Y2: =I2 -> 5000 | Z2: =J2 -> 5000 | AA2: =K2 -> 5000 | AB2: =L2 -> 4869.5652 | AC2: 4000 | AD2: =N2 -> 5000 | AE2: =O2 -> 11000 | AF2: =P2 -> 8000 | AG2: =Q2 -> 6260.8696 | AH2: =R2 -> 6000 | AI2: a | AJ2: =SUM(W2:AH2) -> 69130.435 | AK2: =S2-W2-X2-Y2-Z2-AA2-AB2-AC2-AD2-AE2-AF2-AG2-AH2 -> 7.2759576e-12 | AL2: ='2021'!S2-'2021'!AD2-'2021'!AE2-'2021'!AF2-'2021'!AG2-'2021'!AH2-'2021'!AI2-'2021'!AJ2 -> 20000 | AN2: =AK2+AL2 -> 20000
A3: 2 | B3: Sherkhan Misbah ismail | C3: Accounts | D3: 10000 | E3: 8000 | F3: Akbar sir | G3: 5000 | H3: 4500 | I3: 5000 | J3: 5000 | K3: 5000 | L3: 5000 | M3: 5000 | N3: 5000 | O3: =E3/22*17 -> 6181.8182 | P3: 8000 | Q3: 8000 | R3: =E3/22*18 -> 6545.4545 | S3: =SUM(G3:R3) -> 68227.273 | T3: =D3*2 -> 20000 | U3: ='2021'!S3+'2022'!G3 -> 20045.455 | V3: =0 -> 0 | W3: 0 | X3: =H3 -> 4500 | Y3: =I3 -> 5000 | Z3: =J3 -> 5000 | AA3: =K3 -> 5000 | AB3: =L3 -> 5000 | AC3: 5000 | AD3: =N3 -> 5000 | AE3: =O3 -> 6181.8182 | AF3: =P3 -> 8000 | AG3: =Q3 -> 8000 | AH3: =R3 -> 6545.4545 | AI3: a | AJ3: =SUM(W3:AH3) -> 63227.273 | AK3: =S3-W3-X3-Y3-Z3-AA3-AB3-AC3-AD3-AE3-AF3-AG3-AH3 -> 5000 | AL3: ='2021'!S3-'2021'!AK3 -> 15045.455 | AN3: =AK3+AL3 -> 20045.455
A4: 3 | B4: Imran Ahmed | C4: Angular | D4: 25000 | E4: 5000 | F4: Akbar sir | G4: 6000 | H4: 6000 | I4: 6000 | J4: =I4 -> 6000 | K4: 6000 | L4: 6000 | M4: 6000 | N4: 4000 | O4: 0 | P4: 5000 | Q4: 5000 | R4: =E4/21*18 -> 4285.7143 | S4: =SUM(G4:R4) -> 60285.714 | T4: =D4*2 -> 50000 | U4: 0 | V4: ='Hold bonus paid sheet'!C11 -> 66000 | W4: =G4 -> 6000 | X4: =H4 -> 6000 | Y4: =I4 -> 6000 | Z4: =J4 -> 6000 | AA4: =K4 -> 6000 | AB4: =L4 -> 6000 | AC4: 6000 | AD4: =N4 -> 4000 | AE4: =O4 -> 0 | AF4: =P4 -> 5000 | AG4: =Q4 -> 5000 | AH4: =R4 -> 4285.7143 | AI4: a | AJ4: =SUM(W4:AH4) -> 60285.714 | AK4: =S4-AJ4+SUM('To beDeleted'!I55:S55) -> 42000 | AL4: ='2021'!S4-'2021'!AF4-'2021'!AG4-'2021'!AH4-'2021'!AI4-'2021'!AJ4 -> 24000 | AN4: =AK4+AL4-V4 -> 0
A5: 4 | B5: Shaikh Muddassir | C5: Angular | D5: 18000 | E5: 6000 | F5: Akbar sir | G5: 6000 | H5: 6000 | I5: 6000 | J5: 3000 | K5: 3000 | L5: 3000 | M5: 3000 | N5: 3000 | O5: 0 | P5: 3000 | Q5: 0 | R5: =E5/21*10 -> 2857.1429 | S5: =SUM(G5:R5) -> 38857.143 | T5: =D5*2 -> 36000 | U5: ='2020'!AH20+'2021'!AL12+'2022'!G5+'2022'!I5+'2022'!L5 -> 44650 | V5: =0 -> 0 | W5: 0 | X5: =H5 -> 6000 | Y5: 0 | Z5: =J5 -> 3000 | AA5: =K5 -> 3000 | AB5: 0 | AC5: 3000 | AD5: =N5 -> 3000 | AE5: =O5 -> 0 | AF5: =P5 -> 3000 | AG5: =Q5 -> 0 | AH5: =R5 -> 2857.1429 | AI5: a | AJ5: =SUM(W5:AH5) -> 23857.143 | AK5: =S5-AJ5 -> 15000 | AL5: ='2021'!S12-'2021'!AK12 -> 16000 | AM5: ='2020'!S20-'2020'!AG20 -> 13650 | AN5: =AK5+AL5+AM5-V5 -> 44650
A6: 5 | B6: Shaikh Tareque | C6: Angular | D6: 40000 | E6: 10000 | F6: Akbar sir | G6: 5000 | H6: 5000 | I6: 5000 | J6: =I6 -> 5000 | K6: =J6 -> 5000 | L6: 5000 | M6: 5000 | N6: 3000 | O6: 3000 | P6: =E6/21*16 -> 7619.0476 | Q6: 0 | R6: 0 | S6: =SUM(G6:R6) -> 48619.048 | T6: =D6*2 -> 80000 | U6: =SUM(O6:R6) -> 10619.048 | V6: ='Hold bonus paid sheet'!C7 -> 54090 | W6: 0 | X6: =H6 -> 5000 | Y6: =I6 -> 5000 | Z6: =J6 -> 5000 | AA6: =K6 -> 5000 | AB6: =L6 -> 5000 | AC6: 5000 | AD6: =N6 -> 3000 | AE6: 0 | AF6: 0 | AG6: 0 | AH6: 0 | AJ6: =SUM(W6:AH6) -> 33000 | AK6: =S6-AJ6 -> 15619.048 | AL6: ='2021'!S6-'2021'!AK6 -> 26590.909 | AM6: ='2020'!S15-'2020'!AG15 -> 12000
A7: 6 | B7: Khan Noorul Hasan | C7: E-automate | D7: 30000 | E7: 5000 | F7: Akbar sir | G7: 6000 | H7: 6000 | I7: 6000 | J7: =I7 -> 6000 | K7: =J7 -> 6000 | L7: 6000 | M7: 6000 | N7: =6000/23*10 -> 2608.6957 | O7: 5000 | P7: 5000 | Q7: =5000/23*19 -> 4130.4348 | R7: 0 | S7: =SUM(G7:R7) -> 58739.13 | T7: =D7*2 -> 60000 | U7: =SUM(O7:R7) -> 14130.435 | V7: =0 -> 0 | W7: 0 | X7: 0 | Y7: =I7 -> 6000 | Z7: =J7 -> 6000 | AA7: =K7 -> 6000 | AB7: =L7 -> 6000 | AC7: 6000 | AD7: =N7 -> 2608.6957 | AE7: 0 | AF7: 0 | AG7: 0 | AH7: 0 | AJ7: =SUM(W7:AH7) -> 32608.696
A8: 7 | B8: Shaikh Javed | C8: Microsoft CRM | D8: 12000 | E8: 6000 | F8: Akbar sir | G8: 6000 | H8: 6000 | I8: 6000 | J8: =I8 -> 6000 | K8: =J8 -> 6000 | L8: 3000 | M8: 3000 | N8: 3000 | O8: 0 | P8: 6000 | Q8: 6000 | R8: 6000 | S8: =SUM(G8:R8) -> 57000 | T8: =D8*2 -> 24000 | U8: ='2020'!AH21+'2021'!AL13+'2022'!M9 -> 35800 | V8: =0 -> 0 | W8: =G8 -> 6000 | X8: =H8 -> 6000 | Y8: =I8 -> 6000 | Z8: =J8 -> 6000 | AA8: =K8 -> 6000 | AB8: =L8 -> 3000 | AC8: 0 | AD8: =N8 -> 3000 | AE8: =O8 -> 0 | AF8: =P8 -> 6000 | AG8: =Q8 -> 6000 | AH8: =R8 -> 6000 | AI8: a | AJ8: =SUM(W8:AH8) -> 54000
A9: 8 | B9: Osama Khan | C9: Microsoft CRM | D9: 35000 | E9: 5000 | F9: Akbar sir | G9: 6000 | H9: 6000 | I9: =E9/20*14 -> 3500 | J9: 6000 | K9: 6000 | L9: 6000 | M9: 6000 | N9: =E9/23*16 -> 3478.2609 | O9: 6000 | P9: =6000/21*11+5000/21*10-3142.86 -> 2380.9495 | Q9: 0 | R9: 5000 | S9: =SUM(P9:R9) -> 7380.9495 | T9: =D9*2 -> 70000 | U9: =SUM(P9:R9) -> 7380.9495 | V9: ='Hold bonus paid sheet'!C9 -> 37909 | W9: 0 | X9: =H9 -> 6000 | Y9: 4200 | Z9: =J9 -> 6000 | AA9: =K9 -> 6000 | AB9: =L9 -> 6000 | AC9: 6000 | AD9: 4174 | AE9: =O9 -> 6000 | AF9: =6000/21*11 -> 3142.8571 | AG9: 0 | AH9: 0 | AJ9: =SUM(W9:AH9) -> 47516.857
A10: 9 | B10: Amir Khan | C10: Microsoft CRM | D10: 10000 | E10: 10000 | F10: Akbar sir | G10: NA | H10: NA | I10: NA | J10: NA | K10: NA | L10: NA | M10: NA | N10: NA | O10: =E10/22*9 -> 4090.9091 | P10: 10000 | Q10: 5000 | R10: 10000 | S10: =SUM(G10:R10) -> 29090.909 | T10: =D10*2 -> 20000 | U10: =SUM(O10:R10) -> 29090.909 | V10: 0 | AE10: 0 | AF10: 0 | AG10: 0 | AH10: 0 | AJ10: =SUM(W10:AH10) -> 0
A11: 10 | B11: Mohsin Mohd | C11: OIC | D11: 50000 | E11: 10000 | F11: Akbar sir | G11: 5000 | H11: 3478 | I11: 5000 | J11: =I11 -> 5000 | K11: 5000 | L11: 10000 | M11: 10000 | N11: 10000 | O11: 10000 | P11: =E11/21*10 -> 4761.9048 | Q11: 10000 | R11: =E11/21*16 -> 7619.0476 | S11: =SUM(G11:R11) -> 85858.952 | T11: =D11*2 -> 100000 | U11: =SUM(L11:R11) -> 62380.952 | V11: 0 | W11: 0 | X11: 0 | Y11: 0 | Z11: =J11 -> 5000 | AA11: 5000 | AB11: 0 | AC11: 0 | AD11: 0 | AE11: 0 | AF11: 0 | AG11: 0 | AH11: 0 | AJ11: =SUM(W11:AH11) -> 10000
A12: 11 | B12: Arshad Ansari | C12: OIC | D12: 6000 | E12: 10000 | F12: Akbar sir | G12: NA | H12: 10000 | I12: 10000 | J12: 10000 | K12: 10000 | L12: 10000 | M12: 10000 | N12: 10000 | O12: 10000 | P12: 10000 | Q12: =10000/23*13 -> 5652.1739 | R12: 8000 | S12: =SUM(G12:R12) -> 103652.17 | T12: =D12*2 -> 12000 | U12: =SUM(H12:R12) -> 103652.17 | V12: 0 | W12: 0 | X12: 0 | Y12: 0 | Z12: 0 | AA12: 0 | AB12: 0 | AC12: 0 | AD12: 0 | AE12: 0 | AF12: 0 | AG12: 0 | AH12: 0 | AJ12: =SUM(W12:AH12) -> 0
A13: 12 | B13: Ziaullah Ansari | C13: OIC | D13: 6000 | E13: 10000 | F13: Akbar sir | G13: NA | H13: NA | I13: NA | J13: NA | K13: NA | L13: NA | M13: NA | N13: NA | O13: NA | P13: NA | Q13: 10000 | R13: 10000 | T13: =D13*2 -> 12000 | AG13: 4000 | AH13: 4000 | AI13: a | AJ13: =SUM(W13:AH13) -> 8000
A14: 13 | B14: Tauseef Khan | C14: Qlik sense | D14: 30000 | E14: 10000 | F14: Akbar sir | G14: 6000 | H14: =E14/23*13 -> 5652.1739 | I14: 6000 | J14: 10000 | K14: 10000 | L14: 2000 | M14: 5000 | N14: 5000 | O14: 7000 | P14: 5000 | Q14: 5000 | R14: 0 | S14: =SUM(G14:R14) -> 66652.174 | T14: =D14*2 -> 60000 | U14: ='2021'!AL25+'2022'!G14+'2022'!H14+SUM(J14:R14) -> 78652.174 | V14: 0 | W14: 0 | X14: 0 | Y14: =I14 -> 6000 | Z14: 0 | AA14: 0 | AB14: 0 | AC14: 0 | AD14: 0 | AE14: 0 | AF14: 0 | AG14: 0 | AH14: 0 | AJ14: =SUM(W14:AH14) -> 6000
A15: 14 | B15: Syed Mustafa | C15: Qlik Sense | D15: 6000 | E15: 10000 | F15: Akbar sir | G15: NA | H15: NA | I15: NA | J15: NA | K15: =E15/22*22 -> 10000 | L15: 10000 | M15: 10000 | N15: 10000 | O15: 10000 | P15: 10000 | Q15: 10000 | R15: 10000 | S15: =SUM(G15:R15) -> 80000 | T15: =D15*2 -> 12000 | U15: =SUM(K15:R15) -> 80000 | V15: 0 | W15: 0 | X15: 0 | Y15: 0 | Z15: 0 | AA15: 0 | AB15: 0 | AC15: 0 | AD15: 0 | AE15: 0 | AF15: 0 | AG15: 0 | AH15: 0 | AJ15: =SUM(W15:AH15) -> 0
A16: 15 | B16: Ahtesham Mohammed | C16: Qlik Sense | D16: 30000 | E16: 10000 | F16: Akbar sir | G16: 6000 | H16: 6000 | I16: 4650 | J16: 5429 | K16: 5000 | L16: 0 | M16: 0 | N16: 0 | O16: 0 | P16: 0 | Q16: 0 | R16: 0 | S16: =SUM(G16:R16) -> 27079 | T16: 60000 | U16: =SUM('2022'!L16:R16)+'2021'!AL24 -> 12000 | V16: 0 | W16: =G16 -> 6000 | X16: =H16 -> 6000 | Y16: =I16 -> 4650 | Z16: 5429 | AA16: =K16 -> 5000 | AB16: 0 | AC16: 0 | AD16: 0 | AE16: 0 | AF16: 0 | AG16: 0 | AH16: 0 | AJ16: =SUM(W16:AH16) -> 27079
A17: 16 | B17: Krushna Rauda | C17: Qlik Sense | D17: 15000 | E17: 10000 | F17: Akbar sir | G17: NA | H17: =E17/23*9 -> 3913.0435 | I17: 10000 | J17: 10000 | K17: =E17/22*17 -> 7727.2727 | L17: 10000 | M17: 10000 | N17: 10000 | O17: 10000 | P17: =10000/21*17 -> 8095.2381 | Q17: =10000/23*18 -> 7826.087 | R17: 10000 | S17: =SUM(G17:R17) -> 97561.641 | T17: 60000 | U17: =SUM(H17:R17) -> 97561.641 | V17: 0 | W17: 0 | X17: 0 | Y17: 0 | Z17: 0 | AA17: 0 | AB17: 0 | AC17: 0 | AD17: 0 | AE17: 0 | AF17: 0 | AG17: 0 | AH17: 0 | AJ17: =SUM(W17:AH17) -> 0
A18: 17 | B18: Warfan ahmed khan | C18: Qlik Sense | D18: 14000 | E18: 6000 | F18: Akbar sir | G18: 6000 | H18: =E18/23*18 -> 4695.6522 | I18: =E18/20*10 -> 3000 | J18: =I18 -> 3000 | K18: 0 | L18: 0 | M18: =E18/20*14 -> 4200 | N18: =E18/23*19 -> 4956.5217 | O18: =E18-1272 -> 4728 | P18: 4000 | Q18: =6000/23*16.5 -> 4304.3478 | R18: =E18/21*8 -> 2285.7143 | S18: =SUM(G18:R18) -> 41170.236 | T18: =D18*2 -> 28000 | U18: 29000 | V18: 0 | W18: 0 | X18: =H18 -> 4695.6522 | Y18: =I18 -> 3000 | Z18: =J18 -> 3000 | AA18: =K18 -> 0 | AB18: =L18 -> 0 | AC18: =M18 -> 4200 | AD18: =N18 -> 4956.5217 | AE18: =O18 -> 4728 | ... AH18: =R18 -> 2285.7143 | AI18: a | AJ18: =SUM(W18:AH18) -> 35170.236
A19: 18 | B19: Saif Khan | C19: Qlik sense | D19: 10000 | E19: 6000 | F19: Akbar sir | G19: NA | H19: NA | I19: NA | J19: NA | K19: NA | L19: NA | M19: NA | N19: NA | O19: NA | P19: =E19/21*12 -> 3428.5714 | Q19: 6000 | R19: 6000 | S19: =SUM(G19:R19) -> 15428.571 | T19: =D19*2 -> 20000 | U19: =SUM(P19:R19) -> 15428.571 | V19: 0 | AF19: 0 | AG19: 0 | AH19: 0 | AJ19: =SUM(W19:AH19) -> 0
A20: 19 | B20: Sana Choudhary | C20: Sales | D20: 10000 | E20: 10000 | F20: Akbar sir | G20: 5000 | H20: 5000 | I20: 5000 | J20: =I20 -> 5000 | K20: 5000 | L20: 7000 | M20: 10000 | N20: =E20/23*20 -> 8695.6522 | O20: 10000 | P20: 10000 | Q20: 10000 | R20: =E20/22*16 -> 7272.7273 | S20: =SUM(G20:R20) -> 87968.379 | T20: =D20*2 -> 20000 | U20: ='2021'!AL29+'2022'!G20+'2022'!H20 -> 20727.273 | V20: 0 | W20: 0 | X20: 0 | Y20: =I20 -> 5000 | Z20: =J20 -> 5000 | AA20: =K20 -> 5000 | AB20: =L20 -> 7000 | AC20: 10000 | AD20: =N20 -> 8695.6522 | AE20: =O20 -> 10000 | AF20: =P20 -> 10000 | AG20: =Q20 -> 10000 | AH20: =R20 -> 7272.7273 | AI20: a | AJ20: =SUM(W20:AH20) -> 77968.379
A21: 20 | B21: Hajra Shaikh | C21: Sales | D21: 6000 | E21: 6000 | F21: Akbar sir | G21: 5000 | H21: =E21/23*19 -> 4956.5217 | I21: 5500 | J21: 5500 | K21: 6000 | L21: 4000 | M21: 4000 | N21: 5000 | O21: 6000 | P21: 3000 | Q21: 4000 | R21: 4000 | S21: =SUM(G21:R21) -> 56956.522 | T21: =D21*2 -> 12000 | U21: =SUM(G21:I21) -> 15456.522 | V21: 0 | W21: 0 | X21: 0 | Y21: 0 | Z21: 5500 | AA21: =K21 -> 6000 | AB21: =L21 -> 4000 | AC21: 4000 | AD21: =N21 -> 5000 | AE21: =O21 -> 6000 | AF21: =P21 -> 3000 | AG21: =Q21 -> 4000 | AH21: =R21 -> 4000 | AI21: a | AJ21: =SUM(W21:AH21) -> 41500
A22: 21 | B22: Shariqa Lashkar | C22: Sales | D22: 6000 | E22: 6000 | F22: Akbar sir | G22: NA | H22: NA | I22: NA | J22: NA | K22: NA | L22: NA | M22: NA | N22: NA | O22: 6000 | P22: 6000 | Q22: 4500 | R22: 6000 | S22: =SUM(G22:R22) -> 22500 | T22: =D22*2 -> 12000 | U22: =SUM(O22:R22) -> 22500 | V22: 0 | AE22: 0 | AF22: 0 | AG22: =Q22 -> 4500 | AH22: =R22 -> 6000 | AI22: a | AJ22: =SUM(W22:AH22) -> 10500
A23: 22 | B23: Tehmina Hamduley | C23: Sales | D23: 6000 | E23: 6000 | F23: Akbar sir | G23: NA | H23: NA | I23: NA | J23: NA | K23: NA | L23: NA | M23: NA | N23: NA | O23: 3000 | P23: 4500 | Q23: 4500 | R23: 4500 | S23: =SUM(G23:R23) -> 16500 | T23: =D23*2 -> 12000 | U23: =SUM(O23:R23) -> 16500 | V23: 0 | AE23: 0 | AF23: 0 | AG23: 0 | AH23: =R23 -> 4500 | AI23: a | AJ23: =SUM(W23:AH23) -> 4500
A24: 23 | B24: Yasmeen Shaikh | C24: Sales | D24: 6000 | E24: 6000 | F24: Akbar sir | G24: NA | H24: NA | I24: NA | J24: NA | K24: NA | L24: NA | M24: NA | N24: NA | O24: 6000 | P24: 6000 | Q24: 6000 | R24: 6000 | S24: =SUM(G24:R24) -> 24000 | T24: =D24*2 -> 12000 | U24: =SUM(O24:R24) -> 24000 | V24: 0 | AE24: 0 | AF24: 0 | AG24: =Q24 -> 6000 | AH24: =R24 -> 6000 | AI24: a | AJ24: =SUM(W24:AH24) -> 12000
A25: 24 | B25: Sadat sir | C25: Sales | D25: 3500AED | E25: 3500AED | F25: Akbar sir | G25: NA | H25: NA | I25: NA | J25: NA | K25: NA | L25: NA | M25: NA | N25: NA | O25: =3500/22*12 -> 1909.0909 | P25: 2000 | Q25: 2000 | R25: 0 | S25: =SUM(O25:R25) -> 5909.0909 | V25: 0 | AF25: 0 | AG25: 0 | AH25: 0 | AJ25: =SUM(W25:AH25) -> 0
A26: 25 | B26: Mohammad Rehanuddin | C26: Salesforce admin | D26: 52000 | E26: 5000 | F26: Akbar sir | G26: 1591 | H26: 5000 | I26: 5000 | J26: =I26 -> 5000 | K26: 5000 | L26: =E26/23*8 -> 1739.1304 | M26: 5000 | N26: 5000 | O26: 5000 | P26: 5000 | Q26: 5000 | R26: 5000 | S26: =SUM(G26:R26) -> 53330.13 | T26: =D26*2 -> 104000 | U26: ='On hold bonus'!B4+SUM(P26:R26) -> 105000 | V26: 0 | W26: =G26 -> 1591 | X26: =H26 -> 5000 | Y26: =I26 -> 5000 | Z26: =J26 -> 5000 | AA26: 5000 | AB26: 0 | AC26: 0 | AD26: 0 | AE26: 0 | AF26: 0 | AG26: 0 | AH26: 0 | AJ26: =SUM(W26:AH26) -> 21591
A27: 26 | B27: Basit Khan | C27: Salesforce admin | D27: 10000 | E27: 6000 | F27: Akbar sir | G27: NA | H27: NA | I27: NA | J27: NA | K27: NA | L27: NA | M27: NA | N27: NA | O27: =E27/22*17 -> 4636.3636 | P27: 6000 | Q27: 5000 | R27: 5000 | S27: =SUM(O27:R27) -> 20636.364 | T27: =D27*2 -> 20000 | U27: =SUM(O27:R27) -> 20636.364 | V27: 0 | AE27: 0 | AF27: 0 | AG27: 0 | AH27: 0 | AJ27: =SUM(W27:AH27) -> 0
A28: 27 | B28: Naeem imran | C28: Salesforce admin | D28: 10000 | E28: 6000 | F28: Akbar sir | G28: NA | H28: NA | I28: NA | J28: NA | K28: NA | L28: NA | M28: NA | N28: NA | O28: NA | P28: 6000 | Q28: 5000 | R28: 5000 | S28: =SUM(O28:R28) -> 16000 | T28: =D28*2 -> 20000 | U28: =SUM(P28:R28) -> 16000 | V28: 0 | W28: =G28 -> NA | X28: =H28 -> NA | Y28: =I28 -> NA | Z28: =J28 -> NA | AA28: =K28 -> NA | AB28: =L28 -> NA | AC28: =M28 -> NA | AD28: =N28 -> NA | ... AH28: =R28 -> 5000 | AJ28: =SUM(W28:AH28) -> 16000
A29: 28 | B29: Asbiya Sadaf | C29: Salesforce admin | D29: 10000 | E29: 6000 | F29: Akbar sir | G29: NA | H29: NA | I29: NA | J29: NA | K29: NA | L29: NA | M29: NA | N29: NA | O29: =E29/22*15 -> 4090.9091 | P29: 6000 | Q29: 5000 | R29: 6000 | S29: =SUM(O29:R29) -> 21090.909 | T29: =D29*2 -> 20000 | U29: =SUM(O29:R29) -> 21090.909 | V29: 0 | AE29: 0 | AF29: 0 | AG29: 0 | AH29: 0 | AJ29: =SUM(W29:AH29) -> 0
A30: 29 | B30: Saniya Shaikh | C30: Salesforce admin | D30: 6000 | E30: 10000 | F30: Akbar sir | G30: NA | H30: NA | I30: NA | J30: NA | K30: NA | L30: NA | M30: NA | N30: NA | O30: NA | P30: NA | Q30: NA | R30: 9000 | S30: =SUM(O30:R30) -> 9000 | T30: =D30*2 -> 12000 | U30: =SUM(O30:R30) -> 9000 | V30: 0 | AE30: 0 | AF30: 0 | AG30: 0 | AH30: 0 | AJ30: =SUM(W30:AH30) -> 0
A31: 30 | B31: Naheed | C31: Salesforce Technical | D31: 6000 | E31: 10000 | F31: Akbar sir | G31: NA | H31: NA | I31: NA | J31: NA | K31: NA | L31: NA | M31: =E31/20*7 -> 3500 | N31: 10000 | O31: 10000 | P31: 5000 | Q31: 7000 | R31: 5000 | S31: =SUM(O31:R31) -> 27000 | T31: =D31*2 -> 12000 | U31: =SUM(M31:R31) -> 40500 | V31: 0 | AC31: 0 | AD31: 0 | AE31: 0 | AF31: 0 | AG31: 0 | AH31: 0 | AJ31: =SUM(W31:AH31) -> 0
A32: 31 | B32: Nazmin | C32: Salesforce Technical | D32: 6000 | E32: 10000 | F32: Akbar sir | G32: NA | H32: NA | I32: NA | J32: NA | K32: NA | L32: NA | M32: =E32/20*5 -> 2500 | N32: 10000 | O32: 10000 | P32: 9000 | Q32: 10000 | R32: 8000 | S32: =SUM(O32:R32) -> 37000 | T32: =D32*2 -> 12000 | U32: =SUM(M32:R32) -> 49500 | V32: 0 | AC32: 0 | AD32: 0 | AE32: 0 | AF32: 0 | AG32: 0 | AH32: 0 | AJ32: =SUM(W32:AH32) -> 0
A33: 32 | B33: Akbar | C33: Salesforce Technical | D33: 6000 | E33: 10000 | F33: Akbar sir | G33: NA | H33: NA | I33: NA | J33: NA | K33: NA | L33: NA | M33: =E33/20*5 -> 2500 | N33: 10000 | O33: 10000 | P33: 5000 | Q33: 7000 | R33: 5000 | S33: =SUM(O33:R33) -> 27000 | T33: =D33*2 -> 12000 | U33: =SUM(M33:R33) -> 39500 | V33: 0 | AC33: 0 | AD33: 0 | AE33: 0 | AF33: 0 | AG33: 0 | AH33: 0 | AJ33: =SUM(W33:AH33) -> 0
A34: 33 | B34: Afroz Khan | C34: Salesforce Technical | D34: 10000 | E34: 6000 | F34: Akbar sir | G34: NA | H34: NA | I34: NA | J34: NA | K34: NA | L34: NA | M34: NA | N34: 6000 | O34: 6000 | P34: 6000 | Q34: 6000 | R34: 6000 | S34: =SUM(O34:R34) -> 24000 | T34: =D34*2 -> 20000 | U34: =SUM(O34:R34) -> 24000 | V34: 0 | AE34: 0 | AF34: 0 | AG34: 0 | AH34: 0 | AJ34: =SUM(W34:AH34) -> 0
A35: 34 | B35: Shaikh Zeeshan Shaikh Rafeeque | C35: Salesforce-Eienstein | D35: 40000 | E35: 10000 | F35: Akbar sir | G35: 5000 | H35: 5000 | I35: 5000 | J35: =I35 -> 5000 | K35: 5000 | L35: 5000 | M35: 5000 | N35: 5000 | O35: 10000 | P35: 10000 | Q35: 10000 | R35: =E35/21*12 -> 5714.2857 | S35: =SUM(G35:R35) -> 75714.286 | T35: =D35*2 -> 80000 | U35: ='On hold bonus'!B48 -> 108826 | W35: 0 | X35: 0 | Y35: 0 | Z35: 0 | AA35: 0 | AB35: 5000 | AC35: =M35 -> 5000 | AD35: =N35 -> 5000 | AE35: =O35 -> 10000 | AF35: =P35 -> 10000 | AG35: =Q35 -> 10000 | AH35: =R35 -> 5714.2857 | AI35: a | AJ35: =SUM(W35:AH35) -> 50714.286 | AK35: =S35-AB35-AC35-AD35-AE35-AF35-AG35-AH35 -> 25000 | AL35: 29826.087 | AN35: =SUM(AK35:AL35) -> 54826.087
A36: 35 | B36: Shaikh Samee | C36: Salesforce-Eienstein | D36: 25000 | E36: 5000 | F36: Akbar sir | G36: 4000 | H36: 4000 | I36: 4000 | J36: =D36/21*6 -> 7142.8571 | K36: 4000 | L36: 3500 | M36: 3500 | N36: 5000 | O36: 5000 | P36: 5000 | Q36: 5000 | R36: 5000 | S36: =SUM(G36:R36) -> 55142.857 | T36: =D36*2 -> 50000 | U36: ='2021'!AL42+G36+H36 -> 24782.609 | V36: 0 | W36: 0 | X36: 0 | Y36: =I36 -> 4000 | Z36: 3429 | AA36: =K36 -> 4000 | AB36: =L36 -> 3500 | AC36: =M36 -> 3500 | AD36: =N36 -> 5000 | AE36: =O36 -> 5000 | AF36: 0 | AG36: 0 | AH36: 15000 | AI36: a | AJ36: =SUM(W36:AH36) -> 43429
A37: 36 | B37: Minhaj mohammed | C37: Sharepoint | D37: 6000 | E37: 10000 | F37: Akbar sir | G37: NA | H37: NA | I37: NA | J37: NA | K37: NA | L37: 3000 | M37: 10000 | N37: 10000 | O37: 10000 | P37: 10000 | Q37: 10000 | R37: 7000 | S37: =SUM(G37:R37) -> 60000 | T37: =D37*2 -> 12000 | U37: =SUM(L37:R37) -> 60000 | V37: =0 -> 0 | AB37: 0 | AC37: 0 | AD37: 0 | AE37: 0 | AF37: 0 | AG37: 0 | AH37: 0 | AJ37: =SUM(W37:AH37) -> 0
A38: 37 | B38: Ansari Mohammed Arshduddin Mohammed Masooduddin | C38: SharePoint | D38: 30000 | E38: 5000 | F38: Akbar sir | G38: 6000 | H38: 6000 | I38: 6000 | J38: =I38 -> 6000 | K38: =J38 -> 6000 | L38: 6000 | M38: 6000 | N38: 6000 | O38: 5000 | P38: =E38/21*6 -> 1428.5714 | Q38: 5000 | R38: 4000 | S38: =SUM(G38:R38) -> 63428.571 | T38: =D38*2 -> 60000 | U38: =(28500-6000)+SUM(O38:R38) -> 37928.571 | V38: 0 | W38: =G38 -> 6000 | X38: =H38 -> 6000 | Y38: =I38 -> 6000 | Z38: =J38 -> 6000 | AA38: =K38 -> 6000 | AB38: =L38 -> 6000 | AC38: =M38 -> 6000 | AD38: =N38 -> 6000 | AE38: =O38 -> 5000 | AF38: 0 | AG38: 0 | AH38: 0 | AJ38: =SUM(W38:AH38) -> 53000
A39: 38 | B39: Nagma Khan | C39: SharePoint | D39: 17000 | E39: 10000 | F39: Akbar sir | G39: 10000 | H39: 10000 | I39: 10000 | J39: =I39 -> 10000 | K39: =J39 -> 10000 | L39: 10000 | M39: 10000 | N39: 10000 | O39: 10000 | P39: 10000 | Q39: 10000 | R39: 10000 | S39: =SUM(G39:R39) -> 120000 | T39: =D39*2 -> 34000 | U39: 36000 | V39: 0 | W39: 10000 | X39: =H39 -> 10000 | Y39: =I39 -> 10000 | Z39: =J39 -> 10000 | AA39: =K39 -> 10000 | AB39: =L39 -> 10000 | AC39: =M39 -> 10000 | AD39: =N39 -> 10000 | AE39: =O39 -> 10000 | ... AH39: =R39 -> 10000 | AI39: a | AJ39: =SUM(W39:AH39) -> 120000
A40: 39 | B40: Saba Shaikh | C40: SharePoint | D40: 50000 | E40: 5000 | F40: Akbar sir | G40: 10000 | H40: 10000 | I40: 8000 | J40: 8095 | K40: 10000 | L40: 10000 | M40: 10000 | N40: =E40/23*10 -> 2173.913 | O40: 9091 | P40: 5000 | Q40: 5000 | R40: =E40/21*18 -> 4285.7143 | S40: =SUM(G40:R40) -> 91645.627 | T40: =D40*2 -> 100000 | U40: =49261+SUM(P40:R40) -> 63546.714 | V40: 0 | W40: =G40 -> 10000 | X40: =H40 -> 10000 | Y40: =I40 -> 8000 | Z40: =J40 -> 8095 | AA40: =K40 -> 10000 | AB40: =L40 -> 10000 | AC40: 10000 | AD40: 0 | AE40: =O40 -> 9091 | AF40: 0 | AG40: 0 | AH40: 0 | AJ40: =SUM(W40:AH40) -> 75186
A41: 40 | B41: Rahmatullah | C41: SharePoint | D41: 28000 | E41: 5000 | F41: Akbar sir | G41: 4000 | H41: 4000 | I41: 4000 | J41: =I41 -> 4000 | K41: 4000 | L41: =E41/23*14 -> 3043.4783 | M41: 5000 | N41: 5000 | O41: 5000 | P41: 5000 | Q41: 5000 | R41: 5000 | S41: =SUM(G41:R41) -> 53043.478 | T41: =D41*2 -> 56000 | U41: =SUM(M41:R41) -> 30000 | V41: ='Hold bonus paid sheet'!C12 -> 32000 | W41: 0 | X41: 0 | Y41: 4000 | Z41: =J41 -> 4000 | AA41: =K41 -> 4000 | AB41: =L41 -> 3043.4783 | AC41: 0 | AD41: 0 | AE41: 0 | AF41: 0 | AG41: 0 | AH41: 0 | AJ41: =SUM(W41:AH41) -> 15043.478 | AK41: =S41-Y41-Z41-AA41-AB41 -> 38000 | AL41: =SUM('2021'!M36:R36) -> 24000 | AN41: =AK41+AL41-V41 -> 30000
A42: 41 | B42: Huzaif Khot | C42: SharePoint | D42: 10000 | E42: 6000 | F42: Akbar sir | G42: NA | H42: 5000 | I42: 6000 | J42: 10000 | K42: 10000 | L42: 6000 | M42: 6000 | N42: 6000 | O42: 6000 | P42: 6000 | Q42: 6000 | R42: 6000 | S42: =SUM(G42:R42) -> 73000 | T42: =SUM(H42:R42) -> 73000 | U42: =SUM(H42:R42) -> 73000 | V42: 0 | W42: 0 | X42: 0 | Y42: 0 | Z42: 0 | AA42: 0 | AB42: 0 | AC42: 0 | AD42: 0 | AE42: 0 | AF42: 0 | AG42: 0 | AH42: 0 | AJ42: =SUM(W42:AH42) -> 0
A43: 42 | B43: Noorullah Khan | C43: SharePoint | D43: 6000 | E43: 10000 | F43: Akbar sir | G43: NA | H43: 10000 | I43: 10000 | J43: 7000 | K43: 5000 | L43: 0 | M43: 4000 | N43: 5000 | O43: 5000 | P43: 10000 | Q43: 10000 | R43: =E43/21*10 -> 4761.9048 | S43: =SUM(G43:R43) -> 70761.905 | T43: =SUM(H43:R43) -> 70761.905 | U43: =SUM(H43:R43) -> 70761.905 | V43: 0 | W43: 0 | X43: 0 | Y43: 0 | Z43: 0 | AA43: 0 | AB43: 0 | AC43: 0 | AD43: 0 | AE43: 0 | AF43: 0 | AG43: 0 | AH43: 0 | AJ43: =SUM(W43:AH43) -> 0
A44: 43 | B44: Rameez Sufiyan | C44: Uipath | D44: 20000 | E44: 5000 | F44: Akbar sir | G44: 6000 | H44: 5000 | I44: 5000 | J44: =I44 -> 5000 | K44: 5000 | L44: 1000 | M44: 5000 | N44: =E44/23*10 -> 2173.913 | O44: 5000 | P44: 2500 | Q44: 5000 | R44: 5000 | S44: =SUM(G44:R44) -> 51673.913 | T44: =D44*2 -> 40000 | U44: 12000 | V44: 0 | W44: =G44 -> 6000 | X44: =H44 -> 5000 | Y44: =I44 -> 5000 | Z44: =J44 -> 5000 | AA44: =K44 -> 5000 | AB44: =L44 -> 1000 | AC44: =M44 -> 5000 | AD44: =N44 -> 2173.913 | ... AH44: =R44 -> 5000 | AI44: a | AJ44: =SUM(W44:AH44) -> 51673.913
A45: 44 | B45: Zishan shaikh | C45: Uipath | D45: 6000 | E45: 10000 | F45: Akbar sir | G45: NA | H45: NA | I45: NA | J45: NA | K45: NA | L45: 7000 | M45: 10000 | N45: 10000 | O45: 10000 | P45: 10000 | Q45: 10000 | R45: =E45/21*6 -> 2857.1429 | S45: =SUM(G45:R45) -> 59857.143 | U45: =SUM(L45:R45) -> 59857.143 | V45: 0 | AB45: 0 | AC45: 0 | AD45: 0 | AE45: 0 | AF45: 0 | AG45: 0 | AH45: 0 | AJ45: =SUM(W45:AH45) -> 0
A46: 45 | B46: Abdul Baseet Baig | C46: Uipath | D46: 6000 | E46: 10000 | F46: Akbar sir | G46: NA | H46: NA | I46: NA | J46: NA | K46: NA | L46: NA | M46: NA | N46: NA | O46: NA | P46: NA | Q46: =10000/23*17 -> 7391.3043 | R46: 5000 | U46: =Q46+R46 -> 12391.304 | V46: 0 | W46: 0 | X46: 0 | Y46: 0 | Z46: 0 | AA46: 0 | AB46: 0 | AC46: 0 | AD46: 0 | AE46: 0 | AF46: 0 | AG46: 0 | AH46: 0
A47: 46 | B47: Shaikh Asmina Mohd Aslam | C47: Salesforce Technical | D47: 20000 | E47: 5000 | F47: Akbar sir | G47: 4000 | H47: 4000 | I47: 4000 | J47: =I47 -> 4000 | K47: =E47/22*10.5 -> 2386.3636 | L47: 4000 | M47: 4750 | N47: 5000 | O47: 5000 | P47: 5000 | Q47: 5000 | R47: 5000 | S47: =SUM(G47:R47) -> 52136.364 | T47: =D47*2 -> 40000 | U47: ='On hold bonus'!B14+SUM(M47:R47) -> 56750 | V47: 0 | W47: 0 | X47: =H47 -> 4000 | Y47: =I47 -> 4000 | Z47: =J47 -> 4000 | AA47: =K47 -> 2386.3636 | AB47: =L47 -> 4000 | AC47: 0 | AD47: 0 | AE47: 0 | AF47: 0 | AG47: 0 | AH47: 0 | AJ47: =SUM(W47:AH47) -> 18386.364 | AK47: =S47-X47-Y47-Z47-AA47-AB47 -> 33750 | AL47: ='2021'!S54 -> 23000 | AN47: =AK47+AL47 -> 56750
A48: 47 | B48: Shazeena aslam motani | C48: Financial Force-PSA | D48: 25000 | E48: 8000 | F48: Amir Dalvi | G48: 6000 | H48: 6000 | I48: =E48/20*5 -> 2000 | J48: 6000 | K48: 6000 | L48: 8000 | M48: 8000 | N48: 7000 | O48: 8000 | P48: 6000 | Q48: 6000 | R48: =E48/21*6 -> 2285.7143 | S48: =SUM(G48:R48) -> 71285.714 | T48: =D48*2 -> 50000 | U48: 67000 | V48: 0 | W48: =G48 -> 6000 | X48: =H48 -> 6000 | Y48: 1500 | Z48: =J48 -> 6000 | AA48: =K48 -> 6000 | AB48: 0 | AC48: 0 | AD48: 0 | AE48: 0 | AF48: =P48 -> 6000 | AG48: =Q48 -> 6000 | AH48: =R48 -> 2285.7143 | AI48: a | AJ48: =SUM(W48:AH48) -> 39785.714
A49: 48 | B49: Arshi Sayyed | C49: Financial Force-PSA | D49: 10000 | E49: 6000 | F49: Rehan | G49: NA | H49: NA | I49: NA | J49: =E49/21*7 -> 2000 | K49: 6000 | L49: 6000 | M49: 6000 | N49: 6000 | O49: 6000 | P49: 6000 | Q49: =6000/23*9 -> 2347.8261 | R49: =E49/21*16 -> 4571.4286 | S49: =SUM(G49:R49) -> 44919.255 | U49: =SUM(J49:R49) -> 44919.255 | V49: 0 | W49: 0 | X49: 0 | Y49: 0 | Z49: 0 | AA49: 0 | AB49: 0 | AC49: 0 | AD49: 0 | AE49: 0 | AF49: 0 | AG49: 0 | AH49: 0 | AJ49: =SUM(W49:AH49) -> 0
A50: 49 | B50: Saeed Shaikh | C50: Financial Force-PSA | D50: 12000 | E50: 4000 | F50: Rehan | G50: 4000 | H50: 4000 | I50: 4000 | J50: 4000 | K50: 4000 | L50: 3500 | M50: 3500 | N50: 3500 | O50: 0 | P50: 0 | Q50: =4000/23*14 -> 2434.7826 | R50: 0 | S50: =SUM(G50:R50) -> 32934.783 | T50: =D50*2 -> 24000 | U50: 26500 | V50: 0 | W50: 0 | X50: 0 | Y50: 0 | Z50: 0 | AA50: =K50 -> 4000 | AB50: 0 | AC50: 0 | AD50: 0 | AE50: =O50 -> 0 | AF50: 0 | AG50: =Q50 -> 2434.7826 | AH50: =R50 -> 0 | AJ50: =SUM(W50:AH50) -> 6434.7826
A51: 50 | B51: Mehboob | C51: Salesforce-Eienstein | D51: 10000 | E51: 6000 | F51: Rehan | G51: NA | H51: NA | I51: NA | J51: NA | K51: NA | L51: NA | M51: NA | N51: NA | O51: NA | P51: 2000 | Q51: 5500 | R51: =E51/21*16 -> 4571.4286 | S51: =SUM(O51:R51) -> 12071.429 | T51: =D51*2 -> 20000 | U51: =SUM(P51:R51) -> 12071.429 | V51: 0 | AF51: 0 | AG51: 0 | AH51: 0 | AJ51: =SUM(W51:AH51) -> 0
A52: 51 | B52: imran patel | C52: Salesforce-Eienstein | D52: 25000 | E52: 10000 | F52: Rehan | G52: 4000 | H52: 4000 | I52: 4000 | J52: =I52 -> 4000 | K52: 4000 | L52: 4000 | M52: 0 | N52: 4000 | O52: =4000/22*8 -> 1454.5455 | P52: =10000/21*12 -> 5714.2857 | Q52: 10000 | R52: =E52/21*10 -> 4761.9048 | S52: =SUM(G52:R52) -> 49930.736 | T52: =D52*2 -> 50000 | U52: =24000+SUM(P52:R52) -> 44476.19 | V52: 0 | W52: 0 | X52: 0 | Y52: 0 | Z52: 0 | AA52: 0 | AB52: =M52 -> 0 | AC52: =M52 -> 0 | AD52: =N52 -> 4000 | AE52: =O52 -> 1454.5455 | AF52: =4000/21*9 -> 1714.2857 | AG52: 0 | AH52: 0 | AJ52: =SUM(W52:AH52) -> 7168.8312
A53: 52 | B53: Anam Khan | C53: Sharepoint | D53: 6000 | E53: 10000 | F53: Saba | G53: NA | H53: NA | I53: NA | J53: NA | K53: NA | L53: NA | M53: NA | N53: NA | O53: =E53/22*6 -> 2727.2727 | P53: 4000 | Q53: 5000 | R53: 5000 | S53: =SUM(G53:R53) -> 16727.273 | T53: =SUM(O53:R53) -> 16727.273 | U53: =SUM(O53:R53) -> 16727.273 | V53: 0 | AE53: 0 | AF53: 0 | AG53: 0 | AH53: 0 | AJ53: =SUM(W53:AH53) -> 0
A54: 53 | B54: Sidra Ansari | C54: SharePoint | D54: 6000 | E54: 10000 | F54: Saba | G54: NA | H54: 10000 | I54: 10000 | J54: 8000 | K54: 5000 | L54: 3000 | M54: 5000 | N54: 0 | O54: 3000 | P54: 7000 | Q54: 10000 | R54: =E54/21*14 -> 6666.6667 | S54: =SUM(G54:R54) -> 67666.667 | T54: =SUM(H54:R54) -> 67666.667 | U54: =SUM(H54:R54) -> 67666.667 | V54: 0 | W54: 0 | X54: 0 | Y54: 0 | Z54: 0 | AA54: 0 | AB54: 0 | AC54: 0 | AD54: 0 | AE54: 0 | AF54: 0 | AG54: 0 | AH54: 0 | AJ54: =SUM(W54:AH54) -> 0
A55: 54 | B55: Huzaif Khan | C55: Salesforce admin | D55: 6000 | E55: 10000 | F55: Shahid | G55: NA | H55: NA | I55: NA | J55: NA | K55: NA | L55: 10000 | M55: 10000 | N55: 10000 | O55: 10000 | P55: 10000 | Q55: 8000 | R55: =E55/21*6 -> 2857.1429 | S55: =SUM(G55:R55) -> 60857.143 | T55: =SUM(L55:R55) -> 60857.143 | U55: =SUM(L55:R55) -> 60857.143 | V55: 0 | AB55: 0 | AC55: 0 | AD55: 0 | AE55: 0 | AF55: 0 | AG55: 0 | AH55: 0 | AJ55: =SUM(W55:AH55) -> 0
A56: 55 | B56: Maaz Shaokat Choughle | C56: Salesforce admin | D56: 47000 | E56: 5000 | F56: Shahid | G56: 5000 | H56: 2000 | I56: 5000 | J56: 5000 | K56: 5000 | L56: 4000 | M56: 5000 | N56: =E56/23*18 -> 3913.0435 | O56: 5000 | P56: 3500 | Q56: 4000 | R56: 5000 | S56: =SUM(G56:R56) -> 52413.043 | T56: =D56*2 -> 94000 | U56: =SUM(P56:R56) -> 12500 | V56: ='Hold bonus paid sheet'!C4 -> 63454 | W56: 0 | X56: 0 | Y56: 0 | Z56: =J56 -> 5000 | AA56: =K56 -> 5000 | AB56: =L56 -> 4000 | AC56: =M56 -> 5000 | AD56: =N56 -> 3913.0435 | AE56: =O56 -> 5000 | AF56: 0 | AG56: 0 | AH56: 0 | AJ56: =SUM(W56:AH56) -> 27913.043
A57: 56 | B57: Rijvana | C57: Salesforce admin | D57: 6000 | E57: 10000 | F57: Shahid | G57: NA | H57: NA | I57: 8000 | J57: 10000 | K57: 10000 | L57: 10000 | M57: 10000 | N57: 9000 | O57: 10000 | P57: 9000 | Q57: 8000 | R57: =E57/21*6 -> 2857.1429 | S57: =SUM(G57:R57) -> 86857.143 | T57: =SUM(I57:R57) -> 86857.143 | U57: =SUM(I57:R57) -> 86857.143 | V57: 0 | W57: 0 | X57: 0 | Y57: 0 | Z57: 0 | AA57: 0 | AB57: 0 | AC57: 0 | AD57: 0 | AE57: 0 | AF57: 0 | AG57: 0 | AH57: 0 | AJ57: =SUM(W57:AH57) -> 0
A58: 57 | B58: Ansari Mohd Ateef | C58: Salesforce admin | D58: 30000 | E58: 5000 | F58: Shahid | G58: 5000 | H58: 0 | I58: 2500 | J58: 5000 | K58: 4000 | L58: 4000 | M58: 5000 | N58: 4000 | O58: 5000 | P58: 2500 | Q58: =5000/23*14 -> 3043.4783 | R58: 5000 | S58: =SUM(G58:R58) -> 45043.478 | T58: =D58*2 -> 60000 | U58: =SUM(G58:L58)+'2020'!AH25+'2021'!AL46 -> 61339.13 | V58: 0 | W58: 0 | X58: 0 | Y58: 0 | Z58: 0 | AA58: 0 | AB58: 0 | AC58: =M58 -> 5000 | AD58: 0 | AE58: =O58 -> 5000 | AF58: =P58 -> 2500 | AG58: =Q58 -> 3043.4783 | AH58: =R58 -> 5000 | AI58: a | AJ58: =SUM(W58:AH58) -> 20543.478
A59: 58 | B59: Swati Amode | C59: Salesforce admin | D59: 25000 | E59: 5000 | F59: Shahid | G59: 4000 | H59: 4000 | I59: =4000/20*15.5 -> 3100 | J59: 3000 | K59: 3000 | L59: =4000/23*15 -> 2608.6957 | M59: =4000/20*13 -> 2600 | N59: 3500 | O59: =E59/22*16.5 -> 3750 | P59: 4000 | Q59: 3000 | R59: 3000 | S59: =SUM(G59:R59) -> 39558.696 | T59: =D59*2 -> 50000 | U59: =SUM(P59:R59) -> 10000 | V59: ='Hold bonus paid sheet'!C3 -> 26100 | W59: 4000 | X59: 4000 | Y59: 3100 | Z59: 3000 | AA59: =K59 -> 3000 | AB59: =L59 -> 2608.6957 | AC59: =M59 -> 2600 | AD59: =N59 -> 3500 | AE59: =O59 -> 3750 | AF59: =P59 -> 4000 | AG59: =Q59 -> 3000 | AH59: =R59 -> 3000 | AJ59: =SUM(W59:AH59) -> 39558.696
A60: 59 | B60: Sohail Inamdar | C60: Salesforce admin | D60: 30000 | E60: 5000 | F60: Shahid | G60: 10000 | H60: =E60/23*8 -> 1739.1304 | I60: 0 | J60: 5000 | K60: 5000 | L60: =E60/23*11 -> 2391.3043 | M60: =E60/20*16 -> 4000 | N60: 5000 | O60: 5000 | P60: 3500 | Q60: 5000 | R60: 5000 | S60: =SUM(G60:R60) -> 51630.435 | T60: =D60*2 -> 60000 | U60: =SUM(H60:N60)+'2021'!AL45 -> 28630.435 | V60: 0 | W60: 10000 | X60: 0 | Y60: =I60 -> 0 | Z60: 0 | AA60: 0 | AB60: 0 | AC60: 0 | AD60: 0 | AE60: =O60 -> 5000 | AF60: =P60 -> 3500 | AG60: 0 | AH60: 0 | AJ60: =SUM(W60:AH60) -> 18500
A61: 60 | B61: Mahek Shaikh | C61: Salesforce-Eienstein | D61: 6000 | E61: 10000 | F61: Zeeshan Shaikh | G61: NA | H61: NA | I61: NA | J61: =E61/21*14 -> 6666.6667 | K61: 10000 | L61: 10000 | M61: 6000 | N61: 10000 | O61: 10000 | P61: 10000 | Q61: 0 | R61: =E61/21*15 -> 7142.8571 | S61: =SUM(G61:R61) -> 69809.524 | T61: =D61*2 -> 12000 | U61: =SUM(J61:R61) -> 69809.524 | V61: 0 | W61: 0 | X61: 0 | Y61: 0 | Z61: 0 | AA61: 0 | AB61: 0 | AC61: 0 | AD61: 0 | AE61: 0 | AF61: 0 | AG61: 0 | AH61: 0 | AJ61: =SUM(W61:AH61) -> 0
A62: 61 | B62: Humera Shaikh | C62: Salesforce-Eienstein | D62: 6000 | E62: 10000 | F62: Zeeshan Shaikh | G62: NA | H62: NA | I62: 8000 | J62: =E62/21*16 -> 7619.0476 | K62: 10000 | L62: =E62/23*17 -> 7391.3043 | M62: 6000 | N62: 10000 | O62: 10000 | P62: 10000 | Q62: 10000 | R62: 10000 | S62: =SUM(G62:R62) -> 89010.352 | T62: =D62*2 -> 12000 | U62: =SUM(I62:R62) -> 89010.352 | V62: 0 | W62: 0 | X62: 0 | Y62: 0 | Z62: 0 | AA62: 0 | AB62: 0 | AC62: 0 | AD62: 0 | AE62: 0 | AF62: 0 | AG62: 0 | AH62: 0 | AJ62: =SUM(W62:AH62) -> 0
A63: 62 | B63: Saleha Khan | C63: Salesforce-Eienstein | D63: 6000 | E63: 10000 | F63: Zeeshan Shaikh | G63: NA | H63: NA | I63: NA | J63: NA | K63: NA | L63: NA | M63: NA | N63: 10000 | O63: 10000 | P63: 10000 | Q63: 10000 | R63: 10000 | S63: =SUM(G63:R63) -> 50000 | T63: =D63*2 -> 12000 | U63: =SUM(K63:R63) -> 50000 | V63: 0 | W63: 0 | X63: 0 | Y63: 0 | Z63: 0 | AA63: 0 | AB63: 0 | AC63: 0 | AD63: 0 | AE63: 0 | AF63: 0 | AG63: 0 | AH63: 0 | AJ63: =SUM(W63:AH63) -> 0
B64: Total | D64: =SUM(D2:D63) -> 1027000 | E64: =SUM(E2:E63) -> 468000 | F64: =SUM(F2:F63) -> 0 | G64: =SUM(G2:G63) -> 166591 | H64: =SUM(H2:H63) -> 186934.52 | I64: =SUM(I2:I63) -> 205250 | J64: =SUM(J2:J63) -> 233452.57 | K64: =SUM(K2:K63) -> 239113.64 | ... O64: =SUM(O2:O63) -> 344659.91 | P64: =SUM(P2:P58) -> 315428.57 | Q64: =SUM(Q2:Q58) -> 331891.3 | S64: =SUM(S2:S58) -> 2770735.6 | T64: =SUM(T2:T58) -> 2189870.1 | V64: =SUM(V2:V58) -> 253453 | W64: =SUM(W2:W58) -> 62591 | X64: =SUM(X2:X58) -> 94195.652 | Y64: =SUM(Y2:Y58) -> 103350 | Z64: =SUM(Z2:Z58) -> 122453 | AA64: =SUM(AA2:AA58) -> 124386.36 | AB64: =SUM(AB2:AB58) -> 93413.043 | AC64: =SUM(AC2:AC58) -> 102700 | ... AG64: =SUM(AG2:AG58) -> 99543.478 | AH64: =SUM(AH2:AH63) -> 110746.75 | AJ64: =SUM(W64:AH64) -> 1186213.6
AD65: 4000 | AH65: 2286
AD66: =AD2+AD3+AD4+AD5+AD6+AD9+AD8+AD10+'To beDeleted'!AE56+'To beDeleted'!AD61+'To beDeleted'!AF59+'To beDeleted'!AD60+AD20+AD21+'To beDeleted'!AE57+AD18+'To beDeleted'!AE53+AD37+AD38+AD42+AD43+AD44+AD49+AD48+AD53+AD58+AD65 -> 88695.739 | AH66: 5714
AH67: 4500
AH68: =AH65+AH66+AH67 -> 12500
C69: after 1 year will be pay bonus | AH69: =AH64-AH68 -> 98246.753
C70: Samee Quarterly bonus | AH70: 13286
C71: Sadat sir UAE | Y71: 11500 | AH71: =AH70-AH69 -> -84960.753
C72: Ziaullah propotion bonus | Y72: 24000
Y73: 23130
Y74: =SUM(Y71:Y73) -> 58630 | Z74: =Y74-30000 -> 28630

Sheet 2023
A1: Sr No | B1: Name of the Employee | C1: Technology | D1: Salary | E1: Bonus amount | F1: Commitment Start date | G1: Commitment End date | H1: Reporting manager | I1: Jan | J1: Feb | K1: Mar | L1: Apr | M1: May | N1: June | O1: Jul | P1: Aug | Q1: Sep | R1: Oct | S1: Nov | T1: Dec | U1: This year 2023 bonus amount | V1: Deposit bonus Amount along with us till 2023 paid after notice period /Contract | W1: To be Paid with Salary in Jan 2023 | X1: To be Paid with Salary in Feb 2023 | Y1: To be Paid with Salary in Mar 2023 | Z1: To be Paid with Salary in Apr 2023 | AA1: To be Paid with Salary in May 2023 | AB1: To be Paid with Salary in Jun 2023 | AC1: To be Paid with Salary in July 2023 | AD1: To be Paid with Salary in Aug 2023 | AE1: To be Paid with Salary in Sep 2023 | AF1: To be Paid with Salary in Oct 2023 | AG1: To be Paid with Salary in Nov 2023 | AH1: To be Paid with Salary in Dec 2023 | AI1: Total bonus given in 2023 amount | AJ1: remaining 2023 | AK1: remaining 2022 | AL1: remaining 2021 | AM1: remaining 2020 | AN1: Total Balance need to pay after notice period
A2: 1 | B2: Ansari Yasmeen | C2: Accounts | D2: 10000 | E2: 8000 | H2: Akbar Sir | I2: 8000 | J2: 4000 | K2: 6000 | L2: 8000 | M2: 4000 | N2: 8000 | O2: 8000 | P2: 4000 | Q2: 6000 | R2: 8000 | S2: 8000 | T2: 8000 | U2: =SUM(I2:T2) -> 80000 | V2: ='[1]2022'!U2 -> #REF! | W2: =I2 -> 8000 | X2: =J2 -> 4000 | Y2: =K2 -> 6000 | Z2: =L2 -> 8000 | AA2: =M2 -> 4000 | AB2: =N2 -> 8000 | AC2: =O2 -> 8000 | AD2: =P2 -> 4000 | ... AH2: =T2 -> 8000 | AI2: =SUM(W2:AH2) -> 80000 | AJ2: =U2-W2-X2-Y2-Z2-AA2-AB2-AC2-AD2-AE2-AF2-AG2-AH2 -> 0 | AK2: #REF! | AL2: #REF! | AN2: =AK2+AL2+AM2 -> #VALUE!
A3: 2 | B3: Tanzeela Shaikh | C3: Accounts | D3: 6000 | E3: 6000 | H3: Akbar Sir | I3: NA | J3: NA | K3: 6000 | L3: 6000 | M3: 6000 | N3: 5500 | O3: 6000 | P3: 6000 | Q3: 6000 | R3: 6000 | S3: =E3/23*17 -> 4434.7826 | T3: 6000 | U3: =SUM(I3:T3) -> 57934.783 | AA3: =M3 -> 6000 | AB3: 5500 | AC3: =O3 -> 6000 | AD3: =P3 -> 6000 | AE3: =Q3 -> 6000 | AF3: =R3 -> 6000 | AG3: =S3 -> 4434.7826 | AH3: =T3 -> 6000
A4: 3 | B4: Sherkhan Misbah ismail | C4: Accounts | D4: 13000 | E4: 8000 | H4: Akbar Sir | I4: 8000 | J4: 8000 | K4: =E4/20*15 -> 6000 | L4: 8000 | M4: 0 | N4: 8000 | O4: 8000 | P4: 8000 | Q4: 8000 | R4: 8000 | S4: 8000 | T4: 8000 | U4: =SUM(I4:T4) -> 86000 | V4: ='2022'!AN3 -> 20045.455 | W4: =I4 -> 8000 | X4: =J4 -> 8000 | Y4: =K4 -> 6000 | Z4: =L4 -> 8000 | AA4: =M4 -> 0 | AB4: =N4 -> 8000 | AC4: =O4 -> 8000 | AD4: =P4 -> 8000 | ... AH4: =T4 -> 8000 | AI4: =SUM(W4:AH4) -> 86000 | AJ4: =U4-W4-X4-Y4-Z4-AA4-AB4-AC4-AD4-AE4-AF4-AG4-AH4 -> 0 | AK4: ='2022'!G3 -> 5000 | AL4: ='2021'!S3 -> 15045.455 | AM4: 0 | AN4: =AK4+AL4+AM4 -> 20045.455
A5: 4 | B5: Farheen Sultanpuri | C5: Accounts | D5: 6000 | E5: 6000 | H5: Akbar Sir | I5: NA | J5: NA | K5: NA | L5: NA | M5: NA | N5: NA | O5: 6000 | P5: 6000 | Q5: 6000 | R5: 6000 | S5: 6000 | T5: 6000 | U5: =SUM(I5:T5) -> 36000 | V5: =SUM(O5:P5) -> 12000 | W5: 0 | X5: 0 | Y5: 0 | Z5: 0 | AA5: 0 | AB5: 0 | AC5: 0 | AD5: 0 | AE5: =Q5 -> 6000 | AF5: =R5 -> 6000 | AG5: =S5 -> 6000 | AH5: =T5 -> 6000 | AI5: =SUM(W5:AH5) -> 24000 | AJ5: =SUM(O5:P5) -> 12000 | AK5: 0 | AL5: 0 | AM5: 0 | AN5: =SUM(AJ5:AM5) -> 12000
A6: 5 | B6: Shaikh Tareque | C6: Angular | D6: 40000 | E6: 10000 | F6: 44798 | G6: 45163 | H6: Akbar Sir | I6: 0 | J6: 0 | K6: 0 | L6: 10000 | M6: 10000 | N6: 10000 | O6: =E6/21*12 -> 5714.2857 | P6: 10000 | Q6: 2000 | R6: 2000 | S6: 5000 | T6: 5000 | U6: =SUM(I6:T6) -> 59714.286 | V6: ='[1]2022'!U6 -> #REF! | W6: =I6 -> 0 | X6: =J6 -> 0 | Y6: =K6 -> 0 | Z6: =L6 -> 10000 | AA6: =M6 -> 10000 | AB6: =N6 -> 10000 | AC6: =O6 -> 5714.2857 | AD6: =P6 -> 10000 | AE6: =Q6 -> 2000 | AI6: =SUM(W6:AH6) -> 47714.286 | AJ6: =U6-W6-X6-Y6-Z6-AA6-AB6-AC6-AD6-AE6-AF6-AG6-AH6 -> 12000 | AK6: ='[1]2022'!AK7 -> #REF! | AL6: ='[1]2021'!S6-'[1]2021'!AD6-'[1]2021'!AE6-'[1]2021'!AF6-'[1]2021'!AG6-'[1]2021'!AH6-'[1]2021'!AI6-'[1]2021'!AJ6 -> #REF! | AN6: =AK6+AL6+AM6 -> #REF!
A7: 6 | B7: Imran Ahmed | C7: Angular | D7: 25000 | E7: 5000 | F7: 44830 | G7: 45195 | H7: Akbar Sir | I7: =E7/22*12 -> 2727.2727 | J7: 5000 | K7: 5000 | L7: 5000 | M7: 5000 | N7: 5000 | O7: 5000 | P7: 5000 | Q7: =E7/21*9 -> 2142.8571 | R7: 5000 | S7: 5000 | T7: 5000 | U7: =SUM(I7:T7) -> 54870.13 | V7: ='[1]2022'!U4 -> #REF! | W7: =I7 -> 2727.2727 | X7: =J7 -> 5000 | Y7: =K7 -> 5000 | Z7: =L7 -> 5000 | AA7: =M7 -> 5000 | AB7: =N7 -> 5000 | AC7: =O7 -> 5000 | AD7: =P7 -> 5000 | AE7: =Q7 -> 2142.8571 | AI7: =SUM(W7:AH7) -> 39870.13 | AJ7: =U7-W7-X7-Y7-Z7-AA7-AB7-AC7-AD7-AE7-AF7-AG7-AH7 -> 15000 | AK7: #REF! | AL7: #REF! | AM7: #REF! | AN7: =AK7+AL7+AM7 -> #VALUE!
A8: 7 | B8: Khan Noorul Hasan | C8: E-automate | D8: 30000 | E8: 5000 | F8: 44799 | G8: 45164 | H8: Akbar Sir | I8: 0 | J8: 5000 | K8: 5000 | L8: 5000 | M8: 0 | N8: 5000 | O8: 5000 | P8: 5000 | Q8: 5000 | R8: 5000 | S8: =E8/23*19 -> 4130.4348 | T8: =E8/20*8 -> 2000 | U8: =SUM(I8:T8) -> 46130.435 | V8: ='[1]2022'!U7 -> #REF! | W8: =I8 -> 0 | AI8: =SUM(W8:AH8) -> 0 | AJ8: =U8-W8-X8-Y8-Z8-AA8-AB8-AC8-AD8-AE8-AF8-AG8-AH8 -> 46130.435 | AN8: =AK8+AL8+AM8 -> 0
A9: 8 | B9: Alfahad Shaikh | C9: E-automate | D9: 6000 | E9: 4000 | F9: 45271 | G9: 45819 | H9: Akbar Sir | I9: NA | J9: NA | K9: NA | L9: NA | M9: NA | N9: NA | O9: NA | P9: NA | Q9: NA | R9: NA | S9: 5000 | T9: =E9/25*11 -> 1760 | U9: =SUM(I9:T9) -> 6760 | W9: =S9 -> 5000 | AG9: =S9 -> 5000
A10: 9 | B10: Arshi Sayyed | C10: Financial Force-PSA | D10: 10000 | E10: 6000 | F10: 44665 | G10: 45030 | H10: Akbar Sir | I10: 0 | J10: =E10/23*15.5 -> 4043.4783 | K10: 4000 | L10: 3000 | M10: 4900 | N10: 5700 | O10: =E10-1800 -> 4200 | P10: 5500 | Q10: 0 | R10: =E10/22*15 -> 4090.9091 | S10: 0 | T10: =E10/20*7 -> 2100 | U10: =SUM(I10:T10) -> 37534.387 | V10: ='[1]2022'!U49 -> #REF! | W10: =I10 -> 0 | AI10: =SUM(W10:AH10) -> 0 | AJ10: =U10-W10-X10-Y10-Z10-AA10-AB10-AC10-AD10-AE10-AF10-AG10-AH10 -> 37534.387 | AK10: =V10 -> #REF! | AN10: =AJ10+AK10+AL10+AM10 -> #REF!
A11: 10 | B11: Yasir khan | C11: Microsoft CRM | D11: 6000 | E11: 10000 | F11: 45056 | G11: 45606 | H11: Akbar Sir | I11: NA | J11: NA | K11: NA | L11: NA | M11: =E11/22*12 -> 5454.5455 | N11: 7000 | O11: 10000 | P11: =E11/23*19 -> 8260.8696 | Q11: =E11/21*12 -> 5714.2857 | R11: 4000 | S11: 7000 | T11: 10000 | U11: =SUM(I11:T11) -> 57429.701
A12: 11 | B12: Naeem Imran | C12: Microsoft CRM | D12: 10000 | E12: 6000 | F12: 44830 | G12: 45194 | H12: Akbar Sir | I12: 5000 | J12: =E12/23*8 -> 2086.9565 | K12: 6000 | L12: 5000 | M12: 3000 | N12: 0 | O12: 0 | P12: 4000 | Q12: 4000 | R12: =E12/22*14 -> 3818.1818 | S12: 3000 | T12: =E12/25*21 -> 5040 | U12: =SUM(I12:T12) -> 40945.138 | V12: ='[1]2022'!U28 -> #REF! | W12: =I12 -> 5000 | X12: =J12 -> 2086.9565 | Y12: =K12 -> 6000 | Z12: =L12 -> 5000 | AA12: =M12 -> 3000 | AB12: =N12 -> 0 | AC12: =O12 -> 0 | AD12: =P12 -> 4000 | AE12: =Q12 -> 4000 | AI12: =SUM(W12:AH12) -> 29086.957 | AJ12: =U12-W12-X12-Y12-Z12-AA12-AB12-AC12-AD12-AE12-AF12-AG12-AH12 -> 11858.182 | AN12: =AK12+AL12+AM12 -> 0
A13: 12 | B13: Hamza khot | C13: Microsoft CRM | D13: 6000 | E13: 10000 | F13: 45056 | G13: 45606 | H13: Akbar Sir | I13: NA | J13: NA | K13: NA | L13: NA | M13: =E13/22*12 -> 5454.5455 | N13: 10000 | O13: 10000 | P13: 10000 | Q13: 10000 | R13: 10000 | S13: =R13/23*17 -> 7391.3043 | T13: 10000 | U13: =SUM(I13:T13) -> 72845.85
A14: 13 | B14: Irfan Shaikh | C14: Microsoft CRM | D14: 40000 | E14: 5000 | F14: 44838 | G14: 45202 | H14: Akbar Sir | I14: NA | J14: NA | K14: NA | L14: NA | M14: NA | N14: NA | O14: NA | P14: NA | Q14: NA | R14: =E14/22*6 -> 1363.6364 | S14: =E14/23*13 -> 2826.087 | T14: =E14/20*15 -> 3750 | U14: =SUM(I14:T14) -> 7939.7233
A15: 14 | B15: Osama Khan | C15: Microsoft CRM | D15: 35000 | E15: 5000 | F15: 44812 | G15: 45177 | H15: Akbar Sir | I15: 5000 | J15: 2000 | K15: NA | L15: NA | M15: NA | N15: NA | O15: NA | P15: NA | Q15: NA | R15: 2500 | S15: 2500 | T15: 5000 | U15: =SUM(I15:T15) -> 17000 | Y15: =K15 -> NA | Z15: =L15 -> NA | AA15: =M15 -> NA | AB15: =N15 -> NA | AC15: =O15 -> NA | AD15: =P15 -> NA | AE15: =Q15 -> NA | AL15: =AI15+AJ15+AK15 -> 0
A16: 15 | B16: Amir Khan | C16: Microsoft CRM | D16: 25000 | E16: 5000 | F16: 44817 | G16: 45182 | H16: Akbar Sir | I16: =E16/22*13 -> 2954.5455 | J16: 0 | K16: 10000 | L16: 10000 | M16: 10000 | N16: 10000 | O16: 10000 | P16: 10000 | Q16: 10000 | R16: 2500 | S16: 0 | T16: 2500 | U16: =SUM(I16:T16) -> 77954.545 | V16: ='[1]2022'!U10 -> #REF! | AF16: =R16 -> 2500 | AG16: =S16 -> 0 | AH16: =T16 -> 2500 | AI16: =SUM(W16:AH16) -> 5000 | AJ16: =U16-W16-X16-Y16-Z16-AA16-AB16-AC16-AD16-AE16-AF16-AG16-AH16 -> 72954.545 | AN16: =AK16+AL16+AM16 -> 0
A17: 16 | B17: Ziaullah Ansari | C17: OIC | D17: 15000 | E17: 6000 | F17: 45228 | G17: 45594 | H17: Akbar Sir | I17: 10000 | J17: =E17/23*8 -> 2086.9565 | K17: 10000 | L17: 10000 | M17: 10000 | N17: 10000 | O17: 10000 | P17: 10000 | Q17: 6000 | R17: 6000 | S17: 0 | T17: 6000 | U17: =SUM(I17:T17)-4000 -> 86086.957 | V17: ='[1]2022'!U13 -> #REF! | W17: 200 | X17: 3478 | Y17: 4000 | Z17: 4000 | AA17: 4000 | AB17: 4000 | AC17: 4000 | AD17: 4000 | AG17: =S17 -> 0 | AI17: =SUM(W17:AH17) -> 27678 | AJ17: =U17-W17-X17-Y17-Z17-AA17-AB17-AC17-AD17-AE17-AF17-AG17-AH17 -> 58408.957 | AN17: =AK17+AL17+AM17 -> 0
A18: 17 | B18: Mohsin Mohd | C18: OIC | D18: 70000 | E18: 10000 | F18: 44710 | G18: 45074 | H18: Akbar Sir | I18: 10000 | J18: 10000 | K18: 10000 | L18: 10000 | M18: 10000 | N18: 10000 | O18: 10000 | P18: 10000 | Q18: 10000 | R18: =E18/22*15 -> 6818.1818 | S18: 10000 | T18: 10000 | U18: =SUM(I18:T18) -> 116818.18 | V18: ='[1]2022'!U11 -> #REF! | AI18: =SUM(W18:AH18) -> 0 | AJ18: =U18-W18-X18-Y18-Z18-AA18-AB18-AC18-AD18-AE18-AF18-AG18-AH18 -> 116818.18 | AN18: =AK18+AL18+AM18 -> 0
A19: 18 | B19: Arshad Ansari | C19: OIC | D19: 20000 | E19: 10000 | F19: 44945 | G19: 45309 | H19: Akbar Sir | I19: =8182+1818 -> 10000 | J19: 10000 | K19: 10000 | L19: 10000 | M19: 10000 | N19: 10000 | O19: 10000 | P19: 10000 | Q19: =E19/21*16 -> 7619.0476 | R19: 8000 | S19: 7000 | T19: 5000 | U19: =SUM(I19:T19) -> 107619.05 | V19: =SUM(I19:T19) -> 107619.05 | AI19: =SUM(W19:AH19) -> 0 | AJ19: =U19-W19-X19-Y19-Z19-AA19-AB19-AC19-AD19-AE19-AF19-AG19-AH19 -> 107619.05 | AN19: =AK19+AL19+AM19 -> 0
A20: 19 | B20: Syed Mustafa | C20: Qlik Sense | D20: 25000 | E20: 10000 | F20: 45049 | G20: 45599 | H20: Akbar Sir | I20: 10000 | J20: =E20/23*12 -> 5217.3913 | K20: 10000 | L20: 10000 | M20: 10000 | N20: 10000 | O20: 10000 | P20: 10000 | Q20: 10000 | R20: 10000 | S20: 10000 | T20: 10000 | U20: =SUM(I20:T20) -> 115217.39 | V20: ='[1]2022'!U15 -> #REF! | AI20: =SUM(W20:AH20) -> 0 | AJ20: =U20-W20-X20-Y20-Z20-AA20-AB20-AC20-AD20-AE20-AF20-AG20-AH20 -> 115217.39 | AN20: =AK20+AL20+AM20 -> 0
A21: 20 | B21: Saif Khan | C21: Qlik Sense | D21: 15000 | E21: 6000 | F21: 44841 | G21: 45206 | H21: Akbar Sir | I21: 6000 | J21: =E21/23*14 -> 3652.1739 | K21: 6000 | L21: 6000 | M21: 6000 | N21: 6000 | O21: 6000 | P21: 6000 | Q21: 6000 | R21: 4000 | S21: =E21/23*18 -> 4695.6522 | T21: =E21/20*14 -> 4200 | U21: =SUM(I21:T21) -> 64547.826 | V21: ='[1]2022'!U19 -> #REF! | AF21: =R21 -> 4000 | AG21: =S21 -> 4695.6522 | AH21: =T21 -> 4200 | AI21: =SUM(W21:AH21) -> 12895.652 | AJ21: =U21-W21-X21-Y21-Z21-AA21-AB21-AC21-AD21-AE21-AF21-AG21-AH21 -> 51652.174 | AN21: =AK21+AL21+AM21 -> 0
A22: 21 | B22: Krushna Rauda | C22: Qlik Sense | D22: 25000 | E22: 10000 | F22: 44972 | G22: 45336 | H22: Akbar Sir | I22: 10000 | J22: 10000 | K22: 0 | L22: 10000 | M22: 10000 | N22: 4000 | O22: 4000 | P22: 4000 | Q22: 8000 | R22: 8000 | S22: 8000 | T22: 8000 | U22: =SUM(I22:T22) -> 84000 | V22: =SUM(K22:T22) -> 64000 | W22: 10000 | X22: 10000 | AI22: =SUM(W22:AH22) -> 20000 | AJ22: =U22-W22-X22-Y22-Z22-AA22-AB22-AC22-AD22-AE22-AF22-AG22-AH22 -> 64000 | AN22: =AK22+AL22+AM22 -> 0
A23: 22 | B23: Fahim Shaikh | C23: Qlik Sense | D23: 6000 | E23: 10000 | F23: 45164 | G23: 45714 | H23: Akbar Sir | I23: NA | J23: NA | K23: NA | L23: NA | M23: NA | N23: NA | O23: NA | P23: NA | Q23: 8000 | R23: 8000 | S23: 10000 | T23: 8000 | U23: =SUM(I23:T23) -> 34000
A24: 23 | B24: Abdus Samad Chaudhary | C24: Qlik Sense | D24: 6000 | E24: 4000 | F24: 45227 | G24: 45775 | H24: Akbar Sir | I24: NA | J24: NA | K24: NA | L24: NA | M24: NA | N24: NA | O24: NA | P24: NA | Q24: NA | R24: NA | S24: =E24/27*24 -> 3555.5556 | T24: 4000 | U24: =SUM(I24:T24) -> 7555.5556
A25: 24 | B25: Yasmeen Shaikh | C25: Sales | D25: 15000 | E25: 10000 | F25: 44936 | G25: 45301 | H25: Akbar Sir | I25: =3000+5000 -> 8000 | J25: =E25/23*18 -> 7826.087 | K25: 10000 | L25: 10000 | M25: 10000 | N25: =E25/22*18 -> 8181.8182 | O25: 10000 | P25: 10000 | Q25: 10000 | R25: 10000 | S25: 10000 | T25: 10000 | U25: =SUM(I25:T25) -> 114007.91 | V25: ='[1]2022'!U24 -> #REF! | AA25: =M25 -> 10000 | AI25: =SUM(W25:AH25) -> 10000 | AJ25: =U25-W25-X25-Y25-Z25-AA25-AB25-AC25-AD25-AE25-AF25-AG25-AH25 -> 104007.91 | AN25: =AK25+AL25+AM25 -> 0
A26: 25 | B26: Shariqa Lashkar (Performance Bonus) | C26: Sales | D26: 6000 | E26: 6000 | H26: Akbar Sir | I26: 6000 | J26: 6000 | K26: =E26/20*15 -> 4500 | L26: 6000 | M26: 6000 | N26: 6000 | O26: 6000 | P26: 6000 | Q26: 6000 | R26: 6000 | S26: 6000 | T26: 6000 | U26: =SUM(I26:T26) -> 70500 | V26: ='[1]2022'!U22 -> #REF! | W26: =I26 -> 6000 | X26: =J26 -> 6000 | Y26: =K26 -> 4500 | AA26: =M26 -> 6000 | AB26: 6000 | AC26: =O26 -> 6000 | AD26: =P26 -> 6000 | AE26: =Q26 -> 6000 | AF26: =R26 -> 6000 | AG26: =S26 -> 6000 | AH26: =T26 -> 6000 | AI26: =SUM(W26:AH26) -> 64500 | AJ26: =U26-W26-X26-Y26-Z26-AA26-AB26-AC26-AD26-AE26-AF26-AG26-AH26 -> 6000 | AN26: =AK26+AL26+AM26 -> 0
A27: 26 | B27: Shariqa Lashkar (Lead Bonus) | C27: Sales | D27: 6000 | E27: 6000 | H27: Akbar Sir | I27: NA | J27: NA | K27: NA | L27: NA | M27: NA | N27: NA | O27: 0 | P27: 6000 | Q27: 6000 | R27: 6000 | S27: 6000 | T27: 6000 | U27: =SUM(I27:T27) -> 30000 | AC27: =O27 -> 0 | AD27: =P27 -> 6000 | AE27: =Q27 -> 6000 | AF27: =R27 -> 6000 | AG27: =S27 -> 6000 | AH27: =T27 -> 6000
A28: 27 | B28: Sana Choudhary | C28: Sales | D28: 25000 | E28: 5000 | F28: 44937 | H28: Akbar Sir | I28: =5000+5000 -> 10000 | J28: 5000 | K28: 5000 | L28: 5000 | M28: 5000 | N28: 5000 | O28: 5000 | P28: 5000 | Q28: 5000 | R28: 5000 | S28: 5000 | T28: =E28/20*10 -> 2500 | U28: =SUM(I28:T28) -> 62500 | V28: ='[1]2022'!U20 -> #REF! | AA28: =M28 -> 5000 | AI28: =SUM(W28:AH28) -> 5000 | AJ28: =U28-W28-X28-Y28-Z28-AA28-AB28-AC28-AD28-AE28-AF28-AG28-AH28 -> 57500 | AN28: =AK28+AL28+AM28 -> 0
A29: 28 | B29: Heena khan | C29: Sales | D29: 6000 | E29: 6000 | H29: Akbar Sir | I29: NA | J29: NA | K29: NA | L29: =E29/21*15 -> 4285.7143 | M29: 6000 | N29: 6000 | O29: 6000 | P29: 6000 | Q29: 6000 | R29: 6000 | S29: =E29 -> 6000 | T29: 6000 | U29: =SUM(I29:T29) -> 52285.714 | AC29: =O29 -> 6000 | AD29: =P29 -> 6000 | AE29: =Q29 -> 6000 | AF29: =R29 -> 6000 | AG29: =S29 -> 6000 | AH29: =T29 -> 6000
A30: 29 | B30: Shama Parveen | C30: Sales | D30: 6000 | E30: 0 | F30: On Stipend | H30: Akbar Sir | I30: NA | J30: NA | K30: NA | L30: NA | M30: NA | N30: NA | O30: NA | P30: NA | Q30: NA | R30: NA | S30: NA | T30: 3000 | U30: =SUM(I30:T30) -> 3000 | AH30: =T30-750 -> 2250
A31: 30 | B31: Hajra Shaikh | C31: Sales | D31: 6000 | E31: 6000 | H31: Akbar Sir | I31: =E31/22*7 -> 1909.0909 | J31: =E31/23*12 -> 3130.4348 | K31: 3000 | L31: 6000 | M31: 6000 | N31: =E31/22*17 -> 4636.3636 | O31: 6000 | P31: 6000 | Q31: 6000 | R31: 4000 | S31: 5000 | T31: =E31/20*15 -> 4500 | U31: =SUM(I31:T31) -> 56175.889 | V31: ='[1]2022'!U21 -> #REF! | W31: =I31 -> 1909.0909 | X31: =J31 -> 3130.4348 | Y31: =K31 -> 3000 | Z31: =L31 -> 6000 | AA31: =M31 -> 6000 | AB31: =N31 -> 4636.3636 | AC31: =O31 -> 6000 | AD31: =P31 -> 6000 | ... AH31: =T31 -> 4500 | AI31: =SUM(W31:AH31) -> 56175.889 | AJ31: =U31-W31-X31-Y31-Z31-AA31-AB31-AC31-AD31-AE31-AF31-AG31-AH31 -> 0 | AN31: =AK31+AL31+AM31 -> 0
A32: 31 | B32: Swati Amode | C32: Salesforce admin | D32: 25000 | E32: 5000 | F32: 44806 | G32: 45171 | H32: Shahid Qadri | I32: 3500 | J32: 4000 | K32: 5000 | L32: 5000 | M32: =E32/22*16 -> 3636.3636 | N32: 3000 | O32: 5000 | P32: 0 | Q32: 4000 | R32: 5000 | S32: 5000 | T32: 5000 | U32: =SUM(I32:T32) -> 48136.364 | V32: ='[1]2022'!U59 -> #REF! | W32: =I32 -> 3500 | X32: =J32 -> 4000 | Y32: =K32 -> 5000 | Z32: =L32 -> 5000 | AA32: =M32 -> 3636.3636 | AB32: =N32 -> 3000 | AC32: =O32 -> 5000 | AD32: =P32 -> 0 | AE32: =Q32 -> 4000 | AI32: =SUM(W32:AH32) -> 33136.364 | AJ32: =U32-W32-X32-Y32-Z32-AA32-AB32-AC32-AD32-AE32-AF32-AG32-AH32 -> 15000 | AN32: =AK32+AL32+AM32 -> 0
A33: 32 | B33: Saniya Shaikh | C33: Salesforce admin | D33: 6000 | E33: 10000 | F33: 44823 | G33: 45370 | H33: Akbar Sir | I33: 9000 | J33: 10000 | K33: 10000 | L33: 10000 | M33: 0 | N33: 10000 | O33: 9000 | P33: 8000 | Q33: 8000 | R33: 10000 | S33: 10000 | T33: 10000 | U33: =SUM(I33:T33) -> 104000 | V33: ='[1]2022'!U30 -> #REF! | AI33: =SUM(W33:AH33) -> 0 | AJ33: =U33-W33-X33-Y33-Z33-AA33-AB33-AC33-AD33-AE33-AF33-AG33-AH33 -> 104000 | AN33: =AK33+AL33+AM33 -> 0
A34: 33 | B34: Nazmin Shaikh | C34: Salesforce admin | D34: 15000 | E34: 6000 | F34: 45153 | G34: 45519 | H34: Akbar Sir | I34: 8000 | J34: 4000 | K34: 5000 | L34: 10000 | M34: 8000 | N34: =E34/22*10 -> 2727.2727 | O34: 6000 | P34: 8783 | Q34: 6000 | R34: 6000 | S34: =E34/23*18 -> 4695.6522 | T34: 6000 | U34: =SUM(I34:T34) -> 75205.925 | V34: ='[1]2022'!U32 -> #REF! | W34: 6957 | AI34: =SUM(W34:AH34) -> 6957 | AJ34: =U34-W34-X34-Y34-Z34-AA34-AB34-AC34-AD34-AE34-AF34-AG34-AH34 -> 68248.925 | AN34: =AK34+AL34+AM34 -> 0
A35: 34 | B35: Naheed Khan | C35: Salesforce admin | D35: 15000 | E35: 6000 | F35: 45154 | G35: 45520 | H35: Akbar Sir | I35: 10000 | J35: 5000 | K35: 5000 | L35: 10000 | M35: 6000 | N35: 8000 | O35: 6000 | P35: 8609 | Q35: 6000 | R35: 6000 | S35: 6000 | T35: 6000 | U35: =SUM(I35:T35) -> 82609 | V35: ='[1]2022'!U31 -> #REF! | W35: 3478 | AI35: =SUM(W35:AH35) -> 3478 | AJ35: =U35-W35-X35-Y35-Z35-AA35-AB35-AC35-AD35-AE35-AF35-AG35-AH35 -> 79131 | AN35: =AK35+AL35+AM35 -> 0
A36: 35 | B36: Mohammad Rehanuddin | C36: Salesforce admin | D36: 52000 | E36: 5000 | F36: 44491 | G36: 44856 | H36: Akbar Sir | I36: 5000 | J36: 5000 | K36: 0 | L36: 5000 | M36: 0 | N36: 5000 | O36: 5000 | P36: 5000 | Q36: 5000 | R36: 5000 | S36: 5000 | T36: 5000 | U36: =SUM(I36:T36) -> 50000 | V36: ='[1]On hold bonus'!B4 -> #REF! | W36: =I36 -> 5000 | X36: =J36 -> 5000 | Y36: 0 | Z36: loan deduct | AA36: loan deduct | AB36: =N36 -> 5000 | AC36: =O36 -> 5000 | AD36: =P36 -> 5000 | AE36: =Q36 -> 5000 | AF36: =R36 -> 5000 | AG36: =S36 -> 5000 | AH36: =T36 -> 5000 | AI36: =SUM(W36:AH36) -> 45000 | AJ36: =U36-W36-X36-Y36-Z36-AA36-AB36-AC36-AD36-AE36-AF36-AG36-AH36 -> #VALUE! | AN36: =AK36+AL36+AM36 -> 0
A37: 36 | B37: Mehboob Shaikh | C37: Salesforce admin | D37: 10000 | E37: 6000 | F37: 44841 | G37: 45206 | H37: Akbar Sir | I37: 0 | J37: 3000 | K37: 0 | L37: 0 | M37: 0 | N37: 2000 | O37: 0 | P37: 3000 | Q37: 0 | R37: 0 | S37: 0 | T37: 0 | U37: =SUM(I37:T37) -> 8000 | V37: ='[1]2022'!U51 -> #REF! | AI37: =SUM(W37:AH37) -> 0 | AJ37: =U37-W37-X37-Y37-Z37-AA37-AB37-AC37-AD37-AE37-AF37-AG37-AH37 -> 8000 | AN37: =AK37+AL37+AM37 -> 0
A38: 37 | B38: Maaz Shaokat Choughle | C38: Salesforce admin | D38: 47000 | E38: 5000 | F38: 44814 | G38: 45179 | H38: Shahid Qadri | I38: 4000 | J38: 4000 | K38: 5000 | L38: 5000 | M38: 4000 | N38: 4000 | O38: =E38/21*14 -> 3333.3333 | P38: 3000 | Q38: 4000 | R38: 5000 | S38: 5000 | T38: 5000 | U38: =SUM(I38:T38) -> 51333.333 | V38: ='[1]2022'!U56 -> #REF! | AI38: =SUM(W38:AH38) -> 0 | AJ38: =U38-W38-X38-Y38-Z38-AA38-AB38-AC38-AD38-AE38-AF38-AG38-AH38 -> 51333.333 | AN38: =AK38+AL38+AM38 -> 0
A39: 38 | B39: Imran patel | C39: Salesforce admin | D39: 25000 | E39: 10000 | F39: 44837 | G39: 45202 | H39: Akbar Sir | I39: 10000 | J39: 5000 | K39: 0 | L39: 5000 | M39: 0 | N39: 5000 | O39: 5000 | P39: 5000 | Q39: 10000 | R39: 10000 | S39: 10000 | T39: 10000 | U39: =SUM(I39:T39) -> 75000 | V39: #REF! | AF39: =R39 -> 10000 | AG39: =S39 -> 10000 | AH39: =T39 -> 10000 | AI39: =SUM(W39:AH39) -> 30000 | AJ39: =U39-W39-X39-Y39-Z39-AA39-AB39-AC39-AD39-AE39-AF39-AG39-AH39 -> 45000 | AN39: =AK39+AL39+AM39 -> 0
A40: 39 | B40: Neesha Yadav | C40: Salesforce admin | D40: 10000 | E40: 6000 | F40: 45166 | G40: 45531 | H40: Shahid Qadri | I40: NA | J40: NA | K40: NA | L40: NA | M40: NA | N40: NA | O40: NA | P40: NA | Q40: 4500 | R40: 4000 | S40: 5000 | T40: =E40/20*14 -> 4200 | U40: =SUM(I40:T40) -> 17700 | V40: #REF!
A41: 40 | B41: Shaikh Samee | C41: Salesforce-Eienstein | D41: 25000 | E41: 5000 | F41: 44747 | G41: 45112 | H41: Akbar Sir | I41: 5000 | J41: 5000 | K41: 5000 | L41: 5000 | M41: 5000 | N41: 5000 | O41: 5000 | P41: NA | Q41: NA | R41: NA | S41: NA | T41: =E41/20*14 -> 3500 | U41: =SUM(I41:T41) -> 38500 | V41: ='[1]2022'!U36 -> #REF! | X41: =I41+J41+K41 -> 15000 | AA41: 15000 | AC41: =P41 -> NA | AD41: =Q41 -> NA | AE41: =R41 -> NA | AF41: =S41 -> NA | AG41: =T41 -> 3500 | AH41: =T41 -> 3500 | AM41: =AJ41+AK41+AL41 -> 0
A42: 41 | B42: Shaikh Zeeshan Shaikh Rafeeque | C42: Salesforce-Eienstein | D42: 40000 | E42: 10000 | F42: 44817 | G42: 45182 | H42: Akbar Sir | I42: 10000 | J42: 10000 | K42: 10000 | L42: 10000 | M42: 10000 | N42: 10000 | O42: 10000 | P42: 10000 | Q42: 10000 | R42: 0 | S42: 0 | T42: 0 | U42: =SUM(I42:T42) -> 90000 | V42: ='[1]On hold bonus'!B47 -> #REF! | W42: =I42 -> 10000 | X42: =J42 -> 10000 | Y42: =K42 -> 10000 | Z42: =L42 -> 10000 | AA42: =M42 -> 10000 | AC42: =O42 -> 10000 | AD42: =P42 -> 10000 | AE42: =Q42 -> 10000 | AF42: =R42 -> 0 | AG42: =S42 -> 0 | AH42: =T42 -> 0 | AI42: =SUM(W42:AH42) -> 80000 | AJ42: =U42-W42-X42-Y42-Z42-AA42-AB42-AC42-AD42-AE42-AF42-AG42-AH42 -> 10000 | AN42: =AK42+AL42+AM42 -> 0
A43: 42 | B43: Saleha khan | C43: Salesforce-Eienstein | D43: 6000 | E43: 10000 | F43: 44679 | G43: 45227 | H43: Akbar Sir | I43: =E43/22*7 -> 3181.8182 | J43: =E43/23*14 -> 6086.9565 | K43: 10000 | L43: 10000 | M43: 10000 | N43: 10000 | O43: 6000 | P43: 10000 | Q43: 5000 | R43: 4000 | S43: 5000 | U43: =SUM(I43:T43) -> 79268.775 | V43: ='[1]2022'!U63 -> #REF!
A44: 43 | B44: Sidra Ansari | C44: SharePoint | D44: 15000 | E44: 10000 | F44: 44945 | G44: 45310 | H44: Akbar Sir | I44: 8000 | J44: 8000 | K44: 7000 | L44: 7000 | M44: =E44/22*4 -> 1818.1818 | N44: 5000 | O44: 7000 | P44: 7000 | Q44: 10000 | R44: 10000 | S44: =E44/23*18 -> 7826.087 | T44: =E44/20*10 -> 5000 | U44: =SUM(I44:T44) -> 83644.269 | V44: ='[1]2022'!U54 -> #REF! | AI44: =SUM(W44:AH44) -> 0 | AJ44: =U44-W44-X44-Y44-Z44-AA44-AB44-AC44-AD44-AE44-AF44-AG44-AH44 -> 83644.269 | AN44: =AK44+AL44+AM44 -> 0
A45: 44 | B45: Noorullah khan | C45: SharePoint | D45: 15000 | E45: 10000 | F45: 45075 | G45: 45441 | H45: Akbar Sir | I45: =E45/22*18 -> 8181.8182 | J45: 7000 | K45: 10000 | L45: 8000 | M45: 10000 | N45: 10000 | O45: 8000 | P45: 7000 | Q45: 7000 | R45: 8000 | S45: 5000 | T45: 6000 | U45: =SUM(I45:T45) -> 94181.818 | V45: ='[1]2022'!U43 -> #REF! | AI45: =SUM(W45:AH45) -> 0 | AJ45: =U45-W45-X45-Y45-Z45-AA45-AB45-AC45-AD45-AE45-AF45-AG45-AH45 -> 94181.818 | AK45: =V45 -> #REF! | AN45: =AK45+AL45+AM45+AJ45 -> #REF!
A46: 45 | B46: Nagma Khan | C46: SharePoint | D46: 27000 | E46: 10000 | H46: Akbar Sir | I46: 10000 | J46: 10000 | K46: 10000 | L46: 10000 | M46: =E46/22*7 -> 3181.8182 | N46: 10000 | O46: 8000 | P46: 5000 | Q46: 10000 | R46: 10000 | S46: =E46/23*19 -> 8260.8696 | T46: =E46/20*14 -> 7000 | U46: =SUM(I46:T46) -> 101442.69 | V46: ='[1]2022'!U39 -> #REF! | W46: =I46 -> 10000 | X46: =J46 -> 10000 | Y46: =K46 -> 10000 | Z46: =L46 -> 10000 | AA46: 10000 | AB46: 10000 | AC46: =O46-6818 -> 1182 | AD46: =P46 -> 5000 | AE46: =Q46 -> 10000 | AF46: =R46 -> 10000 | AG46: =S46 -> 8260.8696 | AH46: =T46 -> 7000 | AI46: =SUM(W46:AH46) -> 101442.87 | AJ46: =U46-W46-X46-Y46-Z46-AA46-AC46-#REF!-AD46-AE46-AF46-AG46-AH46 -> #REF! | AN46: =AK46+AL46+AM46 -> 0
A47: 46 | B47: Mohammed Rahmatullah | C47: SharePoint | D47: 38000 | E47: 5000 | F47: 45114 | G47: 45477 | H47: Akbar Sir | I47: =E47/22*7 -> 1590.9091 | J47: 5000 | K47: 5000 | L47: 5000 | M47: 5000 | N47: 5000 | O47: 5000 | P47: 5000 | Q47: 5000 | R47: 5000 | S47: =E47/23*15 -> 3260.8696 | T47: 5000 | U47: =SUM(I47:T47) -> 54851.779 | V47: #REF! | AI47: =SUM(W47:AH47) -> 0 | AJ47: =U47-W47-X47-Y47-Z47-AA47-AB47-AC47-AD47-AE47-AF47-AG47-AH47 -> 54851.779 | AN47: =AK47+AL47+AM47 -> 0
A48: 47 | B48: Huzaif Khot | C48: SharePoint | D48: 20000 | E48: 5000 | F48: 44945 | G48: 45310 | H48: Akbar Sir | I48: =4909+909 -> 5818 | J48: 5000 | K48: 5000 | L48: 5000 | M48: 5000 | N48: 5000 | O48: 5000 | P48: 5000 | Q48: 5000 | R48: 5000 | S48: 5000 | T48: =E48/20*13 -> 3250 | U48: =SUM(I48:T48) -> 59068 | V48: #REF! | AI48: =SUM(W48:AH48) -> 0 | AJ48: =U48-W48-X48-Y48-Z48-AA48-AB48-AC48-AD48-AE48-AF48-AG48-AH48 -> 59068 | AN48: =AK48+AL48+AM48 -> 0
A49: 48 | B49: Ansari MohammedArshduddin MohammedMasooduddin | C49: SharePoint | D49: 30000 | E49: 5000 | F49: 44806 | G49: 45171 | H49: Akbar Sir | I49: 5000 | J49: =E49/23*14.5 -> 3152.1739 | K49: =E49/20*11 -> 2750 | L49: 5000 | M49: 5000 | N49: 0 | O49: 2000 | P49: 5000 | Q49: 4000 | R49: =E49/22*17 -> 3863.6364 | S49: =E49/23*12 -> 2608.6957 | T49: =E49/20*10 -> 2500 | U49: =SUM(I49:T49) -> 40874.506 | V49: ='[1]2022'!U38 -> #REF! | AI49: =SUM(W49:AH49) -> 0 | AJ49: =U49-W49-X49-Y49-Z49-AA49-AB49-AC49-AD49-AE49-AF49-AG49-AH49 -> 40874.506 | AN49: =AK49+AL49+AM49 -> 0
A50: 49 | B50: Minhaj mohammed | C50: SharePoint | D50: 10000 | E50: 6000 | F50: 45252 | G50: 45449 | H50: Akbar Sir | I50: 5000 | J50: =E50/23*17 -> 4434.7826 | K50: =E50/20*9.5 -> 2850 | L50: 8000 | M50: 5000 | N50: 5000 | O50: 10000 | P50: NA | Q50: NA | R50: NA | S50: =E50/23*3 -> 782.6087 | T50: 6000 | U50: =SUM(I50:T50) -> 47067.391 | V50: ='[1]2022'!#REF! -> #REF! | AD50: =P50 -> NA | AE50: =Q50 -> NA | AF50: =R50 -> NA | AI50: =SUM(W50:AH50) -> 0 | AJ50: =U50-W50-X50-Y50-Z50-AA50-AB50-AC50-AD50-AE50-AF50-AG50-AH50 -> #VALUE! | AN50: =AK50+AL50+AM50 -> 0
A51: 50 | B51: Zishan shaikh | C51: Uipath | D51: 28000 | E51: 7000 | F51: 45084 | H51: Akbar Sir | I51: 10000 | J51: 10000 | K51: 10000 | L51: 10000 | M51: =E51/22*16 -> 5090.9091 | N51: 6591 | O51: 7000 | P51: 7000 | Q51: =E51/21*6 -> 2000 | R51: 7000 | S51: 7000 | T51: =E51/20*16 -> 5600 | U51: =SUM(I51:T51) -> 87281.909 | V51: #REF! | AI51: =SUM(W51:AH51) -> 0 | AJ51: =U51-W51-X51-Y51-Z51-AA51-AB51-AC51-AD51-AE51-AF51-AG51-AH51 -> 87281.909 | AN51: =AK51+AL51+AM51 -> 0
A52: 51 | B52: Baseet Baig | C52: Uipath | D52: 6000 | E52: 10000 | F52: 44881 | G52: 45246 | H52: Akbar Sir | I52: 3000 | J52: 4000 | K52: 5000 | L52: 5000 | M52: 5000 | N52: 5000 | O52: 5000 | P52: 4000 | Q52: 6000 | R52: =E52/22*17.5 -> 7954.5455 | S52: 3000 | T52: 0 | U52: =SUM(I52:T52) -> 52954.545 | V52: #REF! | AI52: =SUM(W52:AH52) -> 0 | AJ52: =U52-X52-Y52-Z52-AA52-AB52 -> 52954.545 | AK52: #REF! | AL52: #REF! | AN52: =AK52+AL52+AM52 -> #VALUE!
A53: 52 | B53: Saniya khanam | C53: Uipath | D53: 6000 | E53: 4000 | F53: 45227 | G53: 45775 | H53: Akbar Sir | I53: NA | J53: NA | K53: NA | L53: NA | M53: NA | N53: NA | O53: NA | P53: NA | Q53: NA | R53: NA | S53: =E53/27*24 -> 3555.5556 | T53: 3000 | U53: =SUM(I53:T53) -> 6555.5556
A54: 53 | B54: Amir shaikh | C54: Wordpress | D54: 12000 | E54: 6000 | F54: 45061 | H54: Akbar Sir | I54: NA | J54: NA | K54: NA | L54: NA | M54: =E54/22*8 -> 2181.8182 | N54: 3000 | O54: 6000 | P54: 0 | Q54: 6000 | R54: 4000 | S54: =E54/23*15 -> 3913.0435 | T54: =E54/20*14 -> 4200 | U54: =SUM(I54:T54) -> 29294.862 | AA54: =S54/22*8 -> 1422.9249 | AB54: 3000 | AC54: 6000 | AD54: 0 | AE54: 6000 | AF54: 4000 | AG54: =S54-2815 -> 1098.0435 | AH54: =T54 -> 4200 | AI54: =SUM(W54:AH54) -> 25720.968 | AJ54: =SUM(M54:R54)+2824 -> 24005.818 | AK54: 0 | AL54: 0 | AM54: 0 | AN54: =AJ54 -> 24005.818
B55: TOTAL | D55: =SUBTOTAL(9,D2:D26,D28,D29:D54) -> 6000 | E55: =SUBTOTAL(9,E2:E26,E28:E54) -> 10000 | H55: =SUM(H49:H54) -> 0 | I55: =SUM(I49:I54) -> 23000 | J55: =SUM(J49:J54) -> 21586.957 | K55: =SUM(K49:K54) -> 20600 | L55: =SUM(L49:L54) -> 28000 | M55: =SUM(M49:M54) -> 22272.727 | N55: =SUM(N49:N54) -> 19591 | O55: =SUM(O49:O54) -> 30000 | ... V55: =SUM(V49:V54) -> #REF! | W55: =SUM(#REF!,W49:W54) -> #REF! | X55: =SUM(X49:X54) -> 0 | Y55: =SUM(Y49:Y54) -> 0 | Z55: =SUM(Z49:Z54) -> 0 | AA55: =SUM(AA49:AA54) -> 1422.9249 | AB55: =SUM(AB49:AB54) -> 3000 | AC55: =SUM(AC49:AC54) -> 6000 | AD55: =SUM(AD2:AD54) -> 85000 | AE55: =SUM(AE49:AE54) -> 6000 | AF55: =SUM(AF49:AF54) -> 4000 | AG55: =SUM(AG49:AG54) -> 1098.0435 | AH55: =SUM(AH49:AH54) -> 4200 | AI55: =SUM(AI49:AI54) -> 25720.968 | AJ55: =SUM(AJ49:AJ54) -> #VALUE! | AK55: =SUM(AK49:AK54) -> 0 | AL55: =SUM(AL49:AL54) -> 0 | ... AN55: =SUM(AN49:AN54) -> #VALUE!
S57: 1089
S58: =S54-S57 -> 2824.0435
C59: after 1 year will be pay bonus
C60: Samee Quarterly bonus | I60: 50000
C61: Sadat sir UAE | I61: =SUM(I43:R43,I60) -> 124268.77 | R61: 50000
C62: Ziaullah propotion bonus
C63: Lead Bonus
C64: On Stipend

Sheet 2024
A1: Sr No | B1: Name of the Employee | C1: Technology | D1: Salary | E1: Bonus amount | F1: Commitment Start date | G1: Commitment End date | H1: Reporting manager | I1: Jan | J1: Feb | K1: Mar | L1: Apr | M1: May | N1: June | O1: July | P1: August | Q1: September | R1: Oct | S1: Nov | T1: Dec | U1: Comments | V1: Remark | W1: This year 2024 bonus amount | X1: Deposit bonus Amount along with us till 2023 paid after notice period /Contract | Y1: To be Paid with Salary in Jan 2024 | Z1: To be Paid with Salary in Feb 2024 | AA1: To be Paid with Salary in Mar 2024 | AB1: To be Paid with Salary in Apr 2024 | AC1: To be Paid with Salary in May 2024 | AD1: To be Paid with Salary in Jun 2024 | AE1: To be Paid with Salary in July 2024 | AF1: To be Paid with Salary in Aug 2024 | AG1: To be Paid with Salary in Sep 2024 | AH1: To be Paid with Salary in Oct 2024 | AI1: To be Paid with Salary in Nov 2024 | AJ1: To be Paid with Salary in Dec 2024 | AK1: Total bonus given in 2024 amount | AL1: remaining 2023 | AM1: remaining 2022 | AN1: remaining 2021 | AO1: remaining 2020 | AP1: Total Balance need to pay after notice period
A2: 47 | B2: Abdul Raheem | C2: Salesforce admin | D2: 6000 | E2: 4000 | F2: 45428 | G2: 46158 | H2: Akbar Sir | I2: NA | J2: NA | K2: NA | L2: NA | M2: NA | N2: NA | O2: NA | P2: NA | Q2: 1076 | R2: 4000 | S2: =E2/22*13 -> 2363.6364 | T2: =E2/22*22 -> 4000
A3: 26 | B3: Abdus Samad Chaudhary | C3: Power Bi | D3: 10000 | E3: 6000 | F3: 45227 | G3: 45775 | H3: Akbar Sir | I3: 4000 | J3: 4000 | K3: 4000 | L3: =4000/23*22 -> 3826.087 | M3: 6000 | N3: =E3/21*21 -> 6000 | O3: =E3/22*21 -> 5727.2727 | P3: =E3/22*22 -> 6000 | Q3: =E3/22*22 -> 6000 | R3: =E3/22*22 -> 6000 | S3: =E3/22*18 -> 4909.0909 | T3: =E3/22*22 -> 6000 | X3: =SUM(I3:V3) -> 62462.451
A4: 4 | B4: Ajida Samani | C4: HR | D4: 6000 | E4: 6000 | F4: 45476 | H4: Akbar Sir | O4: =4000/22*21.5 -> 3909.0909 | P4: =4000/22*20.5 -> 3727.2727 | Q4: =4000/22*20 -> 3636.3636 | R4: =4000/22*7 -> 1272.7273 | S4: =E4/21*16+1426 -> 5997.4286 | T4: =E4/22*21.5 -> 5863.6364 | U4: 0.5 leaves | AH4: =E4/21*5 -> 1428.5714 | AI4: 4473.619 | AJ4: =T4 -> 5863.6364
A5: 21 | B5: Alfahad Shaikh | C5: OIC | D5: 10000 | E5: 6000 | F5: 45271 | G5: 45819 | H5: Akbar Sir | I5: =4000/27*20 -> 2962.963 | J5: 4000 | K5: 4000 | L5: =4000/23*20 -> 3478.2609 | M5: =4000/22*20 -> 3636.3636 | N5: 0 | O5: 3000 | P5: 0 | Q5: 0 | R5: 0 | S5: 0 | T5: 3000 | U5: 3.5 leaves | X5: =SUM(I5:V5)+'[2]2023'!T9 -> 25837.587
A6: 14 | B6: Amir Khan | C6: Microsoft CRM | D6: 25000 | E6: 5000 | F6: 44817 | G6: 45182 | H6: Akbar Sir | I6: =E6/23*18 -> 3913.0435 | J6: 5000 | K6: 4000 | L6: 3000 | M6: 3000 | N6: =E6/21*21 -> 5000 | O6: 0 | P6: 0 | Q6: 0 | R6: 0 | S6: =E6/22*21 -> 4772.7273 | T6: 0 | U6: 1.5 Leaves & Blog not submitted he will not submit as today is his last date | X6: =SUM(I6:V6) -> 28685.771 | Y6: ='[3]2022'!U10 -> 29090.909 | Z6: =I6 -> 3913.0435 | AA6: 5000 | AB6: 4000 | AC6: =L6 -> 3000 | AD6: =M6 -> 3000 | AE6: =N6 -> 5000 | AF6: =P6 -> 0 | AG6: =Q6 -> 0 | AH6: =R6 -> 0 | AJ6: =T6 -> 0 | AK6: =V6 -> 0
A7: 55 | B7: Amir shaikh | C7: Wordpress | D7: 20000 | E7: 5000 | F7: 45061 | H7: Akbar Sir | I7: =E7/23*16 -> 3478.2609 | J7: 6000 | K7: 6000 | L7: =E7/23*22 -> 4782.6087 | M7: 5000 | N7: =E7/21*21 -> 5000 | O7: 2000 | P7: =E7/22*22 -> 5000 | Q7: =E7/22*19 -> 4318.1818 | R7: =E7/22*22 -> 5000 | S7: =E7/22*21.5 -> 4886.3636 | T7: =E7/22*22 -> 5000 | X7: =SUM(I7:V7) -> 56465.415 | Z7: =I7 -> 3478.2609 | AA7: 0 | AB7: 6000 | AC7: after 2 month salary | AD7: 5000 | AE7: =N7 -> 5000 | AF7: =P7 -> 5000 | AG7: =Q7 -> 4318.1818 | AH7: =R7 -> 5000 | AI7: =S7 -> 4886.3636 | AJ7: =T7 -> 5000 | AK7: =V7 -> 0
A8: 5 | B8: Ansari Yasmeen | C8: HR | D8: 12000 | E8: 9000 | H8: Akbar Sir | I8: =E8/22*18 -> 7363.6364 | J8: 2000 | K8: 9000 | L8: 9000 | M8: 9000 | N8: =E8/21*15 -> 6428.5714 | O8: 8000 | P8: 7000 | Q8: =E8/22*19.5 -> 7977.2727 | R8: =E8/22*22 -> 9000 | S8: =E8/22*6 -> 2454.5455 | T8: =E8/22*19-1000 -> 6772.7273 | U8: 3 leaves 7182 | V8: bank account not opened | X8: =SUM(I8:V8) -> 83996.753 | Y8: ='[3]2022'!U2 -> 20000 | Z8: =I8 -> 7363.6364 | AA8: 2000 | AB8: 9000 | AC8: =M8 -> 9000 | AD8: =M8 -> 9000 | AE8: =N8 -> 6428.5714 | AF8: =P8 -> 7000 | AG8: =Q8 -> 7977.2727 | AH8: =R8 -> 9000 | AI8: =S8 -> 2454.5455 | AJ8: =T8 -> 6772.7273
A9: 7 | B9: Arshduddin Ansari MohammedMasooduddin | C9: Joget | D9: 30000 | E9: 5000 | F9: 44806 | G9: 45171 | H9: Akbar Sir | I9: 5000 | J9: =E9/22*16 -> 3636.3636 | K9: =E9/20*16 -> 4000 | L9: 5000 | M9: 5000 | N9: =E9/21*21 -> 5000 | O9: =E9/22*21.5 -> 4886.3636 | P9: 4500 | Q9: =E9/22*22 -> 5000 | R9: =E9/22*19 -> 4318.1818 | S9: =E9/22*21 -> 4772.7273 | T9: =E9/22*22 -> 5000 | U9: Blog Not Submitted will submit by tomorrow | X9: =SUM(I9:V9) -> 56113.636 | Y9: ='[3]2022'!U38 -> 37928.571
A10: 24 | B10: Fahim Shaikh | C10: OIC | D10: 10000 | E10: 6000 | F10: 45164 | G10: 45714 | H10: Akbar Sir | I10: 10000 | J10: 10000 | K10: 10000 | L10: =10000/23*20 -> 8695.6522 | M10: 10000 | N10: =E10/21*21 -> 6000 | O10: =E10/22*22 -> 6000 | P10: =E10/22*22 -> 6000 | Q10: =E10/22*22 -> 6000 | R10: =E10/22*22 -> 6000 | S10: =E10/22*12.5 -> 3409.0909 | T10: =E10/22*22 -> 6000 | X10: =SUM(I10:V10) -> 88104.743
A11: 1 | B11: Farheen Sultanpuri | C11: Odoo | D11: 6000 | E11: 6000 | H11: Akbar Sir | I11: 8000 | J11: 6000 | K11: 6000 | L11: 5500 | M11: 6000 | N11: =E11/21*21 -> 6000 | O11: =E11/22*20 -> 5454.5455 | P11: =E11/22*20 -> 5454.5455 | Q11: 6000 | R11: =E11/22*20 -> 5454.5455 | S11: =E11/22*21 -> 5727.2727 | T11: =E11/22*19 -> 5181.8182 | U11: 2.5 leaves | W11: =SUM(I11:T11) -> 70772.727 | X11: ='2023'!AN5 -> 12000 | Y11: 8000 | Z11: 6000 | AA11: 6000 | AB11: 5500 | AC11: 6000 | AD11: 6000 | AE11: 5454.5455 | AF11: 5454.5455 | AG11: 6000 | AH11: 5454.5455 | AI11: 5727.2727 | AJ11: 5181.8182 | AK11: =SUM(Y11:AJ11) -> 70772.727 | AL11: =SUM('2023'!O5:P5) -> 12000 | AM11: 0 | AN11: 0 | AO11: 0 | AP11: =AL11 -> 12000
A12: 15 | B12: Hamza khot | C12: Microsoft CRM | D12: 16000 | E12: 6000 | F12: 45608 | G12: 46338 | H12: Akbar Sir | I12: 10000 | J12: 6000 | K12: 0 | L12: =10000/23*19 -> 8260.8696 | M12: 9000 | N12: =10000/21*21 -> 10000 | O12: =10000/22*21 -> 9545.4545 | P12: =10000/22*22 -> 10000 | Q12: =10000/22*22 -> 10000 | R12: =10000/22*15 -> 6818.1818 | S12: =E12/22*9+5909 -> 8363.5455 | T12: =E12/22*22 -> 6000 | X12: =SUM(I12:V12) -> 93988.051
A13: 8 | B13: Huzaif Khot | C13: Joget | D13: 30000 | E13: 5000 | F13: 45317 | G13: 45683 | H13: Akbar Sir | I13: 5000 | J13: 5000 | K13: 5000 | L13: 5000 | M13: 5000 | N13: =E13/21*21 -> 5000 | O13: =E13/22*22 -> 5000 | P13: =E13/22*21-500 -> 4272.7273 | Q13: =E13/22*22 -> 5000 | R13: =E13/22*22 -> 5000 | S13: =E13/22*22 -> 5000 | T13: =E13/22*22 -> 5000 | X13: =SUM(I13:V13) -> 59272.727 | Y13: #REF! | AA13: 5000 | AB13: 5000 | AC13: =L13 -> 5000 | AD13: =M13 -> 5000 | AE13: =N13 -> 5000 | AF13: =P13 -> 4272.7273 | AG13: =Q13 -> 5000 | AH13: =R13 -> 5000 | AI13: =S13 -> 5000 | AJ13: =T13 -> 5000
A14: 28 | B14: Imran Ahmed | C14: PowerApps | D14: 25000 | E14: 5000 | F14: 44830 | G14: 45195 | H14: Akbar Sir | I14: =E14/23*18 -> 3913.0435 | J14: 5000 | K14: 5000 | L14: 5000 | M14: =E14/22*17 -> 3863.6364 | N14: =E14/21*20.5 -> 4880.9524 | O14: 2500 | P14: =E14/22*12 -> 2727.2727 | Q14: 0 | R14: =E14/22*22 -> 5000 | S14: 0 | T14: 0 | X14: =SUM(I14:V14) -> 37884.905 | Y14: ='[3]2022'!U4 -> 0
A15: 39 | B15: Imran patel | C15: Salesforce admin | D15: 25000 | E15: 10000 | F15: 44837 | G15: 45202 | H15: Akbar Sir | I15: =E15 -> 10000 | J15: 10000 | K15: 10000 | L15: 10000 | M15: 10000 | N15: =E15/21*21 -> 10000 | O15: =E15/22*22 -> 10000 | P15: =E15/22*22 -> 10000 | Q15: =E15/22*22 -> 10000 | R15: =E15/22*22 -> 10000 | S15: =E15/22*22 -> 10000 | T15: =E15/22*22 -> 10000 | X15: =SUM(I15:V15) -> 120000 | Y15: ='[3]On hold bonus'!B51 -> 24000 | Z15: =I15 -> 10000 | AA15: 10000 | AB15: 10000 | AC15: =L15 -> 10000 | AD15: =M15 -> 10000 | AE15: =N15 -> 10000 | AF15: =P15 -> 10000 | AG15: =Q15 -> 10000 | AH15: =R15 -> 10000 | AI15: =S15 -> 10000 | AJ15: =T15 -> 10000 | AK15: =V15 -> 0
A16: 25 | B16: Kashaf Shaikh | C16: Power Bi | D16: 6000 | E16: 4000 | F16: 45517 | G16: 46246 | H16: Akbar Sir | I16: NA | J16: NA | K16: NA | L16: NA | M16: NA | N16: NA | O16: NA | P16: =E16/22*11 -> 2000 | Q16: =E16/22*22 -> 4000 | R16: =E16/26*26 -> 4000 | S16: =E16/22*22 -> 4000 | T16: =E16/26*26 -> 4000
A17: 3 | B17: Khan Noorul Hasan | C17: E-automate | D17: 30000 | E17: 5000 | F17: 44799 | G17: 45164 | H17: Akbar Sir | I17: 5000 | J17: 3000 | K17: 5000 | L17: =E17/23*19 -> 4130.4348 | M17: 2000 | N17: =E17/21*18 -> 4285.7143 | O17: =E17/22*22 -> 5000 | P17: =E17/22*22 -> 5000 | Q17: 0 | R17: =E17/22*22 -> 5000 | S17: =E17/22*22 -> 5000 | T17: =E17/22*21 -> 4772.7273 | U17: 1 leaves | X17: =SUM(I17:V17) -> 48188.876 | Y17: ='[3]2022'!U7 -> 14130.435
A18: 31 | B18: Krushna Rauda | C18: Qlik Sense | D18: 30000 | E18: 10000 | F18: 45362 | G18: 45727 | H18: Akbar Sir | I18: =E18/23*14 -> 6086.9565 | J18: 8000 | K18: 10000 | L18: 10000 | M18: 10000 | N18: 0 | O18: =E18/22*21 -> 9545.4545 | P18: =E18/22*22 -> 10000 | Q18: =E18/22*22 -> 10000 | R18: 0 | S18: 0 | T18: 0 | X18: =SUM(I18:V18) -> 73632.411 | Y18: =SUM(K18:V18) -> 59545.455
A19: 49 | B19: Maaz Shaokat Choughle | C19: Salesforce CPQ | D19: 57000 | E19: 5000 | F19: 45370 | G19: 45735 | H19: Akbar Sir | I19: 5000 | J19: 5000 | K19: 5000 | L19: 5000 | M19: 5000 | N19: =E19/21*21 -> 5000 | O19: =E19/22*22 -> 5000 | P19: =E19/22*22 -> 5000 | Q19: =E19/22*22 -> 5000 | R19: =E19/22*22 -> 5000 | S19: =E19/22*19 -> 4318.1818 | T19: =E19/22*10 -> 2272.7273 | U19: 12 Annual leaves | X19: =SUM(I19:V19) -> 56590.909 | Y19: ='[3]2022'!U56 -> 12500 | AB19: 5000 | AC19: =L19 -> 5000 | AD19: =M19 -> 5000 | AE19: =N19 -> 5000 | AF19: =P19 -> 5000 | AG19: =Q19 -> 5000 | AH19: =R19 -> 5000 | AI19: =S19 -> 4318.1818 | AJ19: =T19 -> 2272.7273
A20: 44 | B20: Mohammad Faiz | C20: Salesforce admin | D20: 6000 | E20: 4000 | F20: 45383 | G20: 46113 | H20: Akbar Sir | I20: NA | J20: NA | K20: NA | L20: NA | M20: NA | N20: NA | O20: NA | P20: =E20/27*22 -> 3259.2593 | Q20: 0 | R20: =E20/22*21 -> 3818.1818 | S20: =E20/22*21.5 -> 3909.0909 | T20: =E20/22*22 -> 4000
A21: 40 | B21: Mohammad Rehanuddin | C21: Salesforce admin | D21: 52000 | E21: 5000 | F21: 44491 | G21: 44856 | H21: Akbar Sir | I21: 5000 | J21: 5000 | K21: 5000 | L21: 5000 | M21: 5000 | N21: =E21/21*21 -> 5000 | O21: =E21/22*22 -> 5000 | P21: =E21/22*22 -> 5000 | Q21: =E21/22*22 -> 5000 | R21: =E21/22*22 -> 5000 | S21: 0 | T21: 0 | U21: 12.5 Annual leaves | X21: =SUM(I21:V21) -> 50000 | Y21: ='[3]On hold bonus'!B4 -> 90000 | Z21: =I21 -> 5000 | AA21: 5000 | AB21: 5000 | AC21: =L21 -> 5000 | AD21: =M21 -> 5000 | AE21: =N21 -> 5000 | AF21: =P21 -> 5000 | AG21: =Q21 -> 5000 | AH21: =R21 -> 5000 | AI21: =S21 -> 0 | AJ21: =T21 -> 0 | AK21: =V21 -> 0
A22: 20 | B22: Muzaffar Sayyed | C22: Microsoft CRM | D22: 10000 | E22: 6000 | F22: 45286 | G22: 45834 | H22: Akbar Sir | I22: =4000/27*18.5 -> 2740.7407 | J22: 4000 | K22: 4000 | L22: =4000/23*20 -> 3478.2609 | M22: =4000/22*17 -> 3090.9091 | N22: 0 | O22: 0 | P22: =E22/22*22 -> 6000 | Q22: =E22/22*22 -> 6000 | R22: =E22/22*20 -> 5454.5455 | S22: =E22/22*19 -> 5181.8182 | T22: =E22/22*22 -> 6000 | U22: Blog Not Submitted will submit till 25 Dec
A23: 17 | B23: Naeem Imran | C23: Microsoft CRM | D23: 10000 | E23: 10000 | F23: 45362 | G23: 45727 | H23: Akbar Sir | I23: 0 | J23: 6000 | K23: =5000+3000 -> 8000 | L23: =E23/27*22 -> 8148.1481 | M23: =E23/22*16 -> 7272.7273 | N23: 0 | O23: 7000 | P23: =E23/22*20 -> 9090.9091 | Q23: 5000 | R23: =E23/22*18 -> 8181.8182 | S23: =E23/22*17.5 -> 7954.5455 | T23: =E23/22*11 -> 5000 | U23: 9.5 Leaves & Blog Not Submitted | X23: =SUM(I23:V23) -> 71648.148 | Y23: ='[3]2022'!U28 -> 16000 | AB23: 8000 | AC23: =L23 -> 8148.1481 | AD23: =M23 -> 7272.7273 | AE23: =N23 -> 0 | AF23: =P23 -> 9090.9091 | AG23: =Q23 -> 5000 | AH23: =R23 -> 8181.8182 | AI23: =S23 -> 7954.5455 | AJ23: =T23 -> 5000
A24: 9 | B24: Nagma Khan | C24: Joget | D24: 27000 | E24: 10000 | H24: Akbar Sir | I24: 10000 | J24: 10000 | K24: 10000 | L24: 10000 | M24: 10000 | N24: =E24/21*21 -> 10000 | O24: =E24/22*22 -> 10000 | P24: =E24/22*22 -> 10000 | Q24: =E24/22*22 -> 10000 | R24: =E24/22*22 -> 10000 | S24: =E24/22*22 -> 10000 | T24: =E24/22*22 -> 10000 | X24: =SUM(I24:V24) -> 120000 | Y24: ='[3]2022'!U39 -> 36000 | Z24: 10000 | AA24: 10000 | AB24: 10000 | AC24: =L24 -> 10000 | AD24: =M24 -> 10000 | AE24: =N24 -> 10000 | AF24: =P24 -> 10000 | AG24: =Q24 -> 10000 | AH24: =R24 -> 10000 | AI24: =S24 -> 10000 | AJ24: =T24 -> 10000 | AK24: =V24 -> 0
A25: 50 | B25: Naheed Khan | C25: Salesforce CPQ | D25: 15000 | E25: 6000 | F25: 45154 | G25: 45520 | H25: Akbar Sir | I25: 6000 | J25: 6000 | K25: 6000 | L25: 6000 | M25: 6000 | N25: =E25/21*21 -> 6000 | O25: =E25/22*22 -> 6000 | P25: =E25/22*22 -> 6000 | Q25: =E25/22*21.5 -> 5863.6364 | R25: =E25/22*22 -> 6000 | S25: =E25/22*22 -> 6000 | T25: =E25/22*22 -> 6000 | U25: Blog Not Submitted will submit after project | X25: =SUM(I25:V25) -> 71863.636 | Y25: #REF!
A26: 53 | B26: Owais Chipa | C26: Marketing | D26: 6000 | E26: 6000 | F26: 45498 | I26: NA | J26: NA | K26: NA | L26: NA | M26: NA | N26: NA | O26: NA | P26: =E26/22*21.5 -> 5863.6364 | Q26: 3000 | R26: =E26/22*20.5 -> 5590.9091 | S26: =E26/22*17 -> 4636.3636 | T26: 4000 | U26: 2 leaves | AI26: =S26 -> 4636.3636 | AJ26: =T26 -> 4000
A27: 32 | B27: Pratham | C27: Qlik Sense | D27: 8000 | E27: 6000 | F27: 45369 | G27: 45553 | K27: =E27/20*5 -> 1500 | L27: 4000 | M27: =E27/23*20 -> 5217.3913 | N27: =E27/21*19 -> 5428.5714 | O27: =E27/26*26 -> 6000 | P27: =E27/27*21 -> 4666.6667 | Q27: 1091 | R27: =E27/22*22 -> 6000 | S27: =E27/22*20 -> 5454.5455 | T27: =E27/22*22 -> 6000
A28: 12 | B28: Rifah Shaikh | C28: Marketing | D28: 6000 | E28: 6000 | F28: 45358 | H28: Akbar Sir | I28: NA | J28: NA | K28: =E28/20*12 -> 3600 | L28: 6000 | M28: =E28/22*17 -> 4636.3636 | N28: =E28/21*17 -> 4857.1429 | O28: =E28/22*20.5 -> 5590.9091 | P28: =E28/22*22 -> 6000 | Q28: =E28/22*21 -> 5727.2727 | R28: =E28/22*22 -> 6000 | S28: =E28/22*19.5 -> 5318.1818 | T28: =E28/22*15.5 -> 4227.2727 | U28: 6.5 Annual leaves | AD28: =N28 -> 4857.1429 | AE28: =O28 -> 5590.9091 | AF28: =P28 -> 6000 | AG28: =Q28 -> 5727.2727 | AH28: =R28 -> 6000 | AI28: =S28 -> 5318.1818 | AJ28: =T28 -> 4227.2727
A29: 42 | B29: Saleha khan | C29: Salesforce admin | D29: 20000 | E29: 5000 | F29: 45364 | G29: 45729 | H29: Akbar Sir | I29: 7000 | J29: 7000 | K29: =4000+2000 -> 6000 | L29: 5000 | M29: 3000 | N29: 0 | O29: 3000 | P29: =E29/22*19-500 -> 3818.1818 | Q29: 0 | R29: =E29/22*21 -> 4772.7273 | S29: 2000 | T29: 3500 | U29: 1.5 leaves | X29: =SUM(I29:V29) -> 45090.909 | Y29: ='[3]2022'!U63 -> 50000
A30: 13 | B30: Sana Choudhary | C30: Marketing | D30: 25000 | E30: 5000 | F30: 44937 | H30: Akbar Sir | I30: 5000 | J30: 5000 | K30: 5000 | L30: 5000 | M30: 5000 | N30: =E30/21*21 -> 5000 | O30: =E30/22*21 -> 4772.7273 | P30: =E30/22*22 -> 5000 | Q30: =E30/22*21 -> 4772.7273 | R30: =E30/22*22 -> 5000 | S30: =E30/22*21 -> 4772.7273 | T30: =E30/22*19.5 -> 4431.8182 | U30: 1 half day and 2 leaves | X30: =SUM(I30:V30) -> 58750 | Y30: ='[3]2022'!U20 -> 20727.273
A31: 52 | B31: Saniya khanam | C31: Uipath | D31: 10000 | E31: 6000 | F31: 45227 | G31: 45775 | H31: Akbar Sir | I31: =E31/27*18 -> 4000 | J31: 4000 | K31: 4000 | L31: =4000/23*22 -> 3826.087 | M31: 6000 | N31: =E31/21*21 -> 6000 | O31: =E31/22*20 -> 5454.5455 | P31: 2000 | Q31: 3000 | R31: =E31/22*19.5 -> 5318.1818 | S31: 3000 | T31: =E31/22*22 -> 6000 | X31: =SUM(I31:V31) -> 52598.814
A32: 10 | B32: Saqlain Supariwala | C32: Joget | D32: 10000 | E32: 6000 | F32: 45420 | G32: 46150 | H32: Akbar Sir | I32: NA | J32: NA | K32: NA | L32: NA | M32: 2308 | N32: =E32/26*26 -> 6000 | O32: =E32/26*25 -> 5769.2308 | P32: =E32/27*27 -> 6000 | Q32: =E32/26*25 -> 5769.2308 | R32: =E32/26*26 -> 6000 | S32: =E32/22*22 -> 6000 | T32: =E32/22*22 -> 6000 | AD32: =M32 -> 2308 | AF32: =P32 -> 6000 | AG32: =Q32 -> 5769.2308 | AH32: =R32 -> 6000 | AI32: =S32 -> 6000 | AJ32: =T32 -> 6000
A33: 29 | B33: Shahad Alam Chaudary | C33: PowerApps | D33: 10000 | E33: 6000 | F33: 45286 | G33: 45834 | H33: Akbar Sir | I33: =4000/23*22 -> 3826.087 | J33: 4000 | K33: 4000 | L33: =4000/23*22 -> 3826.087 | M33: 4000 | N33: =4000/26*26 -> 4000 | O33: =E33/22*22 -> 6000 | P33: =E33/22*22 -> 6000 | Q33: =E33/22*22 -> 6000 | R33: =E33/22*22 -> 6000 | S33: =E33/22*12 -> 3272.7273 | T33: =E33/22*22 -> 6000
A34: 45 | B34: Shaikh Saif | C34: Salesforce admin | D34: 6000 | E34: 4000 | F34: 45383 | G34: 46113 | H34: Akbar Sir | I34: NA | J34: NA | K34: NA | L34: NA | M34: NA | N34: NA | O34: =E34/27*19 -> 2814.8148 | P34: =E34/27*19.5 -> 2888.8889 | Q34: 0 | R34: =E34/22*15 -> 2727.2727 | S34: =E34/22*15.5 -> 2818.1818 | T34: =E34/22*22 -> 4000
A35: 6 | B35: Shaikh Tareque | C35: Joget | D35: 40000 | E35: 10000 | F35: 44798 | G35: 45163 | H35: Akbar Sir | I35: =E35/23*18 -> 7826.087 | J35: 10000 | K35: 8000 | L35: 8000 | M35: 10000 | N35: =E35/21*20 -> 9523.8095 | O35: =E35/22*22 -> 10000 | P35: 9500 | Q35: 8000 | R35: =E35/22*22 -> 10000 | S35: =E35/22*20.5 -> 9318.1818 | T35: =E35/22*20.5 -> 9318.1818 | U35: 1.5 leaves | X35: =SUM(I35:V35) -> 109486.26 | Y35: ='[3]2022'!U6 -> 10619.048 | AD35: =M35 -> 10000
A36: 35 | B36: Shaziya Shaikh | C36: Sales | D36: 6000 | E36: 6000 | F36: 45477 | H36: Akbar Sir | O36: =E36/22*16 -> 4363.6364 | P36: =E36/22*22 -> 6000 | Q36: =E36/22*22 -> 6000 | R36: 4000 | S36: =E36/22*22 -> 6000 | T36: 5000 | AH36: =R36 -> 4000 | AI36: =S36 -> 6000 | AJ36: =T36 -> 5000
A37: 2 | B37: Sherkhan Misbah ismail | C37: Accounts | D37: 13000 | E37: 8000 | H37: Akbar Sir | I37: 8000 | J37: 8000 | K37: 8000 | L37: =E37/23*22 -> 7652.1739 | M37: 8000 | N37: =E37/21*20 -> 7619.0476 | O37: =E37/22*19 -> 6909.0909 | P37: =E37/22*19.5 -> 7090.9091 | Q37: 8000 | R37: =E37/22*21 -> 7636.3636 | S37: =E37/22*12 -> 4363.6364 | T37: 6636 | U37: 1 Leave | V37: bank account not opened | W37: =SUM(I37:T37) -> 87907.222 | X37: ='2023'!AN4 -> 20045.455 | Y37: 8000 | Z37: =I37 -> 8000 | AA37: 8000 | AB37: 8000 | AC37: =L37 -> 7652.1739 | AD37: =M37 -> 8000 | AE37: =N37 -> 7619.0476 | AF37: =P37 -> 7090.9091 | AG37: 8000 | AH37: =R37 -> 7636.3636 | AI37: =S37 -> 4363.6364 | AJ37: =T37 -> 6636 | AK37: =SUM(Y37:AJ37) -> 88998.131 | AL37: 0 | AM37: ='2022'!G3 -> 5000 | AN37: =SUM('2021'!O3:R3) -> 15045.455 | AO37: 0 | AP37: =SUM(AL37:AO37) -> 20045.455
A38: 36 | B38: Shirin Muzaffar | C38: Sales | D38: 6000 | E38: 6000 | H38: Akbar Sir | I38: NA | J38: NA | K38: NA | L38: NA | M38: =E38/22*14 -> 3818.1818 | N38: 6000 | O38: =E38/22*19.5 -> 5318.1818 | P38: =E38/22*22 -> 6000 | Q38: =E38/22*21 -> 5727.2727 | R38: =E38/22*21 -> 5727.2727 | S38: =E38/22*19 -> 5181.8182 | T38: =E38/22*22 -> 6000 | AD38: After 2 month salary | AF38: =P38 -> 6000 | AG38: =Q38 -> 5727.2727 | AH38: =R38 -> 5727.2727 | AI38: =S38 -> 5181.8182 | AJ38: =T38 -> 6000
A39: 33 | B39: Shirin Muzaffar (Lead Bonus) | C39: Sales | D39: 6000 | E39: 6000 | H39: Akbar Sir | I39: NA | J39: NA | K39: NA | L39: NA | M39: NA | N39: NA | O39: NA | P39: NA | Q39: 0 | R39: 6000 | S39: =E39/22*22 -> 6000 | T39: 6000 | U39: Point of Rental (Salesforce CPQ) Singed but terminated focustek (Full Stack developer )contract signed CPPBI (Tableau Development )Contract | X39: =SUM(I39:V39) -> 18000 | Z39: =I39 -> NA | AA39: 6000 | AB39: 6000 | AC39: a | AD39: 6000 | AE39: =N39 -> NA | AF39: =P39 -> NA | AG39: =Q39 -> 0 | AH39: =R39 -> 6000 | AI39: =S39 -> 6000 | AJ39: =T39 -> 6000 | AK39: =V39 -> 0
A40: 43 | B40: Sohail Inamdar | C40: Salesforce admin | D40: 30000 | E40: 5000 | F40: 45383 | G40: 45748 | H40: Akbar Sir | I40: NA | J40: NA | K40: NA | L40: =E40/23*18 -> 3913.0435 | M40: 5000 | N40: =E40/21*21 -> 5000 | O40: =E40/22*22 -> 5000 | P40: 4500 | Q40: =E40/22*22 -> 5000 | R40: =E40/22*20 -> 4545.4545 | S40: =E40/22*17 -> 3863.6364 | T40: =E40/22*13 -> 2954.5455 | U40: 9 Annual leaves | AD40: 5000 | AE40: =N40 -> 5000 | AF40: =P40 -> 4500 | AG40: =Q40 -> 5000 | AH40: =R40 -> 4545.4545 | AI40: =S40 -> 3863.6364 | AJ40: =T40 -> 2954.5455
A41: 30 | B41: Sufiya kalepad | C41: PowerApps | D41: 10000 | E41: 6000 | F41: 45323 | G41: 46054 | H41: Akbar Sir | I41: NA | J41: =4000/27*21 -> 3111.1111 | K41: 4000 | L41: =4000/23*22 -> 3826.087 | M41: =4000/22*19 -> 3454.5455 | N41: =4000/26*20 -> 3076.9231 | O41: =4000/26*22 -> 3384.6154 | P41: =3000-500 -> 2500 | Q41: =E41/22*22 -> 6000 | R41: =E41/22*20 -> 5454.5455 | S41: =E41/22*14 -> 3818.1818 | T41: 0 | U41: 2 Leaves | V41: low performance
A42: 46 | B42: Swati Amode | C42: Salesforce admin | D42: 25000 | E42: 5000 | F42: 44806 | G42: 45171 | H42: Akbar Sir | I42: =E42/23*16 -> 3478.2609 | J42: 5000 | K42: =E42/20*16 -> 4000 | L42: =E42/23*21 -> 4565.2174 | M42: 5000 | N42: =E42/21*14 -> 3333.3333 | O42: =E42/22*20 -> 4545.4545 | P42: =E42/22*15 -> 3409.0909 | Q42: =E42/22*19 -> 4318.1818 | R42: =E42/22*20 -> 4545.4545 | S42: =E42/22*16 -> 3636.3636 | T42: =E42/22*22 -> 5000 | X42: =SUM(I42:V42) -> 50831.357 | Y42: ='[3]2022'!U59 -> 10000 | AD42: =M42 -> 5000
A43: 48 | B43: Vishakah | C43: Salesforce admin | D43: 10000 | E43: 6000 | F43: 45356 | G43: 45721 | H43: Akbar Sir | I43: N/A | J43: N/A | K43: =E43/20*14 -> 4200 | L43: =E43/23*20 -> 5217.3913 | M43: =E43/22*12 -> 3272.7273 | N43: =E43/21*19.5 -> 5571.4286 | O43: =E43/22*20.5 -> 5590.9091 | P43: =E43/22*19 -> 5181.8182 | Q43: =E43/22*21.5 -> 5863.6364 | R43: =E43/22*21 -> 5727.2727 | S43: =E43/22*18.5 -> 5045.4545 | T43: =E43/22*20 -> 5454.5455 | U43: 2 leaves
A44: 37 | B44: Yasmeen Shaikh | C44: Sales | D44: 15000 | E44: 10000 | F44: 44936 | G44: 45301 | H44: Akbar Sir | I44: 10000 | J44: 10000 | K44: 10000 | L44: 0 | M44: 10000 | N44: 0 | O44: =E44/22*21 -> 9545.4545 | P44: =E44/22*22 -> 10000 | Q44: =E44/22*21 -> 9545.4545 | R44: =E44/22*22 -> 10000 | S44: =E44/22*22 -> 10000 | T44: 10000 | U44: Point of Rental (Salesforce CPQ) Singed but terminated focustek (Full Stack developer )contract signed CPPBI (Tableau Development )Contract | W44: =SUM(I44:V44) -> 99090.909 | X44: =W44-AJ44 -> 99090.909 | AH44: =R44 -> 10000 | AK44: =SUM(Z44:AJ44) -> 10000 | AP44: =W44-AK44 -> 89090.909
A45: 56 | B45: TOTAL | D45: =SUBTOTAL(9,D1:D12,D15,D16:D27) -> 0 | E45: =SUM(E2:E44) -> 267000 | H45: =SUM(H21:H27) -> 0 | I45: =SUM(I1:I27) -> 113458.64 | J45: =SUM(J1:J27) -> 113636.36 | K45: =SUM(K1:K27) -> 121500 | L45: =SUM(L21:L27) -> 36626.409 | M45: =SUM(M21:M27) -> 36581.028 | R45: =SUM(R21:R27) -> 46227.273 | T45: =SUM(T2:T44) -> 210386 | V45: =SUM(V21:V27) -> 0 | X45: =SUM(X21:X27) -> 313511.78 | Y45: =SUM(Y21:Y27) -> 142000 | Z45: =SUM(Z21:Z27) -> 15000 | AA45: =SUM(AA21:AA27) -> 15000 | AB45: =SUM(AB1:AB27) -> 67500 | AC45: =SUM(AC21:AC27) -> 23148.148 | AD45: =SUM(AD21:AD41) -> 58437.87 | AE45: =SUM(AE21:AE27) -> 15000 | AF45: =SUM(AF21:AF27) -> 24090.909 | AH45: =SUM(AH21:AH27) -> 23181.818 | AI45: =SUM(AI21:AI27) -> 22590.909 | AJ45: =SUM(AJ21:AJ27) -> 19000 | AK45: =SUM(AK21:AK27) -> 0 | AL45: =SUM(AL21:AL27) -> 0 | AM45: =SUM(AM21:AM27) -> 0 | AN45: =SUM(AN21:AN27) -> 0 | AO45: =SUM(AO21:AO27) -> 0 | AP45: =SUM(AP21:AP27) -> 0
R46: 2455

Sheet 2025
A1: Sr No | B1: Name of the Employee | C1: Technology | D1: Salary | E1: Bonus amount | F1: Commitment Start date | G1: Commitment End date | H1: Reporting manager | I1: Jan | J1: Feb | K1: March | L1: April | M1: Comment | N1: Remark | O1: This year 2025 bonus amount | P1: Deposit bonus Amount along with us till 2024 paid after notice period /Contract | Q1: To be Paid with Salary in Jan 2025 | R1: To be Paid with Salary in Feb 2025 | S1: To be Paid with Salary in Mar 2025 | T1: To be Paid with Salary in Apr 2025 | U1: To be Paid with Salary in May 2025 | V1: To be Paid with Salary in Jun 2025 | W1: To be Paid with Salary in July 2025 | X1: To be Paid with Salary in Aug 2025 | Y1: To be Paid with Salary in Sep 2025 | Z1: To be Paid with Salary in Oct 2025 | AA1: To be Paid with Salary in Nov 2025 | AB1: To be Paid with Salary in Dec 2025 | AC1: Total bonus given in 2025 amount | AD1: remaining 2024 | AE1: remaining 2023 | AF1: remaining 2022 | AG1: remaining 2021 | AH1: remaining 2020 | AI1: Total Balance need to pay after notice period
A2: 1 | B2: Farheen Sultanpuri | C2: Odoo | D2: 6000 | E2: 6000 | H2: Akbar Sir | I2: =E2/23*22.5 -> 5869.5652 | J2: =E2/21*19 -> 5428.5714 | K2: =E2/20*20 -> 6000 | L2: =E2/23*23 -> 6000 | O2: =SUM(I2:K2) -> 17298.137 | P2: 12000 | Q2: =I2 -> 5869.5652 | R2: =J2 -> 5428.5714 | S2: =K2 -> 6000 | AC2: =SUM(Q2:AB2) -> 17298.137 | AD2: 0 | AE2: =SUM('2023'!O5:P5) -> 12000 | AF2: 0 | AG2: 0 | AH2: 0 | AI2: =SUM(AD2:AH2) -> 12000
A3: 2 | B3: Samreen Suapriwala | C3: Accounts | D3: 6000 | E3: 6000 | F3: 45712 | H3: Akbar Sir | I3: NA | J3: NA | K3: =E3/20*20 -> 6000 | L3: =E3/23*23 -> 6000
A4: 3 | B4: Sherkhan Misbah ismail | C4: Accounts | D4: 13000 | E4: 8000 | H4: Akbar Sir | I4: =E4/23*23 -> 8000 | J4: 3000 | K4: =E4/20*20 -> 8000 | L4: =E4/23*23 -> 8000 | O4: =SUM(I4:K4) -> 19000 | P4: =SUM(M4:N4) -> 0 | Q4: =I4 -> 8000 | R4: =J4 -> 3000 | S4: =K4 -> 8000 | AC4: =SUM(T4:AB4) -> 0 | AD4: 0 | AE4: 0 | AF4: ='2022'!G3 -> 5000 | AG4: =SUM('2021'!O3:R3) -> 15045.455 | AH4: 0 | AI4: =SUM(AD4:AH4) -> 20045.455
A5: 4 | B5: Ajida Samani | C5: HR | D5: 6000 | E5: 6000 | F5: 45476 | H5: Akbar Sir | I5: 5500 | J5: =E5/21*21 -> 6000 | K5: =E5/20*18.5 -> 5550 | L5: =E5/23*20 -> 5217.3913 | M5: 3 Leaves | Q5: =I5 -> 5500 | R5: =J5 -> 6000 | S5: =K5 -> 5550
A6: 5 | B6: Ansari Yasmeen | C6: HR | D6: 12000 | E6: 9000 | H6: Akbar Sir | I6: =E6/23*22 -> 8608.6957 | J6: =E6/21*11 -> 4714.2857 | K6: =E6/20*16.5 -> 7425 | L6: =E6/23*20 -> 7826.087 | M6: 3 Leaves | P6: =SUM(M6:N6) -> 0 | Q6: =I6 -> 8608.6957 | R6: =J6 -> 4714.2857 | S6: =K6 -> 7425
A7: 6 | B7: Shaikh Tareque | C7: Joget | D7: 40000 | E7: 10000 | F7: 44798 | G7: 45163 | H7: Akbar Sir | I7: =E7/23*23 -> 10000 | J7: =E7/21*20.5 -> 9761.9048 | K7: 10000 | L7: =E7/23*23 -> 10000 | P7: =SUM(M7:N7) -> 0
A8: 7 | B8: Arshduddin Ansari MohammedMasooduddin | C8: Joget | D8: 30000 | E8: 5000 | F8: 44806 | G8: 45171 | H8: Akbar Sir | I8: =E8/23*23-500 -> 4500 | J8: 4500 | K8: 4500 | L8: =E8/23*23 -> 5000 | P8: =SUM(M8:N8) -> 0
A9: 8 | B9: Huzaif Khot | C9: Joget | D9: 30000 | E9: 5000 | F9: 45317 | G9: 45683 | H9: Akbar Sir | I9: =E9/23*23 -> 5000 | J9: =E9/21*21 -> 5000 | K9: =E9/20*20 -> 5000 | L9: =E9/23*15 -> 3260.8696 | M9: 8 Leaves | P9: =SUM(M9:N9) -> 0 | Q9: =I9 -> 5000 | R9: =J9 -> 5000 | S9: =K9 -> 5000
A10: 9 | B10: Nagma Khan | C10: Joget | D10: 27000 | E10: 10000 | H10: Akbar Sir | I10: =E10/23*23 -> 10000 | J10: =E10/21*21 -> 10000 | K10: =E10/20*20 -> 10000 | L10: =E10/23*23 -> 10000 | P10: =SUM(M10:N10) -> 0 | Q10: =I10 -> 10000 | R10: =J10 -> 10000 | S10: =K10 -> 10000 | AC10: =N10 -> 0
A11: 10 | B11: Saqlain Supariwala | C11: Joget | D11: 10000 | E11: 6000 | F11: 45420 | G11: 46150 | H11: Akbar Sir | I11: 3000 | J11: 0 | K11: =E11/20*20 -> 6000 | L11: 0 | M11: 3.5 Leaves | N11: porject not delivered
A12: 11 | B12: Rifah Shaikh | C12: Marketing | D12: 6000 | E12: 6000 | F12: 45358 | H12: Akbar Sir | I12: =E12/23*21 -> 5478.2609 | J12: =E12/21*20 -> 5714.2857 | K12: =E12/20*20 -> 6000 | L12: =E12/23*20 -> 5217.3913 | M12: 3 Leaves | Q12: =I12 -> 5478.2609 | R12: =J12 -> 5714.2857 | S12: =K12 -> 6000
A13: 12 | B13: Sana Choudhary | C13: Marketing | D13: 25000 | E13: 5000 | F13: 44937 | H13: Akbar Sir | I13: =E13/23*17.5 -> 3804.3478 | J13: =E13/21*20.5 -> 4880.9524 | K13: =E13/20*20 -> 5000 | L13: =E13/23*23 -> 5000 | P13: =SUM(M13:N13) -> 0
A14: 13 | B14: Hamza khot | C14: Salesforce | D14: 16000 | E14: 6000 | F14: 45608 | G14: 46338 | H14: Akbar Sir | I14: =E14/23*23 -> 6000 | J14: =E14/21*21 -> 6000 | K14: =E14/20*20 -> 6000 | L14: =E14/23*23 -> 6000 | P14: =SUM(M14:N14) -> 0
A15: 14 | B15: Naeem Imran | C15: Salesforce | D15: 10000 | E15: 10000 | F15: 45362 | G15: 45727 | H15: Akbar Sir | I15: 0 | J15: =E15/21*19 -> 9047.619 | K15: 9500 | L15: =E15/23*23 -> 10000 | P15: =SUM(M15:N15) -> 0 | Q15: =I15 -> 0 | R15: =J15 -> 9047.619 | S15: =K15 -> 9500
A16: 15 | B16: Muzaffar Sayyed | C16: Salesforce | D16: 10000 | E16: 6000 | F16: 45286 | G16: 45834 | H16: Akbar Sir | I16: =E16/23*18 -> 4695.6522 | J16: =E16/21*21 -> 6000 | K16: =E16/20*20 -> 6000 | L16: =E16/23*23 -> 6000
A17: 16 | B17: Alfahad Shaikh | C17: OIC | D17: 10000 | E17: 6000 | F17: 45271 | G17: 45819 | H17: Akbar Sir | I17: 4696 | J17: 6000 | K17: 0 | L17: 2000 | M17: 3.5 leaves | N17: slow
A18: 17 | B18: Fahim Shaikh | C18: Power Bi | D18: 15000 | E18: 6000 | F18: 45728 | G18: 46093 | H18: Akbar Sir | I18: =E18/23*23 -> 6000 | J18: =E18/21*21 -> 6000 | K18: =E18/20*20 -> 6000 | L18: =E18/23*22 -> 5739.1304 | M18: 1 leave | P18: =SUM(M18:N18) -> 0
A19: 18 | B19: Kashaf Shaikh | C19: Power Bi | D19: 6000 | E19: 4000 | F19: 45517 | G19: 46246 | H19: Akbar Sir | I19: =E19/27*26.5 -> 3925.9259 | J19: =E19/26*26 -> 4000 | K19: 4000 | L19: =E19/23*20.5 -> 3565.2174 | M19: 2.5 leaves
A20: 19 | B20: Abdus Samad Chaudhary | C20: Power Bi | D20: 10000 | E20: 6000 | F20: 45227 | G20: 45775 | H20: Akbar Sir | I20: =E20/23*23 -> 6000 | J20: =E20/21*21 -> 6000 | K20: =E20/20*11 -> 3300 | L20: =E20/23*22 -> 5739.1304 | M20: 1 leave | P20: =SUM(M20:N20) -> 0
A21: 20 | B21: Imran Ahmed | C21: PowerApps | D21: 25000 | E21: 5000 | F21: 44830 | G21: 45195 | H21: Akbar Sir | I21: 0 | J21: =E21/21*21 -> 5000 | K21: 5000 | L21: 0 | N21: Not on prodject | P21: =SUM(M21:N21) -> 0 | Q21: =I21 -> 0 | R21: =J21 -> 5000 | S21: =K21 -> 5000
A22: 21 | B22: Shahad Alam Chaudary | C22: PowerApps | D22: 10000 | E22: 6000 | F22: 45286 | G22: 45834 | H22: Akbar Sir | I22: =E22/23*19 -> 4956.5217 | J22: =E22/21*21 -> 6000 | K22: =E22/20*20 -> 6000 | L22: 2000 | M22: project not delivered
A23: 22 | B23: Sufiya kalepad | C23: PowerApps | D23: 10000 | E23: 6000 | F23: 45323 | G23: 46054 | H23: Akbar Sir | I23: =E23/23*18 -> 4695.6522 | J23: =E23/21*21 -> 6000 | K23: =E23/20*20 -> 6000 | L23: =E23/23*23 -> 6000
A24: 23 | B24: Pratham | C24: Power Bi | D24: 8000 | E24: 6000 | F24: 45369 | G24: 45553 | H24: Akbar Sir | I24: =E24/23*23 -> 6000 | J24: =E24/21*21 -> 6000 | K24: 5500 | L24: =E24/23*15 -> 3913.0435 | M24: 8 leaves
A25: 24 | B25: Shaziya Shaikh | C25: Sales | D25: 6000 | E25: 6000 | F25: 45477 | H25: Akbar Sir | I25: =E25/23*23 -> 6000 | J25: =E25/21*21 -> 6000 | K25: =E25/20*20 -> 6000 | L25: =E25/23*13 -> 3391.3043 | M25: 10 Leaves | Q25: =I25 -> 6000 | R25: =J25 -> 6000 | S25: =K25 -> 6000
A26: 25 | B26: Shirin Muzaffar | C26: Sales | D26: 6000 | E26: 6000 | H26: Akbar Sir | I26: =E26/23*23 -> 6000 | J26: =E26/21*21 -> 6000 | K26: =E26/20*20 -> 6000 | L26: =E26/23*20 -> 5217.3913 | M26: 3 Leaves | Q26: =I26 -> 6000 | R26: =J26 -> 6000 | S26: =K26 -> 6000
A27: 26 | B27: Shirin Muzaffar (Lead Bonus) | C27: Sales | D27: 6000 | E27: 6000 | H27: Akbar Sir | I27: - | J27: =E27/21*21 -> 6000 | K27: =E27/20*20 -> 6000 | L27: =E27/23*23 -> 6000 | M27: Grover corlew : Sharepoint hourly support for 6 month contract signed (Sufiya is working) | P27: =SUM(M27:N27) -> 0 | Q27: =SUM(N27:O27) -> 0 | R27: =J27 -> 6000 | S27: =K27 -> 6000 | AC27: =N27 -> 0
A28: 27 | B28: Yasmeen Shaikh | C28: Sales | D28: 15000 | E28: 10000 | F28: 44936 | G28: 45301 | H28: Akbar Sir | I28: 0 | J28: =E28/21*21 -> 10000 | K28: =E28/20*20 -> 10000 | L28: =E28/23*23 -> 10000 | M28: Grover corlew : Sharepoint hourly support for 6 month contract signed (Sufiya is working) | O28: =SUM(M28:N28) -> 0 | P28: =O28-AB28 -> 0 | AC28: =SUM(R28:AB28) -> 0 | AI28: =O28-AC28 -> 0
A29: 28 | B29: Mohammad Rehanuddin | C29: Salesforce admin | D29: 52000 | E29: 5000 | F29: 44491 | G29: 44856 | H29: Akbar Sir | I29: 0 | J29: =E29/21*21 -> 5000 | K29: =E29/20*20 -> 5000 | L29: =E29/23*23 -> 5000 | P29: =SUM(M29:N29) -> 0 | Q29: =I29 -> 0 | R29: =J29 -> 5000 | S29: =K29 -> 5000 | AC29: =N29 -> 0
A30: 29 | B30: Saleha khan | C30: Salesforce admin | D30: 20000 | E30: 5000 | F30: 45364 | G30: 45729 | H30: Akbar Sir | I30: =E30/23*22.5 -> 4891.3043 | J30: =E30/21*19.5 -> 4642.8571 | K30: 4500 | L30: 2500 | M30: Not clients work is slow | P30: =SUM(M30:N30) -> 0
A31: 30 | B31: Sohail Inamdar | C31: Salesforce admin | D31: 30000 | E31: 5000 | F31: 45383 | G31: 45748 | H31: Akbar Sir | I31: =E31/23*23 -> 5000 | J31: =E31/21*21 -> 5000 | K31: =E31/20*20 -> 5000 | L31: =E31/23*23 -> 5000 | Q31: =I31 -> 5000 | R31: =J31 -> 5000 | S31: =K31 -> 5000
A32: 31 | B32: Mohammad Faiz | C32: Salesforce admin | D32: 10000 | E32: 6000 | F32: 45383 | G32: 46113 | H32: Akbar Sir | I32: 3913 | J32: 4000 | K32: 5500 | L32: =E32/23*23 -> 6000
A33: 32 | B33: Shaikh Saif | C33: Salesforce admin | D33: 10000 | E33: 6000 | F33: 45383 | G33: 46113 | H33: Akbar Sir | I33: 4000 | J33: 3810 | K33: 0 | L33: 0 | M33: noyt on client
A34: 33 | B34: Swati Amode | C34: Salesforce admin | D34: 25000 | E34: 5000 | F34: 44806 | G34: 45171 | H34: Akbar Sir | I34: =E34/23*22.5 -> 4891.3043 | J34: =E34/21*18 -> 4285.7143 | K34: =E34/20*0+K34 -> 0 | L34: =F34/20*0+L34 -> 0 | M34: On leave
A35: 34 | B35: Abdul Raheem | C35: Salesforce admin | D35: 6000 | E35: 4000 | F35: 45428 | G35: 46158 | H35: Akbar Sir | I35: =E35/23*23 -> 4000 | J35: =E35/21*19 -> 3619.0476 | K35: =E35/20*18 -> 3600 | L35: =E35/23*22 -> 3826.087 | M35: 1 leave
A36: 35 | B36: Vishakah | C36: Salesforce admin | D36: 10000 | E36: 6000 | F36: 45356 | G36: 45721 | H36: Akbar Sir | I36: =E36/23*22 -> 5739.1304 | J36: =E36/21*18.5 -> 5285.7143 | K36: =E36/20*20 -> 6000 | L36: =E36/23*22 -> 5739.1304 | M36: 1 leave
A37: 36 | B37: Maaz Shaokat Choughle | C37: Salesforce CPQ | D37: 57000 | E37: 5000 | F37: 45370 | G37: 45735 | H37: Akbar Sir | I37: =E37/23*22 -> 4782.6087 | J37: =E37/21*21 -> 5000 | K37: =E37/20*20 -> 5000 | L37: =E37/23*23 -> 5000 | P37: =SUM(M37:N37) -> 0 | Q37: =I37 -> 4782.6087 | R37: =J37 -> 5000 | S37: =K37 -> 5000
A38: 37 | B38: Naheed Khan | C38: Salesforce CPQ | D38: 15000 | E38: 6000 | F38: 45154 | G38: 45520 | H38: Akbar Sir | I38: =E38/23*22 -> 5739.1304 | J38: =E38/21*21 -> 6000 | K38: =E38/20*20 -> 6000 | L38: =E38/23*23 -> 6000 | P38: =SUM(M38:N38) -> 0 | Q38: =SUM(N38:O38) -> 0 | R38: =SUM(O38:P38) -> 0
A39: 38 | B39: Saniya khanam | C39: PowerApps | D39: 10000 | E39: 6000 | F39: 45227 | G39: 45775 | H39: Akbar Sir | I39: =E39/23*23 -> 6000 | J39: =E39/21*19.5 -> 5571.4286 | K39: =E39/20*20 -> 6000 | L39: =E39/23*23 -> 6000 | P39: =SUM(M39:N39) -> 0 | Q39: =SUM(N39:O39) -> 0
A40: 39 | B40: Owais Chipa | C40: Marketing | D40: 6000 | E40: 6000 | F40: 45498 | H40: Akbar Sir | I40: 6000 | J40: =E40/21*21 -> 6000 | K40: =E40/20*20 -> 6000 | L40: 0 | M40: 4 leaves | N40: project not dleivered | Q40: =I40 -> 6000 | R40: =J40 -> 6000 | S40: =K40 -> 6000
A41: 40 | B41: Amir shaikh | C41: Wordpress | D41: 20000 | E41: 5000 | F41: 45061 | H41: Akbar Sir | I41: 5000 | J41: 5000 | K41: =E41/20*20 -> 5000 | L41: =E41/23*15 -> 3260.8696 | M41: 8 leaves | P41: =SUM(M41:N41) -> 0 | Q41: =I41 -> 5000 | R41: =J41 -> 5000 | S41: =K41 -> 5000 | AC41: =N41 -> 0
A42: 56 | B42: TOTAL | D42: =SUBTOTAL(9,D1:D12,D14,D15:D25) -> 322000 | E42: =SUM(E2:E41) -> 247000 | H42: =SUM(H20:H25) -> 0 | N42: =SUM(N20:N25) -> 0 | P42: =SUM(P20:P25) -> 0 | Q42: =I42 -> 0 | R42: =SUM(R20:R25) -> 11000 | S42: =SUM(S20:S25) -> 11000 | T42: =SUM(T1:T25) -> 0 | U42: =SUM(U20:U25) -> 0 | V42: =SUM(V20:V38) -> 0 | W42: =SUM(W20:W25) -> 0 | X42: =SUM(X20:X25) -> 0 | Z42: =SUM(Z20:Z25) -> 0 | AA42: =SUM(AA20:AA25) -> 0 | AB42: =SUM(AB20:AB25) -> 0 | AC42: =SUM(AC20:AC25) -> 0 | AE42: =SUM(AE20:AE25) -> 0 | AF42: =SUM(AF20:AF25) -> 0 | AG42: =SUM(AG20:AG25) -> 0 | AH42: =SUM(AH20:AH25) -> 0 | AI42: =SUM(AI20:AI25) -> 0

Sheet Client Facing Bonus 2025
A1: Sr No | B1: Name | C1: Technology | D1: Salary | E1: Bonus | F1: Client Bonus | G1: Client Name | H1: 45658 | I1: 45689 | J1: 45717 | K1: 45748 | L1: Comments | M1: Total bonus amount | N1: Paid Status
A2: 1 | B2: Nagma Khan | C2: Share point | D2: 27000 | E2: 10000 | F2: 15000 | G2: Retail First | H2: =F2/176*52 -> 4431.8182 | I2: =F2/176*52 -> 4431.8182 | J2: =F2/160*52 -> 4875 | K2: =F2/184*52 -> 4239.1304 | M2: =SUM(H2:I2) -> 8863.6364
A3: 2 | F3: 15000 | G3: ThinkBiz | H3: 15000 | I3: =F3/21*21 -> 15000 | J3: =F3/20*20 -> 15000 | K3: =F3/23*23 -> 15000 | M3: =SUM(H3:I3) -> 30000
A4: 3 | B4: Huzaif Khot | C4: SharePoint | F4: 15000 | G4: PowerAutomate | H4: =F4/176*88+7500+1429 -> 16429 | I4: =F4/168*12 -> 1071.4286 | J4: =F4/160*14.5 -> 1359.375 | K4: - | M4: =SUM(H4:I4) -> 17500.429
A5: 4 | D5: 30000 | E5: 5000 | F5: 9000 | G5: ThinkBiz | H5: =F5/23*23 -> 9000 | I5: =F5/21*21 -> 9000 | J5: =F5/20*20 -> 9000 | K5: NA | M5: =SUM(H5:I5) -> 18000
A6: 5 | B6: Saniya Khannam | C6: Power Apps | D6: 10000 | E6: 6000 | F6: 15000 | G6: PowerAutomate | I6: =F6/168*76 -> 6785.7143 | J6: =F6/160*51+16 -> 4797.25 | K6: =F6/184*92 -> 7500 | M6: =SUM(H6:I6) -> 6785.7143
A7: 6 | B7: Ansari MohammedArshduddin MohammedMasooduddin | C7: SharePoint | D7: 30000 | E7: 5000 | F7: 9000 | G7: ThinkBiz | H7: =F7/23*23 -> 9000 | I7: =F7/21*21 -> 9000 | J7: =F7/20*20 -> 9000 | K7: =F7/23*23 -> 9000 | M7: =SUM(H7:I7) -> 18000
A8: 7 | B8: Imran patel | C8: Salesforce admin | D8: 25000 | E8: 10000 | F8: 9000 | G8: Cloud360 | H8: =F8/23*23 -> 9000 | I8: =F8/21*21 -> 9000 | J8: 0 | K8: 9000 | M8: =SUM(H8:I8) -> 18000
A9: 8 | B9: Samee shaikh | C9: Salesforce-Eienstein | D9: 25000 | E9: 5000 | F9: 10000 | G9: Cloud360 | H9: =F9/23*18 -> 7826.087 | I9: =F9/21*21 -> 10000 | J9: 0 | K9: 10000 | M9: =SUM(H9:I9) -> 17826.087
A10: 9 | B10: Minhaj mohammed | C10: SharePoint | D10: 20000 | E10: 0 | F10: 10000 | G10: ThinkBiz | H10: =F10/23*23 -> 10000 | I10: =F10/21*21-500 -> 9500 | J10: =F10/20*20 -> 10000 | K10: =F10/23*23 -> 10000 | M10: =SUM(H10:I10) -> 19500
A11: 10 | B11: Vishakha Wagh | C11: Salesforce admin | D11: 10000 | E11: 6000 | F11: 15000 | G11: DMG | H11: NA | I11: NA | J11: =F11/20*20 -> 15000 | K11: =F11/23*22 -> 14347.826 | L11: working on behalf of swati for whole month
A12: 11 | B12: Sidra Ansari | C12: SharePoint | D12: 35000 | F12: 15000 | G12: Aban | H12: NA | I12: =F12/21*21 -> 15000 | J12: =F12/20*20 -> 15000 | K12: =F12/23*23 -> 15000 | M12: =SUM(H12:I12) -> 15000 | R12: =200/528*15000 -> 5681.8182
A13: 12 | B13: Rehanuddin | C13: Salesforce admin | D13: 52000 | E13: 5000 | F13: 15000 | G13: Foundation Partners Group | H13: NA | I13: =F13/21*16 -> 11428.571 | J13: =F13/20*20 -> 15000 | K13: =F13/23*23 -> 15000 | M13: =SUM(H13:I13) -> 11428.571
A14: 13 | F14: 8000 | G14: Night allowance | H14: NA | I14: =F14/21*16 -> 6095.2381 | J14: =F14/20*20-1905 -> 6095 | K14: =F14/23*23 -> 8000 | M14: =SUM(H14:I14) -> 6095.2381
A15: 14 | B15: Naheed Khan | C15: Salesforce admin | D15: 15000 | E15: 6000 | F15: 15000 | G15: Foundation Partners Group | H15: NA | I15: =F15/21*16 -> 11428.571 | J15: =F15/20*20 -> 15000 | K15: =F15/23*23 -> 15000 | M15: =SUM(H15:I15) -> 11428.571
A16: 15 | F16: 8000 | G16: Night allowance | H16: NA | I16: =F16/21*16 -> 6095.2381 | J16: =F16/20*20 -> 8000 | K16: =F16/23*23 -> 8000 | M16: =SUM(H16:I16) -> 6095.2381
A17: 16 | B17: Abu Syfiyan | C17: Joget | D17: 6000 | E17: 0 | F17: 20000 | G17: Thinkbiz | H17: =F17/23*23 -> 20000 | I17: =F17/21*21 -> 20000 | J17: 20000 | K17: 10000 | L17: project not delivered | M17: =SUM(H17:I17) -> 40000
A18: 17 | B18: Abdus Samad | C18: Power Bi | D18: 10000 | E18: 6000 | F18: 15000 | G18: PRODEVA | H18: =F18 -> 15000 | I18: =F18/21*20 -> 14285.714 | J18: 0 | K18: =F18/23*23 -> 15000 | M18: =SUM(H18:I18) -> 29285.714
A19: 18 | B19: Hamza Khot | C19: Salesforce | D19: 16000 | E19: 6000 | F19: 15000 | G19: ARS | H19: NA | I19: =F19/21*6 -> 4285.7143 | J19: =F19/20*20 -> 15000 | K19: =F19/23*23 -> 15000 | M19: =SUM(H19:I19) -> 4285.7143
A20: 19 | B20: Naeem Imrran | C20: Salesforce | D20: 10000 | E20: 10000 | F20: 15000 | G20: ARS | H20: NA | I20: =F20/21*6 -> 4285.7143 | J20: =F20/20*20 -> 15000 | K20: =F20/23*23 -> 15000 | M20: =SUM(H20:I20) -> 4285.7143
A21: 20 | F21: 8000 | G21: Night allowance | H21: NA | I21: =F21/21*6 -> 2285.7143 | J21: =F21/20*20 -> 8000 | K21: =F21/23*23 -> 8000 | M21: =SUM(H21:I21) -> 2285.7143
A22: 21 | B22: Sohail Inamdar | C22: Salesforce | D22: 30000 | E22: 5000 | F22: 15000 | G22: ARS | H22: NA | I22: =F22/21*6 -> 4285.7143 | J22: =F22/20*20 -> 15000 | K22: =F22/23*23 -> 15000 | M22: =SUM(H22:I22) -> 4285.7143
A23: 22 | B23: Mohammad Faiz | C23: Salesforce | D23: 10000 | E23: 6000 | F23: 10000 | G23: Jellyfish | H23: NA | I23: NA | J23: =F23/20*16 -> 8000 | K23: =F23/23*23 -> 10000 | M23: =SUM(H23:I23) -> 0
A24: 23 | B24: Raheem | C24: Salesforce | D24: 6000 | E24: 4000 | F24: 15000 | G24: Digital Media Solutions | H24: 3750 | I24: =F24/168*117.5 -> 10491.071 | J24: =F24/160*44.5 -> 4171.875 | K24: =F24/184*54 -> 4402.1739 | L24: calculated till 21 april | M24: =SUM(H24:I24) -> 14241.071
A25: 24 | B25: Pratham Singh | C25: Power Bi | D25: 8000 | E25: 6000 | F25: 15000 | G25: Oilfiled supply centre ltd | H25: NA | I25: NA | J25: =F25/20*16 -> 12000 | K25: =F25/23*15 -> 9782.6087 | L25: leave
A26: 25 | B26: Aditya Ghule | C26: Power Bi | D26: 6000 | F26: 15000 | G26: Backup | H26: NA | I26: NA | J26: NA | K26: =F26/23*8 -> 5217.3913 | L26: worked on pratham behalf and calculated till 24 april
A27: 26 | B27: Sufiya Kalepad | C27: Power Apps | D27: 10000 | E27: 6000 | F27: 15000 | G27: Enigma RM | H27: NA | I27: NA | J27: =F27/160*28 -> 2625 | K27: =F27/184*46 -> 3750
A28: 27 | D28: 10000 | E28: 6000 | F28: 15000 | G28: Grower corlew | H28: NA | I28: NA | J28: NA | K28: =F28/184*28 -> 2282.6087 | L28: Contract start on 7 April
A29: 28 | B29: Noorullah | C29: Joget | D29: 25000 | F29: 15000 | G29: Concordia | H29: NA | I29: NA | J29: NA | K29: =45000/512*270 -> 23730.469 | L29: calculated on hourly basis he worked on 270 hours till 3 month
A30: 29 | B30: Saleha Khan | C30: Power Bi | D30: 20000 | E30: 5000 | F30: 10000 | G30: CPPIB | H30: =F30/176*120 -> 6818.1818 | I30: =F30/168*175.5 -> 10446.429 | J30: =F30/160*98+14 -> 6139 | K30: =F30/184*106 -> 5760.8696 | L30: calculated till 21 april | M30: =SUM(H30:I30) -> 17264.61
B31: Total | D31: =SUM(D2:D10) -> 167000 | E31: =SUM(E2:E10) -> 41000 | F31: =SUM(F2:F30) -> 381000 | H31: =SUM(H2:H24) -> 119436.91 | I31: =SUM(I2:I30) -> 194202.65 | J31: =SUM(J2:J30) -> 234062.5 | K31: =SUM(K2:K30) -> 283013.08 | M31: =SUM(M2:M30) -> 320457.74
D34: paid
D35: Not applicable

Sheet Hold Bonus updated Feb 2025
A1: Name | B1: Deposit Rule | C1: Total Hold Bonus | D1: Hold period | E1: Comment | F1: Updated till | G1: Last paid duration | H1: Last Paid Date | I1: Amount
A2: Farheen Sultanpuri | B2: Monthly | C2: =SUM('2023'!O5:P5) -> 12000 | D2: July 2023 to August 2023 | E2: Two month salary amount is hold, monthly bonus is each given month from august 2023 | F2: March | G2: March | H2: 45742 | I2: 6000
A3: Sherkhan Misbah ismail | B3: Monthly | C3: =SUM('2021'!O3:R3)+SUM('2022'!G3) -> 20045.455 | D3: Sep 2021 to Jan 2022 | E3: Two Month salary amount is hold, monthly bonus is given each month from feb 2022 | F3: March | G3: March | H3: 45742 | I3: 8000
A4: Ajida Samani | B4: Monthly | C4: =SUM('2024'!O4:R4) -> 12545.455 | G4: March | H4: 45742 | I4: 6000
A5: Ansari Yasmeen
A6: Shaikh Tareque
A7: Arshduddin Ansari MohammedMasooduddin
A8: Huzaif Khot
A9: Nagma Khan
A10: Saqlain Supariwala
A11: Rifah Shaikh | B11: Monthly | C11: =SUM('2024'!K28:M28) -> 14236.364 | D11: mach 2024 to may 2024 | E11: Two month salary amount is hold, monthly bonus is each given month from august 2023 | F11: march | G11: March | H11: 45742 | I11: =SUM('2025'!K12) -> 6000
A12: Sana Choudhary | B12: yearly | C12: =SUM('2025'!I13:K13) -> 13685.3 | D12: jan 2025 to March 2025 | E12: paid till 2024 jan to dec | F12: March | G12: Jan2024 to Dec 2024 | H12: 45307 | I12: =SUM('2024'!I13:T13) -> 59272.727
A13: Hamza khot
A14: Naeem Imran
A15: Muzaffar Sayyed | B15: yearly | C15: =SUM('2024'!I17:T17)+SUM('2025'!I16:K16) -> 64884.529 | D15: jan 2024 to March 2025 | E15: No amount is paid till yet | F15: March | H15: - | I15: 0
A16: Alfahad Shaikh | B16: yearly | C16: =SUM('2023'!S9:T9)+SUM('2024'!I5:T5)+SUM('2025'!I17:J17) -> 41533.587 | D16: nov 2023 to March 2025 | E16: No amount is paid till yet | F16: March | G16: - | H16: - | I16: 0
A17: Fahim Shaikh | B17: yearly | C17: =SUM('2025'!K18) -> 6000 | D17: march 2025 to | E17: paid tilll 2025 | F17: March | H17: 45716 | I17: =SUM('2023'!Q23:T23) + SUM('2024'!I19:T19) + SUM('2025'!I18:J18) -> 102590.91
A18: Kashaf Shaikh | C18: =SUM('2024'!P16:T16)+SUM('2025'!I19:K19) -> 29925.926 | D18: Aug 2024 to March 2025 | F18: march | G18: - | H18: - | I18: 0
A19: Abdus Samad Chaudhary | B19: yearly | D19: nov 2023 to March 2025 | E19: No amount is paid till yet | F19: March | H19: - | I19: 0
A20: Imran Ahmed
A21: Shahad Alam Chaudary | C21: =SUM('2024'!I33:T33)+SUM('2025'!I22:K22) -> 73881.423 | D21: jan 2024 to March 2025 | F21: march | G21: - | H21: - | I21: 0
A22: Sufiya kalepad | B22: yearly | C22: =SUM('2024'!I41:T41)+SUM('2025'!I23:K23) -> 55321.661 | D22: Feb 2024 to March 2025 | E22: No amount is paid till yet | F22: March | G22: - | H22: - | I22: 0
A23: Krushna Rauda | B23: yearly | C23: =SUM(0) -> 0 | D23: March 2025 to | E23: paid till 2025 feb | F23: February | H23: 45716 | I23: =SUM('2024'!K25:T25)+SUM('2025'!#REF!) -> #REF!
A24: Pratham | B24: Yearly | C24: =SUM('2024'!K27:T27)+SUM('2025'!I24:K24) -> 62858.175 | D24: March 2024 to March 2025 | E24: Bonus Satart from 2024 | F24: March | H24: - | I24: 0
A25: Shaziya Shaikh
A26: Shirin Muzaffar | B26: Monthly | C26: =SUM('2024'!M38:O38) -> 15136.364 | D26: May 2024 to July 2024 | E26: Two month salary amount is hold, monthly bonus is given each month from August 2024 | F26: March | G26: March | H26: 45742 | I26: =SUM('2025'!K26,'2025'!K27) -> 12000
A27: Yasmeen Shaikh
A28: Imran patel | B28: Monthly | C28: 0 | F28: February | G28: February | H28: 45716 | I28: =SUM('2025'!#REF!) -> #REF!
A29: Mohammad Rehanuddin | B29: Monthly | C29: 0 | E29: Bonus start from 2019 | F29: March | G29: March | H29: 45742 | I29: =SUM('2025'!K29) -> 5000
A30: Saleha khan | B30: yearly | C30: =SUM('2023'!S43:T43)+SUM('2024'!I33:T33)+SUM('2025'!I30:K30) -> 75959.063 | D30: Nov 2023 to march 2025 | E30: Bonus start from 2022 | F30: March | G30: March | H30: 45230 | I30: =SUM('2023'!I43:R43)+SUM('2022'!N63:R63) -> 124268.77
A31: Sohail Inamdar | B31: Monthly | C31: 0 | E31: Bonus Satart from 2024 | F31: March | G31: March | H31: 45742 | I31: =SUM('2025'!K31) -> 5000
A32: Mohammad Faiz | B32: Yearly | C32: =SUM('2024'!I20:T20)+SUM('2025'!I33:K33) -> 22796.532 | D32: Aug 2024 to March 2025 | E32: Bonus Satart from 2024 | F32: March | I32: -
A33: Shaikh Saif | B33: yearly | C33: =SUM('2024'!I34:T34)+SUM('2025'!I33:K33) -> 23059.158 | D33: July 2024 to March 2025 | E33: Bonus Satart from 2024 | F33: March | I33: -
A34: Swati Amode | B34: yearly | C34: =SUM('2023'!T32)+SUM('2024'!I42:T42)+4819+4280+0 -> 64930.357 | D34: Dec 2023 to March 2025 | E34: Bonus Satart from 2022 | F34: March | G34: Jan2023 to nov 2023 | H34: 45204 | I34: =SUM('2023'!I32:S32) -> 43136.364
A35: Abdul Raheem | B35: yearly | C35: =SUM('2024'!I2:T2)+SUM('2025'!I35:K35) -> 22658.684 | D35: Sep 2024 to March 2025 | E35: No amount is paid till yet | F35: March | H35: - | I35: 0
A36: Vishakah | B36: yearly | C36: =SUM('2024'!K39:T39)+SUM('2025'!I36:K36)-1508 -> 33516.845 | D36: march 2024 to march 2025 | E36: No amount is paid till yet | F36: March | H36: - | I36: 0
A37: Maaz Shaokat Choughle
A38: Naheed Khan | B38: yearly | C38: =SUM('2024'!Q25:T25)+SUM('2025'!I38:K38) -> 41602.767 | D38: Sep 2024 to March 2025 | E38: Bonus Satart from 2022 | F38: March | G38: Aug 2023 to Aug 2024 | H38: 45539 | I38: =SUM('2023'!P35:T35)+SUM('2024'!I25:P25) -> 80609
A39: Saniya khanam | B39: yearly | C39: =SUM('2025'!K39) -> 6000 | D39: March 2025 to | E39: Bonus start from 2023 | F39: March | G39: Nov 2023 to Feb 2025 | H39: 45716 | I39: =SUM('2023'!I53:T53)+SUM('2024'!I31:T31)+SUM('2025'!I39:J39) -> 70725.798
A40: Owais Chipa | B40: Monthly | C40: =SUM('2024'!P26:R26)-2455 -> 11999.545 | D40: Aug 2024 to Oct 2024 | E40: Two month salary amount is hold, monthly bonus is given each month from August 2024 | F40: March | G40: March | H40: 45742 | I40: =SUM('2025'!K40) -> 6000
A41: Amir shaikh | B41: Monthly | C41: =SUM('2023'!M54:R54)+2824 -> 24005.818 | D41: May 2023 to Oct 2023 | E41: Two month salary amount is hold, monthly bonus is given each month from May 2023 | F41: March | G41: March | H41: 45742 | I41: =SUM('2025'!K41) -> 5000
A42: Zohra Shaikh | B42: Monthly | C42: 17478 | D42: Jan 2024 to July 2024 | E42: Two month salary amount is hold, monthly bonus given is each month from jan 2024 | I42: 0

Sheet One time bonus sheet march 2025
C1: Bonus | D1: Paid
A2: Aditya Ghule | B2: 1 years, 2 months, 5 days | C2: 6000 | D2: Paid
A3: Sultan raza | B3: 1 years, 2 months, 3 days | C3: 6000 | D3: Paid
A4: Rafiya Shaikh | B4: 1 years, 1 months, 14 days | C4: 6000 | D4: Paid
A5: Shaikh Rehan | B5: 1 years, 2 months, 5 days | C5: 6000 | D5: Paid
A6: Misbah Ansari | B6: 0 years, 6 months, 26 days | C6: 6000 | D6: Paid
A7: Farheen Ansari | B7: 3 years, 2 months, 10 days | C7: 12000 | D7: Paid
A8: Nerli Nazreen | B8: 0 years, 8 months, 7 days | C8: 6000 | D8: Paid
A9: Mohammad Maaz Siddiqui | B9: 0 years, 7 months, 5 days | C9: 6000 | D9: Paid
A10: Iqra Qureshi | B10: 0 years, 6 months, 18 days | C10: 6000 | D10: Paid
A11: Pakeeza Wahid Ali | B11: 0 years, 6 months, 15 days | C11: 6000 | D11: Paid
A12: Sana Ansari | B12: 0 years, 6 months, 15 days | C12: 6000 | D12: Paid
A13: Sharmeen Shaikh | B13: 0 years, 6 months, 11 days | C13: 6000 | D13: Paid
... A17: Faraz Shaikh | B17: 1 years, 4 months, 5 days | C17: 6000 | D17: Paid

Sheet On hold bonus
B1: till september 2022
A2: Name | B2: Total Hold Bonus | C2: Status
A3: Shahid | B3: 62700 | C3: paid
A4: Rehan | B4: 90000 | C4: correct | D4: Till December
A5: Mustaqeem | B5: 56000
A6: Saba | B6: 55435 | C6: paid | D6: Will be paid in October 2023 | F6: Amir Dalvi hold bonus amount
A7: Shamsahd | B7: 49400 | C7: paid
A8: Musharraf | B8: 61000 | C8: paid | F8: Client Bonus | G8: 81000
A9: Shahrukh | B9: 47000 | C9: paid | F9: Total | G9: 1,29,000
A10: Yasmeen | B10: 20000 | C10: correct | F10: Deposit Amount | G10: 55000 | H10: On Hold
A11: Manzar | B11: 42000 | C11: paid | F11: Need to be paid | G11: 74000 | H11: Paid
A12: Shahezad | B12: 25000 | C12: paid
A13: Zeeshan Sayyed | B13: 34000 | C13: paid | D13: 15000 paid him in advance
A14: Asmina | B14: 27000 | C14: paid
A15: Fahmida | B15: 25000 | C15: paid | G15: 96818
A16: Gaus | B16: 34000 | C16: paid
A17: Nabeela | B17: 51500 | C17: paid
A18: Tareq | B18: 54090 | C18: paid
A19: Osama | B19: 37909 | C19: paid
A20: Javed | B20: 29800 | C20: paid
A21: Mohsin | B21: 57478 | C21: paid | G21: 45098
A22: Mohsin new contract 2022 | B22: =62381+50000 -> 112381 | D22: from june 2022 till May 2023 | G22: 56818 | H22: 40000
A23: Sana | B23: 20727 | C23: paid
A24: Warfan | B24: 29000 | C24: paid | D24: Paid
A25: Samee | B25: 24783 | C25: correct | D25: Will be paid when he will leave iqra
A26: Rahmatullah (First Contract) | B26: 32000 | C26: paid
A27: Rahmatullah (Second Contract) | B27: 56591 | C27: Need to paid
A28: Mudassir | B28: 38650 | C28: paid
A29: Salman | B29: 26000 | C29: paid
A30: Nagma | B30: 34000 | C30: correct | D30: Will be paid when she will be left iqra
A31: Noorul hasan | B31: 24000 | C31: paid | D31: paid | O31: Total | P31: paid | Q31: Hold
A32: Shazeena | B32: =36000+31000 -> 67000 | C32: correct | D32: need to be paid | E32: 67000(36000old hold bonus+31000 new)till september month 2022 | N32: 2021 | O32: 71000 | P32: 35000 | Q32: =O32-P32 -> 36000
A33: Maaz | B33: 63454 | C33: paid | N33: 2022 | O33: 57000 | P33: 25500 | Q33: =O33-P33 -> 31500
A34: Swati | B34: 26100 | C34: paid
A35: Muzaffar | B35: 24000 | C35: paid | P35: total Hold | Q35: =SUM(Q32:Q33) -> 67500
A36: Tauseef | B36: 78652 | C36: paid
A37: Neha | B37: 27478 | C37: correct
A38: Arshaduddin | B38: =28500-6000 -> 22500 | C38: paid
A39: Najeeb | B39: 43250 | C39: paid
A40: Irfan | B40: 40909 | C40: paid
A41: Samad | B41: 24000 | C41: paid
A42: Ahtesham | B42: 12000 | C42: correct | D42: need to be paid
A43: Krushna | C43: 1 year bonus
A44: Hajra | B44: 15456 | C44: correct
A45: Batul | B45: 12000 | C45: paid | G45: 108826 | H45: 80000
A46: Rameez | B46: 12000 | C46: correct
A47: Khizer | B47: 12000 | C47: paid
A48: Zeeshan Shaikh | B48: =54826+54000 -> 108826 | C48: correct | D48: 54000client bonus | G48: =G45-H45 -> 28826
A49: Ateef | B49: 61339 | C49: paid
A50: imran ahmed | B50: 24000+42000=66000(teaching bonus) | C50: paid
A51: Saeed | B51: 26500 | C51: correct | E51: =24000+42000 -> 66000
A52: Imran Patel | B52: 24000 | C52: correct
A53: Sohail inamdar | B53: 17391 | C53: 28630 | D53: plz check once
A54: Amir shaikh | B54: 12000 | C54: paid
A55: Yasmeen Shaikh | B55: 12000 | C55: correct
A56: Shariqa | B56: 12000 | C56: correct
A57: Tehmina | B57: 12000 | C57: paid
A58: Arshad Ansari | B58: 103652 | C58: Paid | D58: Till December
A59: Sidra Ansari | B59: 67666 | C59: Paid | D59: Till December
A60: Huzaif Khot | B60: 73000 | C60: Paid | D60: Till December
A61: Tanzeela Shaikh | B61: 12000
A62: Abdul Nausheed | B62: 6000 | C62: paid | E62: 15428.571
A63: Noorullah Khan | B63: 103944 | C63: paid
A64: Arshi Sayyed | B64: 52963 | C64: paid
A65: Mahek Shaikh | B65: 95719
A66: Asbiya | B66: =21091+29800 -> 50891
A67: Humera | B67: ='To beDeleted'!W86 -> 24000 | C67: Need to paid | D67: 92192 already paid till Jan 2023
A68: Afroz | B68: 55000 | C68: paid
A69: Akbar | B69: =35000+33500 -> 68500 | C69: paid
A70: Nazmin | B70: 95045 | C70: paid
A71: Naheed | B71: =40500+50000 -> 90500 | C71: paid
B72: Hold bonus amount paid | E72: =25000-E62 -> 9571.4286
B73: hold bonus amount paid when they left iqra
B74: bonus after 1 yr
A75: Shaziya | B75: 16364 | C75: Hold | D75: Till Sep 2024
A76: Shirin | B76: 15136 | C76: Hold | D76: Till Sep 2024
A77: Owais | B77: 12000 | C77: Hold

Sheet To beDeleted
A1: Sr No | B1: Name of the Employee | C1: Technology | D1: Salary | E1: Bonus amount | F1: Reporting manager | G1: Jan | H1: Feb | I1: JAN | J1: FEB | K1: MAR | L1: APR | M1: MAY | N1: June | O1: July | P1: Oct | Q1: Nov | R1: Dec | S1: This year 2020 | T1: Previous year 2019 total | U1: TOTAL | V1: 2 Months salary | W1: Yearly Permissible Bonus amount | X1: Paid Amount | Y1: To be Paid with Salary in May | Z1: To be Paid with Salary in June | AA1: To be Paid with Salary in July | AB1: To be Paid with Salary in August | AC1: To be Paid with Salary in September | AD1: To be Paid with Salary in October | AE1: To be Paid with Salary in November | AF1: To be Paid with Salary in December | AG1: Total amount | AH1: Remaining Bonus
A2: 1 | B2: Mayur Gore | C2: Salesforce | D2: 15000 | E2: 5000 | H2: Akbar sir | I2: NA | J2: NA | K2: NA | L2: NA | M2: NA | N2: NA | O2: NA | P2: 0 | Q2: 2000 | R2: 3000 | S2: 3500 | T2: 0 | U2: =SUM(I2:T2) -> 8500 | V2: =SUM(J2:U2) -> 17000 | W2: =U2+V2 -> 25500 | X2: =D2*2 -> 30000 | Y2: =X2-W2 -> 4500 | AB2: 0 | AC2: 0 | AE2: =Q2 -> 2000 | AI2: =SUM(AA2:AH2) -> 2000 | AJ2: =Y2+AI2 -> 6500
A3: 2 | B3: Tausif Shaikh | C3: Salesforce | D3: 20000 | E3: 5000 | H3: Akbar sir | I3: NA | J3: NA | K3: NA | L3: NA | M3: NA | N3: NA | O3: NA | P3: NA | Q3: 4000 | R3: 3500 | S3: 0 | T3: 0 | U3: =SUM(I3:T3) -> 7500 | V3: 0 | W3: =U3+V3 -> 7500 | X3: =D3*2 -> 40000 | Y3: =X3-W3 -> 32500 | AB3: 0 | AC3: 0 | AE3: =Q3 -> 4000 | AI3: =SUM(AA3:AH3) -> 4000 | AJ3: =Y3+AI3 -> 36500
A4: 3 | B4: Usaid Syed | C4: E-automate | D4: 6000 | E4: 4000 | H4: Akbar sir | I4: NA | J4: NA | K4: NA | L4: NA | M4: NA | N4: NA | O4: NA | P4: NA | Q4: NA | R4: 2000 | S4: 4000 | T4: 0 | U4: =SUM(I4:T4) -> 6000 | V4: 0 | W4: =U4+V4 -> 6000 | X4: =D4*2 -> 12000 | Y4: =X4-W4 -> 6000 | AB4: 0 | AC4: 0
A5: 4 | B5: Asif Shaikh | C5: Microsoft CRM | D5: 6000 | E5: 6000 | F5: Akbar sir | G5: NA | H5: NA | I5: NA | J5: NA | K5: NA | L5: NA | M5: NA | N5: NA | O5: 3000 | P5: 6000 | Q5: 6000 | R5: 6000 | S5: =SUM(G5:R5) -> 21000 | T5: 0 | U5: =S5+T5 -> 21000 | V5: =D5*2 -> 12000 | W5: =V5-U5 -> -9000 | Z5: 0 | AA5: 0 | AC5: =O5 -> 3000 | AG5: =SUM(Y5:AF5) -> 3000 | AH5: =W5+AG5 -> -6000
A6: 5 | B6: Mohsin inamdar | C6: Uipath | D6: 6000 | E6: 6000 | F6: Akbar sir | G6: NA | H6: NA | I6: NA | J6: NA | K6: NA | L6: NA | M6: NA | N6: NA | O6: NA | P6: 6000 | Q6: 6000 | R6: 6000 | S6: =SUM(G6:R6) -> 18000 | T6: 0 | U6: =S6+T6 -> 18000 | V6: =D6*2 -> 12000 | W6: =V6-U6 -> -6000 | Z6: 0 | AA6: 0
A7: 6 | B7: Shaikh Usama | C7: Salesforce | D7: 6000 | E7: 6000 | F7: Kaniz Fatema | G7: NA | H7: NA | I7: NA | J7: NA | K7: NA | L7: NA | M7: NA | N7: NA | O7: 2000 | P7: 0 | Q7: 0 | R7: 0 | S7: =SUM(G7:R7) -> 2000 | T7: 0 | U7: =S7+T7 -> 2000 | V7: =D7*2 -> 12000 | W7: =V7-U7 -> 10000 | Z7: 0 | AA7: 0 | AC7: =O7 -> 2000
A8: 7 | B8: Murtuza | C8: Uipath | D8: 6000 | E8: 0 | F8: Zahera | G8: NA | H8: NA | I8: NA | J8: NA | K8: NA | L8: NA | M8: =0+2400 -> 2400 | N8: 3000 | O8: 3000 | P8: 3000 | Q8: 0 | R8: 0 | S8: =SUM(G8:R8) -> 11400 | T8: 0 | U8: =S8+T8 -> 11400 | V8: =D8*2 -> 12000 | W8: =V8-U8 -> 600 | Z8: 0 | AA8: 0 | AB8: =O8 -> 3000 | AC8: =O8 -> 3000 | AD8: =P8 -> 3000 | AG8: =SUM(Y8:AF8) -> 9000 | AH8: =W8+AG8 -> 9600
A9: 8 | B9: Tarekh Shaikh | C9: Salesforce | D9: 6000 | E9: 4000 | F9: Akbar sir | O9: 1000 | P9: 0 | Q9: 1500 | R9: 2000 | S9: =SUM(G9:R9) -> 4500 | T9: 0 | U9: =S9+T9 -> 4500
A10: 9 | B10: Shah Alam | C10: Angular | D10: 15000 | E10: 10000 | F10: Akbar sir | H10: 10000 | S10: =SUM(G10:R10) -> 10000
A11: 10 | B11: Zubair Shaikh | C11: E- Commerce | D11: 6000 | E11: 6000 | F11: Akbar sir | G11: 0 | H11: 4000 | S11: =SUM(G11:R11) -> 4000 | T11: ='2020'!AH27 -> -2000 | U11: =S11+T11 -> 2000 | V11: =D11*2 -> 12000 | W11: =T11+V11 -> 10000 | X11: 0 | Y11: =0 -> 0 | AJ11: =SUM(X11:AI11) -> 0 | AK11: =U11-AJ11 -> 2000
A12: 11 | B12: Sohel Shaikh | C12: Microsoft CRM | D12: 6000 | E12: 10000 | F12: Akbar sir | G12: 10000 | H12: 0 | S12: =SUM(G12:R12) -> 10000 | U12: =S12+T12 -> 10000 | V12: 0 | W12: =T12+V12 -> 0 | X12: =G12 -> 10000 | Y12: 0 | AJ12: =SUM(X12:AI12) -> 10000 | AK12: =U12-AJ12 -> 0
A13: 12 | B13: Sohel Ahemad Shaikh | C13: Uipath | D13: 6000 | E13: 6000 | F13: Akbar sir | G13: 6000 | H13: 3000 | I13: 0 | S13: =SUM(G13:R13) -> 9000 | Z13: 0 | AA13: 0
A14: 13 | B14: Kaniz Fatema | C14: Salesforce | D14: 30000 | E14: 5000 | F14: Akbar sir | G14: 5000 | H14: 5000 | I14: 5000 | J14: 5000 | K14: 10000 | S14: =SUM(G14:R14) -> 30000 | T14: ='2020'!AH14 -> 10000 | U14: =S14+T14 -> 40000 | V14: =D14*2 -> 60000 | W14: =T14+V14 -> 70000 | Y14: =G14 -> 5000 | Z14: 5000 | AA14: =I14 -> 5000 | AB14: =J14 -> 5000 | AK14: =SUM(Y14:AJ14) -> 20000 | AL14: =U14-AK14 -> 20000 | AM14: ='2019'!P4 -> 50000 | AN14: ='2020'!S3 -> 57500 | AO14: =S14 -> 30000 | AP14: =AM14+AN14+AO14 -> 137500 | AQ14: =SUM('2020'!K3:R3) -> 37500 | AR14: =SUM(G14:Q14) -> 30000 | AS14: =AQ14+AR14 -> 67500 | AT14: =AP14-AS14 -> 70000
A15: 14 | B15: Mariyam | C15: Salesforce | D15: 20000 | E15: 10000 | F15: Shahid | G15: 8000 | H15: 6000 | I15: 7000 | J15: 7000 | K15: 10000 | S15: =SUM(G15:R15) -> 38000 | T15: ='2020'!AH23 -> -10500 | U15: =S15+T15 -> 27500 | V15: =D15*2 -> 40000 | W15: =T15+V15 -> 29500 | Y15: =0 -> 0 | Z15: =H15 -> 6000 | AA15: =I15 -> 7000 | AB15: =J15 -> 7000 | AK15: =SUM(Y15:AJ15) -> 20000 | AL15: =U15-AK15 -> 7500 | AM15: ='2019'!P2 -> 42500 | AN15: ='2020'!S2 -> 49000 | AO15: =S15 -> 38000 | AP15: =AM15+AN15+AO15 -> 129500 | AQ15: =SUM('2020'!K2:R2) -> 30500 | AR15: =SUM(G15:R15) -> 38000 | AS15: =AQ15+AR15 -> 68500 | AT15: =AP15-AS15 -> 61000
A16: 15 | B16: 4500 | C16: Paid
A17: 16 | B17: 21000 | C17: Paid
A18: 17 | B18: Adil Khan | C18: Salesforce | D18: 12000 | E18: 4000 | F18: Rehan | G18: 2000 | H18: 0 | I18: 2000 | J18: 0 | K18: He is not an employee he is taking dev training we have moved back him on stipend | S18: =SUM(G18:R18) -> 4000 | T18: 0 | U18: =S18+T18 -> 4000 | V18: =D18*2 -> 24000 | W18: =T18+V18 -> 24000 | Y18: 0 | Z18: 0 | AA18: 0 | AB18: 0 | AK18: =SUM(Y18:AJ18) -> 0 | AL18: =U18-AK18 -> 4000
A19: 18 | B19: Muqtadir Khan | C19: Qliksense | D19: 6000 | E19: 6000 | F19: Akbar sir | G19: 6000 | H19: 6000 | I19: 6000 | J19: 0 | K19: 0 | L19: 0 | S19: =SUM(G19:R19) -> 18000 | T19: ='2020'!AH2 -> 21000 | U19: =S19+T19 -> 39000 | V19: =D19*2 -> 12000 | W19: =T19+V19 -> 33000 | Y19: =G19 -> 6000 | Z19: =H19 -> 6000 | AB19: =I19 -> 6000 | AC19: 0 | AD19: 0 | AK19: =SUM(Y19:AJ19) -> 18000 | AL19: =U19-AK19 -> 21000
A20: 19 | B20: Nagma Khan | C20: OIC | D20: 17000 | E20: 10000 | F20: Akbar sir | G20: 10000 | H20: 10000 | I20: 4000 | J20: 0 | K20: 0 | S20: =SUM(G20:R20) -> 24000 | T20: ='2020'!AH10 -> -6000 | U20: =S20+T20 -> 18000 | V20: =D20*2 -> 34000 | W20: =T20+V20 -> 28000 | Y20: =G20 -> 10000 | Z20: =H20 -> 10000 | AA20: =I20 -> 4000 | AB20: =J20 -> 0 | AC20: 0 | AD20: 0 | AK20: =SUM(Y20:AJ20) -> 24000 | AL20: =U20-AK20 -> -6000
A21: 20 | B21: Taleb | C21: Qliksense | D21: 6000 | E21: 6000 | F21: Akbar sir | G21: NA | H21: NA | I21: 6000 | J21: 6000 | K21: 5000 | L21: 6000 | M21: 6000 | S21: =SUM(G21:R21) -> 29000 | U21: =S21+T21 -> 29000 | V21: =D21*2 -> 12000 | W21: =T21+V21 -> 12000 | Y21: =G21 -> NA | Z21: 0 | AA21: 0 | AB21: 0 | AC21: =K21 -> 5000 | AD21: =L21 -> 6000 | AE21: =M21 -> 6000 | AK21: =SUM(Y21:AJ21) -> 17000 | AL21: =U21-AK21 -> 12000
A22: 21 | B22: Kamala | C22: Salesforce | D22: 12000 | E22: 4000 | F22: Shahid | G22: NA | H22: NA | I22: NA | J22: NA | K22: NA | L22: NA | M22: 3000 | V22: =D22*2 -> 24000
A23: 22 | B23: Muntajeeb | C23: Salesforce | D23: 12000 | E23: 4000 | F23: Rehan | G23: NA | H23: NA | I23: 4000 | J23: 3000 | K23: 4000 | L23: 4000 | M23: 3000 | N23: 4000 | O23: =E23/23*0 -> 0 | P23: Whole month absent | V23: 24000 | AA23: 0 | AB23: 0 | AD23: 0 | AE23: 0 | AF23: 0 | AG23: 0
A24: 23 | B24: Madiha pathan | C24: Salesforce | D24: 12000 | E24: 4000 | F24: Rehan | G24: NA | H24: NA | I24: NA | J24: NA | K24: NA | L24: NA | M24: 3000 | N24: 3000 | O24: 4000 | P24: 0 | V24: 24000 | AF24: 0 | AG24: 0 | AH24: 0
A25: 24 | B25: Mehlaqa Khna | C25: Salesforce | D25: 12000 | E25: 4000 | F25: Rehan | G25: NA | H25: NA | I25: NA | J25: NA | K25: NA | L25: NA | M25: 3000 | N25: 3000 | O25: 4000 | P25: 4000 | V25: 24000 | AF25: 0 | AG25: 0 | AH25: 0
A26: 25 | B26: Mustakim | C26: Eienstein | D26: 25000 | E26: 5000 | F26: Rehan | G26: NA | H26: NA | I26: 4000 | J26: 4000 | K26: 4000 | L26: 5000 | M26: 5000 | N26: 5000 | O26: 5000 | P26: =E26/20*0 -> 0 | V26: 50000 | AA26: 0 | AB26: 0 | AD26: 0 | AE26: 0 | AF26: 0 | AG26: 0 | AH26: 0 | AK26: 0 | AL26: 0 | AM26: 0 | AN26: 0 | AO26: 0 | AP26: 0 | AS26: 0 | AT26: 0
A27: 26 | B27: Yusuf | C27: Uipath | D27: 6000 | E27: 11250 | F27: Akbar sir | G27: NA | H27: NA | I27: NA | J27: NA | K27: NA | L27: NA | M27: NA | N27: 9062 | O27: 11250 | P27: 0 | AF27: 9062 | AG27: =O27 -> 11250 | AH27: =P27 -> 0
A28: 27 | B28: Sayyed Manzar Ali | C28: Uipath | D28: 25000 | E28: 10000 | F28: Akbar sir | G28: 10000 | H28: 10000 | I28: 10000 | J28: 10000 | K28: 10000 | L28: 10000 | M28: 10000 | N28: 10000 | O28: 10000 | P28: 10000 | S28: 90000 | T28: 0 | U28: 90000 | V28: 50000 | Y28: 10000 | Z28: 10000 | AA28: 10000 | AB28: 10000 | AC28: 10000 | AD28: 10000 | AE28: 10000 | AF28: 10000 | AG28: =O28 -> 10000 | AH28: =P28 -> 10000
A29: 28 | B29: Musharrafuddin Siddiqui | C29: Dot Net | D29: 25000 | E29: 10000 | F29: Akbar sir | G29: 5000 | H29: 10000 | I29: 10000 | J29: 10000 | K29: 10000 | L29: 10000 | M29: 10000 | N29: 10000 | O29: 10000 | P29: 10000 | S29: 85000 | T29: 0 | V29: 50000 | W29: 50000 | Y29: 5000 | Z29: 10000 | AA29: 10000 | AB29: 10000 | AC29: 10000 | AD29: 10000 | AE29: 10000 | AF29: 10000 | AG29: =O29 -> 10000 | AH29: =P29 -> 10000 | AK29: 75000 | AL29: -75000
A30: 29 | B30: Faizan | C30: Salesforce | D30: 25000 | E30: 10000 | F30: Akbar sir | G30: 2500 | H30: 4000 | I30: 4000 | J30: 10000 | K30: 10000 | L30: 10000 | M30: 10000 | N30: 10000 | O30: 10000 | S30: 70500 | T30: 0 | U30: 70500 | V30: 50000 | W30: 50000 | Z30: 0 | AA30: 0 | AB30: 0 | AC30: 0 | AD30: 0 | AF30: 10000 | AG30: =O30 -> 10000 | AH30: 0
A31: 30 | B31: Shahrukh Siddiqui | C31: Financial Force | D31: 20000 | E31: 25000 | F31: Akbar sir | G31: 8000 | H31: 7000 | I31: 7000 | J31: 7000 | K31: 10000 | L31: 25000 | M31: 25000 | N31: 20000 | O31: =45000-'[4]Sep 21'!$H$80 -> 45000 | P31: 25000 | S31: 154000 | T31: 0 | U31: 154000 | V31: 40000 | W31: 40000 | Y31: 8000 | Z31: 7000 | AA31: 7000 | AB31: 7000 | AC31: =K31 -> 10000 | AD31: 15000 | AE31: 25000 | AF31: 20000 | AG31: =O31 -> 45000 | AH31: =P31 -> 25000 | AK31: 81000 | AL31: 73000
A32: 31 | B32: Danish | C32: Uipath | D32: 6000 | E32: 11250 | F32: Akbar sir | G32: NA | H32: NA | I32: NA | J32: NA | K32: NA | L32: NA | M32: NA | N32: 11000 | O32: 11250 | P32: 11250 | AF32: 11000 | AG32: =O32 -> 11250 | AH32: =P32 -> 11250
A33: 32 | B33: Murtuza | C33: wordpresss | D33: 6000 | E33: 4000 | F33: Akbar sir | G33: NA | H33: 4000 | I33: 4000 | J33: 4000 | K33: 4000 | L33: 4000 | M33: 4000 | N33: 4000 | O33: 4000 | P33: =E33/25*11 -> 1760 | S33: 32000 | U33: 32000 | V33: 12000 | W33: 12000 | Y33: NA | Z33: 4000 | AA33: 4000 | AB33: 4000 | AC33: 4000 | AD33: 4000 | AE33: 4000 | AF33: 4000 | AG33: =O33 -> 4000 | AH33: =P33 -> 1760
A34: 33 | B34: Shahid Qadri | C34: Salesforce | D34: 30000 | E34: 10000 | F34: Akbar sir | G34: 10000 | H34: 8000 | I34: 10000 | J34: 10000 | K34: 10000 | L34: 10000 | M34: 10000 | N34: 10000 | S34: =SUM(G34:R34) -> 78000 | T34: ='[5]2020'!U26 -> #REF! | U34: =S34+T34 -> #REF! | V34: =D34*2 -> 60000 | W34: =T34+V34 -> #REF! | Y34: 0 | Z34: =H34 -> 8000 | AA34: =I34 -> 10000 | AB34: =J34 -> 10000 | AC34: 0 | AD34: 0 | AE34: =M34 -> 10000 | AF34: =N34 -> 10000 | AK34: =SUM(Y34:AJ34) -> 48000 | AL34: =U34-AK34 -> #REF!
A35: 34 | B35: Sayyed Haider | C35: SharePoint | D35: 10000 | E35: 20000 | F35: Akbar sir | G35: 10000 | H35: 2000 | I35: 8000 | J35: 10000 | K35: 10000 | L35: 20000 | M35: 10000 | N35: 11000 | O35: 10000 | P35: 5000 | Q35: 5000 | S35: 86000 | T35: 0 | U35: 86000 | V35: 20000 | W35: 20000 | Y35: 0 | Z35: 2000 | AA35: 8000 | AB35: 10000 | AC35: 10000 | AD35: 20000 | AF35: 11000 | AG35: =O35 -> 10000 | AH35: =P35 -> 5000 | AI35: =Q35 -> 5000
A36: 35 | B36: Wasif | C36: SharePoint | D36: 6000 | E36: 6000 | F36: Akbar sir | G36: NA | H36: 6000 | I36: 4000 | J36: 5000 | K36: 5000 | L36: 6000 | M36: 6000 | N36: 6000 | O36: 6000 | P36: 6000 | Q36: 6000 | S36: 44000 | U36: 44000 | V36: 12000 | Z36: 0 | AA36: 0 | AB36: 0 | AC36: 5000 | AD36: 6000 | AE36: 6000 | AF36: 6000 | AG36: =O36 -> 6000 | AH36: =P36 -> 6000 | AI36: =Q36 -> 6000
A37: 36 | B37: Intekhab Alam | C37: Salesforce | D37: 12000 | E37: 4000 | F37: Shahid | G37: NA | H37: NA | I37: NA | J37: NA | K37: NA | L37: NA | M37: NA | N37: NA | O37: 4000 | P37: 4000 | Q37: 4000 | AG37: 0 | AH37: 0
A38: 37 | B38: Zafar | C38: Salesforce-Conga | D38: 12000 | E38: 4000 | F38: Akbar sir | S38: =SUM(G38:R38) -> 0 | T38: =D38*2 -> 24000 | W38: 0
A39: 38 | B39: Mustaqeem Shaikh | C39: Salesforce admin | D39: 25000 | E39: 10000 | F39: Akbar sir | G39: 10000 | S39: =SUM(G39:R39) -> 10000 | T39: =D39*2 -> 50000 | W39: 0
A40: 39 | B40: Muzafar Khan | C40: Salesforce admin | D40: 12000 | E40: 4000 | F40: Shahid | G40: 0 | S40: =SUM(G40:R40) -> 0 | T40: =D40*2 -> 24000 | W40: 0
A41: 40 | B41: Amaan | C41: Financial Force-PSA | D41: 12000 | E41: 4000 | F41: Akbar sir | G41: =E41/22*16 -> 2909.0909 | H41: 0 | S41: =SUM(G41:R41) -> 2909.0909 | T41: =D41*2 -> 24000 | W41: 0 | X41: 0
A42: 41 | B42: Nabeela khan | C42: Microsoft CRM | D42: 40000 | E42: 10000 | F42: Akbar sir | G42: 10000 | H42: 10000 | I42: 10000 | S42: =SUM(G42:R42) -> 30000 | T42: =D42*2 -> 80000 | W42: =G42 -> 10000 | X42: =H42 -> 10000 | Y42: =I42 -> 10000
A43: 42 | B43: Shamshad Ahmed | C43: Qlik Sense | D43: 22000 | E43: 8000 | F43: Akbar sir | G43: 8000 | H43: 8000 | I43: =E43/20*11 -> 4400 | J43: last date 11 march | S43: =SUM(G43:R43) -> 20400 | T43: =D43*2 -> 44000 | W43: =G43 -> 8000 | X43: =H43 -> 8000 | Y43: 0
A44: 43 | B44: Shahezad Shaikh Sajid | C44: Salesforce Technical | D44: 12000 | E44: 4000 | F44: Akbar sir | G44: 4000 | H44: 4000 | I44: 2000 | S44: =SUM(G44:R44) -> 10000 | T44: =D44*2 -> 24000 | W44: =G44 -> 4000 | X44: =H44 -> 4000 | Y44: 0
A45: 44 | B45: Mohammad Muzaffaruddin Mumtazuddin | C45: Wordpress/PHP | D45: 12000 | E45: 6000 | F45: Akbar sir | G45: 6000 | H45: 6000 | I45: 6000 | S45: =SUM(G45:R45) -> 18000 | T45: =D45*2 -> 24000 | W45: =G45 -> 6000 | X45: =H45 -> 6000 | Y45: =I45 -> 6000
A46: 45 | B46: Priya Sharma | C46: Salesforce Technical | D46: 12000 | E46: 4000 | F46: Shahid | G46: 4000 | H46: 2500 | I46: 2000 | S46: =SUM(G46:R46) -> 8500 | T46: =D46*2 -> 24000 | W46: 0 | X46: 0 | Y46: 0
A47: 46 | B47: Abdul Ahad | C47: Angular | D47: 10000 | E47: 6000 | F47: Akbar sir | G47: 0 | H47: 2000 | I47: 2000 | S47: =SUM(G47:R47) -> 4000 | T47: =D47*2 -> 20000 | W47: 0 | X47: 0 | Y47: 0
A48: 47 | B48: Imran Khan | C48: Salesforce admin | D48: 6000 | E48: 10000 | F48: Akbar sir | G48: NA | H48: NA | I48: NA | J48: =E48/21*6 -> 2857.1429 | K48: 10000 | W48: 0 | X48: 0 | Y48: 0 | Z48: 0 | AA48: 0
A49: 48 | B49: Arzoo | C49: Financial Force-PSA | D49: 12000 | E49: 4000 | F49: Akbar sir | G49: 4000 | H49: 2000 | I49: 0 | J49: 2000 | K49: 4000 | L49: 2000 | M49: 0 | N49: 4 days annaual leave | S49: =SUM(G49:R49) -> 14000 | T49: =D49*2 -> 24000 | W49: 0 | X49: 0 | Y49: 0 | Z49: 0 | AA49: 0 | AB49: 0
A50: 49 | B50: Mustafa Shaikh | C50: SharePoint | D50: 10000 | E50: 6000 | F50: saba | G50: NA | H50: NA | I50: NA | J50: NA | K50: NA | L50: 6000 | AC50: 0
A51: 50 | B51: Sayed Najeeb | C51: Financial Force-PSA | D51: 20000 | E51: 5000 | F51: Akbar sir | G51: 5000 | H51: 5000 | I51: 0 | J51: 2500 | K51: 2500 | L51: 2500 | M51: 5000 | S51: =SUM(G51:R51) -> 22500 | T51: =D51*2 -> 40000 | W51: 0 | X51: 0 | Y51: 0 | Z51: =J51 -> 2500 | AA51: =K51 -> 2500 | AB51: =L51 -> 2500 | AC51: 5000 | AD51: a
A52: 51 | B52: Khan shaista sohail ahmed | C52: Salesforce admin | D52: 6000 | E52: 10000 | F52: Shahid | G52: NA | H52: NA | I52: 8000 | J52: 10000 | K52: 10000 | L52: 10000 | M52: =E52/20*5 -> 2500 | W52: 0 | X52: 0 | Y52: 0 | Z52: 0 | AA52: 0 | AB52: 0 | AC52: 0
A53: 52 | B53: Mohammad Salman | C53: SharePoint | D53: 12000 | E53: 6000 | G53: Akbar sir | H53: 6000 | I53: 6000 | J53: 6000 | K53: =J53 -> 6000 | L53: =K53 -> 6000 | M53: 6000 | N53: 6000 | O53: 6000 | P53: 6000 | T53: =SUM(H53:S53) -> 54000 | U53: =D53*2 -> 24000 | X53: =H53 -> 6000 | Y53: =I53 -> 6000 | Z53: =J53 -> 6000 | AA53: =K53 -> 6000 | AB53: =L53 -> 6000 | AC53: =M53 -> 6000 | AD53: =N53-3500 -> 2500 | AE53: =O53 -> 6000 | AF53: =P53 -> 6000 | AG53: a
A54: 53 | B54: Aamir Dalvi | C54: Financial Force-PSA | D54: 55000 | E54: 0 | F54: 55000 | G54: Akbar sir | H54: 4000 | I54: 4000 | J54: 4000 | K54: =J54 -> 4000 | L54: =K54 -> 4000 | M54: 4000 | N54: 4000 | O54: 4000 | P54: 1818 | T54: =SUM(H54:S54) -> 33818 | U54: =D54*2 -> 110000 | X54: 0 | Y54: 0 | Z54: 0 | AA54: 0 | AB54: 0 | AC54: 0 | AD54: 0 | AE54: 0 | AF54: =P54 -> 1818 | AG54: a
A55: 54 | B55: Imran Ahmed | C55: Teaching Bonus | D55: 25000 | E55: 5000 | F55: 6000 | G55: Akbar sir | H55: NA | I55: 6000 | J55: 6000 | K55: =J55 -> 6000 | L55: =K55 -> 6000 | M55: 6000 | N55: 6000 | O55: 0 | P55: 6000 | T55: After 1 year | AD55: 0 | AE55: 0 | AF55: 0
A56: 55 | B56: Shaikh Irfan | C56: Microsoft CRM | D56: 40000 | E56: 0 | F56: 0 | G56: Akbar sir | H56: 5000 | I56: 5000 | J56: 5000 | K56: =J56 -> 5000 | L56: =K56 -> 5000 | M56: 5000 | N56: 5000 | O56: 5000 | P56: 5000 | Q56: =5000/21*10 -> 2380.9524 | T56: =SUM(H56:S56) -> 47380.952 | U56: =D56*2 -> 80000 | X56: 0 | Y56: 0 | Z56: =J56 -> 5000 | AA56: =K56 -> 5000 | AB56: =L56 -> 5000 | AC56: 0 | AD56: 5000 | AE56: =O56 -> 5000 | AF56: 1045 | AG56: =Q56 -> 2380.9524 | AH56: a
A57: 56 | B57: Batul Kazi | C57: Sales | D57: 6000 | E57: 6000 | F57: ='2021'!R53+'To beDeleted'!H57 -> 12000 | G57: Akbar sir | H57: 6000 | I57: 6000 | J57: =E57/20*11 -> 3300 | K57: 6000 | L57: 6000 | M57: 3000 | N57: 4000 | O57: =E57/23*18 -> 4695.6522 | P57: 6000 | Q57: =6000/21*8 -> 2285.7143 | R57: her last date was 7 oct | T57: =SUM(H57:S57) -> 47281.366 | U57: =D57*2 -> 12000 | X57: 0 | Y57: =I57 -> 6000 | Z57: =J57 -> 3300 | AA57: =K57 -> 6000 | AB57: =L57 -> 6000 | AC57: =M57 -> 3000 | AD57: 4000 | AE57: =O57 -> 4695.6522 | AF57: =P57 -> 6000 | AG57: =Q57 -> 2285.7143 | AH57: a
A58: 57 | B58: Salesforce Technical | C58: 12000 | D58: 4000 | E58: 9000 | F58: 0 | G58: 0 | H58: 9000 | I58: 0 | S58: =SUM(F58:R58) -> 9000
A59: 58 | B59: Samad Shaikh | C59: Microsoft CRM | D59: 12000 | E59: 4000 | G59: Akbar sir | H59: 4000 | I59: 4000 | J59: 4000 | K59: =J59 -> 4000 | L59: 4000 | M59: 4000 | N59: =E59/20*5 -> 1000 | O59: 4000 | P59: 4000 | Q59: 4000 | T59: =SUM(H59:S59) -> 37000 | U59: =D59*2 -> 24000 | V59: ='2021'!S50+'To beDeleted'!H59+'To beDeleted'!I59+'To beDeleted'!J59+'To beDeleted'!K59 -> 24000 | W59: 0 | Y59: 0 | Z59: 0 | AA59: 0 | AB59: 0 | AC59: =L59 -> 4000 | AD59: =M59 -> 4000 | AE59: 1000 | AF59: =O59 -> 4000 | AG59: =P59 -> 4000 | AH59: =Q59 -> 4000 | AI59: a
A60: 59 | B60: Shaikh Ibrahim | C60: Sales | D60: 18000 | E60: 7000 | F60: Akbar sir | G60: 7000 | H60: 7000 | I60: 7000 | J60: =I60 -> 7000 | K60: 7000 | L60: =E60/23*15 -> 4565.2174 | M60: 7000 | N60: 7000 | O60: 7000 | P60: 7000 | S60: =SUM(G60:R60) -> 67565.217 | T60: =D60*2 -> 36000 | U60: 0 | V60: =S60 -> 67565.217 | W60: =G60 -> 7000 | X60: =H60 -> 7000 | Y60: =I60 -> 7000 | Z60: =J60 -> 7000 | AA60: =K60 -> 7000 | AB60: =L60 -> 4565.2174 | AC60: 7000 | AD60: =N60 -> 7000 | AE60: =O60 -> 7000 | AF60: =P60 -> 7000 | AI60: =SUM(W60:AH60) -> 67565.217
A61: 60 | B61: Neha Shaikh | C61: Microsoft CRM | D61: 12000 | E61: 4000 | F61: Akbar sir | G61: 4000 | H61: 4000 | I61: 4000 | J61: =E61/21*16 -> 3047.619 | K61: 4000 | L61: =E61/23*15 -> 2608.6957 | M61: 4000 | N61: 4000 | O61: =E61/22*14 -> 2545.4545 | P61: 2000 | Q61: 4000 | S61: =SUM(G61:R61) -> 38201.769 | T61: =D61*2 -> 24000 | U61: ='2021'!AL21+'To beDeleted'!G61+'To beDeleted'!H61+'To beDeleted'!I61 -> 27478.261 | V61: 0 | W61: 0 | X61: 0 | Y61: 0 | Z61: =J61 -> 3047.619 | AA61: =K61 -> 4000 | AB61: =L61 -> 2608.6957 | AC61: 4000 | AD61: =N61 -> 4000 | AE61: =O61 -> 2545.4545 | AF61: =P61 -> 2000 | AG61: =Q61 -> 4000 | AH61: a | AI61: =SUM(W61:AH61) -> 26201.769
A62: 61 | B62: Shaikh Afshan Jabeen | C62: Microsoft CRM | D62: 10000 | E62: 6000 | F62: Akbar sir | G62: NA | H62: NA | I62: NA | J62: NA | K62: NA | L62: NA | M62: NA | N62: NA | O62: NA | P62: NA | Q62: 0 | S62: =SUM(G62:R62) -> 0 | T62: =D62*2 -> 20000 | U62: =SUM(R62) -> 0 | V62: 0 | AE62: 0 | AF62: 0 | AG62: 0 | AI62: =SUM(W62:AH62) -> 0
A63: 62 | B63: Shaikh Khizer | C63: Uipath | D63: 6000 | E63: 6000 | F63: Akbar sir | G63: 6000 | H63: 6000 | I63: 6000 | J63: =I63 -> 6000 | K63: 6000 | L63: 6000 | M63: 3000 | N63: 5000 | O63: =E63-200 -> 5800 | P63: 0 | Q63: =6000/23*14 -> 3652.1739 | R63: His Last date is 15 Nov | S63: =SUM(G63:R63) -> 53452.174 | T63: =D63*2 -> 12000 | U63: ='2021'!AL37 -> 12062 | V63: 0 | W63: =G63 -> 6000 | X63: =H63 -> 6000 | Y63: =I63 -> 6000 | Z63: =J63 -> 6000 | AA63: =K63 -> 6000 | AB63: =L63 -> 6000 | AC63: =M63 -> 3000 | AD63: =N63 -> 5000 | AE63: =O63 -> 5800 | AF63: 0 | AG63: =Q63 -> 3652.1739 | AH63: a | AI63: =SUM(W63:AH63) -> 53452.174
A64: 63 | B64: Amir Shaikh | C64: Wordpress/PHP | D64: 6000 | E64: 6000 | F64: Akbar sir | G64: 6000 | H64: 6000 | I64: 6000 | J64: =I64 -> 6000 | K64: 6000 | L64: 3000 | M64: 6000 | N64: =E64/23*12 -> 3130.4348 | O64: 6000 | P64: 6000 | Q64: =6000/23*5 -> 1304.3478 | R64: Last date was 31st Oct | S64: =SUM(G64:R64) -> 55434.783 | T64: =D64*2 -> 12000 | U64: ='2021'!AL40 -> 12000 | V64: 0 | W64: =G64 -> 6000 | X64: =H64 -> 6000 | Y64: =I64 -> 6000 | Z64: =J64 -> 6000 | AA64: =K64 -> 6000 | AB64: =L64 -> 3000 | AC64: =M64 -> 6000 | AD64: =N64 -> 3130.4348 | ... AG64: =Q64 -> 1304.3478 | AH64: a | AI64: =SUM(W64:AH64) -> 55434.783
A65: 64 | B65: Zeeshan Sayyed | C65: Salesforce Technical | D65: 15000 | E65: 10000 | F65: Shahid | G65: 10000 | H65: =E65/23*20 -> 8695.6522 | I65: 8000 | J65: 0 | K65: 0 | L65: =E65/23*7 -> 3043.4783 | M65: =E65/20*16 -> 8000 | N65: 7000 | O65: 10000 | P65: 10000 | Q65: =10000/23*5 -> 2173.913 | R65: His Last date is 31st Oct | S65: =SUM(G65:R65) -> 66913.043 | T65: =D65*2 -> 30000 | U65: ='2020'!AH5+'2021'!AL44-15000 -> 19000 | V65: 0 | W65: =G65 -> 10000 | X65: =H65 -> 8695.6522 | Y65: =I65 -> 8000 | Z65: 0 | AA65: =K65 -> 0 | AB65: =L65 -> 3043.4783 | AC65: =M65 -> 8000 | AD65: =N65 -> 7000 | AE65: =O65 -> 10000 | AF65: =P65 -> 10000 | AG65: =Q65 -> 2173.913 | AH65: a | AI65: =SUM(W65:AH65) -> 66913.043
A66: 65 | B66: Tehmina Hamduley | C66: Sales | D66: 6000 | E66: 6000 | F66: Akbar Sir | G66: 3000 | H66: 3000 | S66: =SUM(G66:R66) -> 6000 | T66: =D66*2 -> 12000 | U66: ='2022'!U23 -> 16500 | V66: =G66 -> 3000 | W66: =H66 -> 3000 | Y66: =J66 -> 0 | Z66: =K66 -> 0 | AA66: =L66 -> 0 | AB66: =M66 -> 0 | AC66: =N66 -> 0 | AD66: =O66 -> 0 | AE66: =P66 -> 0 | AF66: =Q66 -> 0 | AG66: =R66 -> 0 | AI66: =SUM(V66:AG66) -> 6000 | AJ66: =S66-V66-W66-X66-Y66-Z66-AA66-AB66-AC66-AD66-AE66-AF66-AG66 -> 0 | AN66: =AK66+AL66+AM66 -> 0
A67: 66 | B67: Saeed Shaikh | C67: Financial Force-PSA | D67: 12000 | E67: 4000 | F67: Akbar Sir | G67: 0 | H67: 0 | I67: 0 | S67: =SUM(G67:R67) -> 0 | T67: =D67*2 -> 24000 | U67: ='2022'!U50 -> 26500 | V67: =G67 -> 0 | X67: =I67 -> 0 | Y67: =J67 -> 0 | Z67: =K67 -> 0 | AA67: =L67 -> 0 | AB67: =M67 -> 0 | AC67: =N67 -> 0 | AD67: =O67 -> 0 | AE67: =P67 -> 0 | ... AG67: =R67 -> 0 | AI67: =SUM(V67:AG67) -> 0 | AJ67: =S67-V67-W67-X67-Y67-Z67-AA67-AB67-AC67-AD67-AE67-AF67-AG67 -> 0 | AN67: =AK67+AL67+AM67 -> 0
A68: 67 | B68: Sohail Inamdar | C68: Salesforce admin | D68: 30000 | E68: 5000 | F68: Shahid Qadri | G68: 5000 | H68: 5000 | I68: 5000 | S68: =SUM(G68:R68) -> 15000 | U68: ='2022'!U60 -> 28630.435 | X68: =I68 -> 5000 | Y68: =J68 -> 0 | Z68: =K68 -> 0 | AA68: =L68 -> 0 | AB68: =M68 -> 0 | AC68: =N68 -> 0 | AD68: =O68 -> 0 | AE68: =P68 -> 0 | ... AG68: =R68 -> 0 | AI68: =SUM(V68:AG68) -> 5000 | AJ68: =S68-X68-Y68-Z68-AA68 -> 10000 | AK68: ='2022'!AK41 -> 38000 | AL68: ='2022'!AL41 -> 24000 | AN68: =AK68+AL68+AM68 -> 62000
A69: 68 | B69: Rameez Sufiyan | C69: Uipath | D69: 20000 | E69: 5000 | F69: Akbar Sir | G69: 2000 | H69: =E69/23*13 -> 2826.087 | I69: 5000 | S69: =SUM(G69:R69) -> 9826.087 | U69: - | V69: =G69 -> 2000 | W69: =H69 -> 2826.087 | X69: =I69 -> 5000 | Y69: =J69 -> 0 | Z69: =K69 -> 0 | AA69: =L69 -> 0 | AB69: =M69 -> 0 | AC69: =N69 -> 0 | ... AG69: =R69 -> 0 | AI69: =SUM(V69:AG69) -> 9826.087 | AJ69: =S69-V69-W69-X69-Y69-Z69-AA69-AB69-AC69-AD69-AE69-AF69-AG69 -> 9.094947e-13 | AN69: =AK69+AL69+AM69 -> 0
A70: 69 | B70: Huzaif Khan | C70: Salesforce admin | D70: 6000 | E70: 10000 | F70: Shahid Qadri | G70: 9000 | H70: 9000 | I70: 0 | J70: Employment End date 20 March 2023 (16 present days) | S70: =SUM(G70:R70) -> 18000 | U70: ='2022'!U55 -> 60857.143 | Y70: =J70 -> Employment End date 20 March 2023 (16 present days) | Z70: =K70 -> 0 | AA70: =L70 -> 0 | AB70: =M70 -> 0 | AC70: =N70 -> 0 | AD70: =O70 -> 0 | AE70: =P70 -> 0 | AF70: =Q70 -> 0 | AG70: =R70 -> 0 | AI70: =SUM(V70:AG70) -> 0 | AJ70: =S70-V70-W70-X70-Y70-Z70-AA70-AB70-AC70-AD70-AE70-AF70-AG70 -> #VALUE! | AN70: =AK70+AL70+AM70 -> 0
A71: 70
A72: 71 | B72: Rijvana Shaikh | C72: Salesforce admin | D72: 6000 | E72: 10000 | F72: Shahid Qadri | G72: 9000 | H72: 10000 | I72: 0 | J72: 0 | K72: 0 | L72: 0 | M72: 0 | N72: 0 | O72: 0 | P72: 0 | Q72: 0 | R72: 0 | S72: =SUM(G72:R72) -> 19000 | U72: =SUM(H72:R72) -> 10000 | W72: 10000 | X72: =I72 -> 0 | Y72: =J72 -> 0 | Z72: =K72 -> 0 | AA72: =L72 -> 0 | AB72: =M72 -> 0 | AC72: =N72 -> 0 | AD72: =O72 -> 0 | AE72: =P72 -> 0 | ... AG72: =R72 -> 0 | AI72: =SUM(V72:AG72) -> 10000 | AJ72: =S72-V72-W72-X72-Y72-Z72-AA72-AB72-AC72-AD72-AE72-AF72-AG72 -> 9000 | AN72: =AK72+AL72+AM72 -> 0
A73: 73 | B73: Abdul Nausheed | C73: SharePoint | D73: 6000 | E73: 6000 | F73: Akbar Sir | G73: NA | H73: NA | I73: 3000 | J73: 3000 | T73: =D73*2 -> 12000 | X73: 0
A74: 74 | B74: Ahtesham Mohammed | C74: Qlik Sense | D74: 30000 | E74: 10000 | F74: 44706 | G74: 45071 | H74: Akbar Sir | I74: 0 | J74: 0 | K74: 0 | L74: 0 | M74: 0 | U74: =SUM(I74:T74) -> 0 | W74: ='On hold bonus'!B42 -> 12000 | AA74: =L74 -> 0 | AC74: =N74 -> 0 | AD74: =O74 -> 0 | AE74: =P74 -> 0 | AF74: =Q74 -> 0 | AG74: =R74 -> 0 | AH74: =S74 -> 0 | AI74: =T74 -> 0 | AK74: =SUM(X74:AI74) -> 0 | AL74: =U74-X74-Y74-Z74-AA74-AB74-AC74-AD74-AE74-AF74-AG74-AH74-AI74 -> 0 | AP74: =AM74+AN74+AO74 -> 0
A75: 75 | B75: Tauseef Khan | C75: Qlik Sense | D75: 30000 | E75: 10000 | F75: 44652 | G75: 45017 | H75: Akbar Sir | I75: 0 | J75: 0 | K75: 0 | L75: 0 | M75: 0 | U75: =SUM(I75:T75) -> 0 | W75: ='2022'!U14 -> 78652.174 | AC75: =N75 -> 0 | AD75: =O75 -> 0 | AE75: =P75 -> 0 | AF75: =Q75 -> 0 | AG75: =R75 -> 0 | AH75: =S75 -> 0 | AI75: =T75 -> 0 | AK75: =SUM(X75:AI75) -> 0 | AL75: =U75-X75-Y75-Z75-AA75-AB75-AC75-AD75-AE75-AF75-AG75-AH75-AI75 -> 0 | AP75: =AM75+AN75+AO75 -> 0
A76: 76 | B76: Basit Khan 2023 | C76: SharePoint | D76: 10000 | E76: 6000 | F76: 44805 | G76: 45169 | H76: Akbar Sir | I76: 5000 | J76: 5000 | K76: =E76/20*16 -> 4800 | L76: 0 | M76: 0 | T76: 0 | U76: =SUM(I76:T76) -> 14800 | W76: ='2022'!U27 -> 20636.364 | X76: Loan Adjusted | Y76: Loan Adjusted | Z76: Loan Adjusted | AA76: =L76 -> 0 | AC76: =N76 -> 0 | AD76: =O76 -> 0 | AE76: =P76 -> 0 | AF76: =Q76 -> 0 | AG76: =R76 -> 0 | AH76: =S76 -> 0 | AI76: =T76 -> 0 | AK76: =SUM(X76:AI76) -> 0 | AL76: =U76-X76-Y76-Z76-AA76-AB76-AC76-AD76-AE76-AF76-AG76-AH76-AI76 -> #VALUE! | AP76: =AM76+AN76+AO76 -> 0
A77: 77 | B77: Shifa Khan | C77: Sales | D77: 6000 | E77: 6000 | H77: Akbar Sir | I77: NA | J77: NA | K77: NA | L77: NA | M77: 0 | AB77: =M77 -> 0
A78: 78 | B78: Rehan Shaikh | C78: Salesforce admin | D78: 6000 | E78: 10000 | F78: 45085 | G78: 45604 | H78: Akbar Sir | I78: NA | J78: NA | K78: NA | L78: NA | M78: NA | N78: 0
A79: 24 | B79: Sadat sir | C79: Sales | D79: 3500AED | E79: 3500AED | H79: Akbar sir | I79: 2500 | J79: 1500 | K79: 0 | L79: 0 | M79: 0 | N79: 0 | O79: 0 | U79: =SUM(I79:T79) -> 4000 | AK79: =SUM(X79:AI79) -> 0 | AL79: =U79-X79-Y79-Z79-AA79-AB79-AC79-AD79-AE79-AF79-AG79-AH79-AI79 -> 4000 | AP79: =AM79+AN79+AO79 -> 0
A80: 37 | B80: Asbiya Sadaf | C80: Salesforce admin | D80: 10000 | E80: 6000 | F80: 44809 | G80: 45173 | H80: Shahid Qadri | I80: 6000 | J80: 5000 | K80: =E80/20*16 -> 4800 | L80: 6000 | M80: 4000 | N80: 4000 | O80: =E80/21*15 -> 4285.7143 | U80: =SUM(I80:T80) -> 34085.714 | W80: ='[1]2022'!U29 -> #REF! | AE80: =P80 -> 0 | AF80: =Q80 -> 0 | AG80: =R80 -> 0 | AH80: =S80 -> 0 | AI80: =T80 -> 0 | AK80: =SUM(X80:AI80) -> 0 | AL80: =U80-X80-Y80-Z80-AA80-AB80-AC80-AD80-AE80-AF80-AG80-AH80-AI80 -> 34085.714 | AP80: =AM80+AN80+AO80 -> 0
A81: 49 | B81: Muneer Ahmad | C81: Sharepoint | D81: 6000 | E81: 10000 | F81: 45085 | G81: 45238 | H81: Akbar Sir | I81: NA | J81: NA | K81: NA | L81: NA | M81: NA | N81: 3000 | O81: 5000
A82: 51 | B82: Mohammad Sameer | C82: Sharepoint | D82: 6000 | E82: 10000 | F82: 45085 | G82: 45604 | H82: Akbar Sir | I82: NA | J82: NA | K82: NA | L82: NA | M82: NA | N82: 3000 | O82: =E82/25*6 -> 2400
A83: 52 | B83: Minhaj mohammed | C83: SharePoint | D83: 6000 | E83: 10000 | F83: 44706 | G83: 45071 | H83: Akbar Sir | I83: 5000 | J83: =E83/23*17 -> 7391.3043 | K83: =E83/20*9.5 -> 4750 | L83: 8000 | M83: 5000 | N83: 5000 | O83: 10000 | U83: =SUM(I83:T83) -> 45141.304 | W83: ='[1]2022'!U37 -> #REF! | AE83: =P83 -> 0 | AF83: =Q83 -> 0 | AG83: =R83 -> 0 | AH83: =S83 -> 0 | AI83: =T83 -> 0 | AK83: =SUM(X83:AI83) -> 0 | AL83: =U83-X83-Y83-Z83-AA83-AB83-AC83-AD83-AE83-AF83-AG83-AH83-AI83 -> 45141.304 | AP83: =AM83+AN83+AO83 -> 0
A85: 37 | B85: Afroz Khan | C85: Salesforce admin | D85: 10000 | E85: 6000 | F85: 44770 | G85: 45136 | H85: Akbar Sir | I85: 6000 | J85: 1000 | K85: 3000 | L85: 3000 | M85: 4000 | N85: 4000 | O85: 4000 | P85: 5000 | U85: =SUM(I85:T85) -> 30000 | W85: #REF! | AG85: =R85 -> 0 | AH85: =S85 -> 0 | AI85: =T85 -> 0 | AK85: =SUM(X85:AI85) -> 0 | AL85: =U85-X85-Y85-Z85-AA85-AB85-AC85-AD85-AE85-AF85-AG85-AH85-AI85 -> 30000 | AP85: =AM85+AN85+AO85 -> 0
A86: 42 | B86: Humera Shaikh | C86: Salesforce-Eienstein | D86: 6000 | E86: 10000 | F86: 44609 | G86: 44974 | H86: Zeeshan shaikh | I86: =E86/22*7 -> 3181.8182 | J86: 3000 | K86: 4000 | L86: 5000 | M86: 4000 | N86: 8000 | O86: 0 | P86: 0 | U86: =SUM(I86:T86) -> 27181.818 | W86: =SUM(J86:T86) -> 24000 | AG86: =R86 -> 0 | AH86: =S86 -> 0 | AI86: =T86 -> 0 | AK86: =SUM(X86:AI86) -> 0 | AL86: =U86-X86-Y86-Z86-AA86-AB86-AC86-AD86-AE86-AF86-AG86-AH86-AI86 -> 27181.818 | AP86: =AM86+AN86+AO86 -> 0
A87: 41 | B87: Mahek shaikh | C87: Salesforce-Eienstein | D87: 6000 | E87: 10000 | F87: 44656 | G87: 45204 | H87: Zeeshan shaikh | I87: =E87/22*13 -> 5909.0909 | J87: 10000 | K87: 10000 | L87: 5000 | M87: 5000 | N87: 7000 | O87: 6000 | P87: 6000 | Q87: 5000 | R87: Bonus has stopped from this month | U87: =SUM(I87:T87) -> 59909.091 | W87: ='[1]2022'!U61 -> #REF! | AH87: =S87 -> 0 | AI87: =T87 -> 0 | AL87: =U87-X87-Y87-Z87-AA87-AB87-AC87-AD87-AE87-AF87-AG87-AH87-AI87 -> 59909.091 | AM87: =W87 -> #REF! | AP87: =AL87+AM87+AN87+AO87 -> #REF!
A88: 48 | B88: Anam Khan | C88: SharePoint | D88: 6000 | E88: 10000 | F88: 44820 | G88: 45185 | H88: Akbar Sir | I88: 5000 | J88: 2000 | K88: 6000 | L88: 5000 | M88: 0 | N88: 5000 | O88: 4000 | P88: 0 | Q88: 10000 | U88: =SUM(I88:T88) -> 37000 | W88: ='[1]2022'!U53 -> #REF! | AH88: =S88 -> 0 | AI88: =T88 -> 0 | AK88: =SUM(X88:AI88) -> 0 | AL88: =U88-X88-Y88-Z88-AA88-AB88-AC88-AD88-AE88-AF88-AG88-AH88-AI88 -> 37000 | AP88: =AM88+AN88+AO88 -> 0
A89: 29 | B89: Shaikh Asmina Mohd Aslam | C89: Salesforce admin | D89: 20000 | E89: 5000 | F89: 44744 | G89: 45109 | H89: Akbar Sir | I89: =E89/22*18 -> 4090.9091 | J89: =E89/23*17 -> 3695.6522 | K89: 5000 | L89: 5000 | M89: 5000 | N89: 5000 | O89: 0 | P89: 2000 | Q89: 0 | U89: =SUM(I89:T89) -> 29786.561 | W89: ='[1]2022'!U47 -> #REF! | AD89: =O89 -> 0 | AH89: =S89 -> 0 | AI89: =T89 -> 0 | AK89: =SUM(X89:AI89) -> 0 | AL89: =U89-X89-Y89-Z89-AA89-AB89-AC89-AD89-AE89-AF89-AG89-AH89-AI89 -> 29786.561 | AP89: =AM89+AN89+AO89 -> 0
A90: 8 | B90: Shazeena aslam motani | C90: Financial Force-PSA | D90: 25000 | E90: 8000 | F90: 44723 | G90: 45454 | H90: Akbar Sir | I90: 0 | J90: 8000 | K90: 8000 | L90: 8000 | M90: 8000 | N90: 4000 | O90: 4000 | P90: 3000 | Q90: 0 | U90: =SUM(I90:T90) -> 43000 | V90: =D90*2 -> 50000 | W90: ='[1]On hold bonus'!B31 -> #REF! | X90: =I90 -> 0 | Y90: 8000 | Z90: =K90 -> 8000 | AA90: =L90 -> 8000 | AB90: =M90 -> 8000 | AC90: =N90 -> 4000 | AD90: =O90 -> 4000 | AE90: =P90 -> 3000 | AF90: =Q90 -> 0 | AH90: =S90 -> 0 | AI90: =T90 -> 0 | AK90: =SUM(X90:AI90) -> 43000 | AL90: =U90-X90-Y90-Z90-AA90-AB90-AC90-AD90-AE90-AF90-AG90-AH90-AI90 -> 0 | AM90: #REF! | AN90: #REF! | AP90: =AM90+AN90+AO90 -> #VALUE!
A91: 42 | B91: Saba Shaikh | C91: SharePoint | D91: 50000 | E91: 5000 | F91: 44824 | G91: 45189 | H91: Akbar Sir | I91: =E91/22*19 -> 4318.1818 | J91: 5000 | K91: =E91/20*14 -> 3500 | L91: 4000 | M91: 5000 | N91: =E91/22*15 -> 3409.0909 | O91: 3000 | P91: 4000 | Q91: 5000 | U91: =SUM(I91:T91) -> 37227.273 | W91: ='[1]2022'!U40 -> #REF! | AH91: =S91 -> 0 | AI91: =T91 -> 0 | AK91: =SUM(X91:AI91) -> 0 | AL91: =U91-X91-Y91-Z91-AA91-AB91-AC91-AD91-AE91-AF91-AG91-AH91-AI91 -> 37227.273 | AP91: =AM91+AN91+AO91 -> 0
A92: 27 | B92: Aaliya Bhatkar | C92: Sales | D92: 6000 | E92: 6000 | F92: 45097 | H92: Akbar Sir | I92: NA | J92: NA | K92: NA | L92: 6000 | M92: NA | N92: NA | O92: 6000 | P92: 6000 | Q92: =E92/21*17 -> 4857.1429 | R92: 6000 | AF92: =Q92 -> 4857.1429 | AG92: =R92 -> 6000 | AH92: a
A93: 38 | B93: Akbar Shaikh | C93: Salesforce admin | D93: 6000 | E93: 10000 | F93: 44758 | G93: 45123 | H93: Akbar Sir | I93: 2000 | J93: 3000 | K93: 5000 | L93: 5000 | M93: 8000 | N93: 0 | O93: 4000 | P93: 5000 | Q93: 4000 | R93: 0 | U93: =SUM(I93:T93) -> 36000 | W93: ='[1]On hold bonus'!B9 -> #REF! | AB93: 39500 | AC93: Fully paid | AH93: =S93 -> 0 | AI93: =T93 -> 0 | AK93: =SUM(X93:AI93) -> 39500 | AL93: =U93-X93-Y93-Z93-AA93-AB93-AC93-AD93-AE93-AF93-AG93-AH93-AI93 -> #VALUE! | AP93: =AM93+AN93+AO93 -> 0
A94: 39 | B94: Mehboob Shaikh | C94: Salesforce admin | D94: 10000 | E94: 6000 | F94: 44841 | G94: 45206 | H94: Akbar Sir | V94: =SUM(I94:T94) -> 0 | W94: ='[1]2022'!U51 -> #REF!
A95: 42 | B95: Shaikh Zeeshan Shaikh Rafeeque | C95: Salesforce-Eienstein | D95: 40000 | E95: 10000 | F95: 44817 | G95: 45182 | H95: Akbar Sir | I95: =E95/23*17 -> 7391.3043 | J95: Last date was on 16 jan | K95: Blog Not Submitted | W95: =SUM(I95:U95) -> 7391.3043 | X95: ='[1]On hold bonus'!B47 -> #REF! | Y95: =I95 -> 7391.3043 | Z95: a | AA95: =K95 -> Blog Not Submitted | AB95: =M95 -> 0 | AC95: =N95 -> 0 | AE95: =P95 -> 0 | AF95: =Q95 -> 0 | AG95: =R95 -> 0 | AH95: =S95 -> 0 | AI95: =T95 -> 0 | AJ95: =U95 -> 0
A96: 50 | B96: Minhaj mohammed | C96: SharePoint | D96: 20000 | E96: 6000 | F96: 45302 | G96: 45668 | H96: Akbar Sir | I96: =E96/23*13 -> 3391.3043 | J96: Contract renewed from 11 jan 2024 | W96: =SUM(I96:U96) -> 3391.3043 | X96: ='[1]2022'!#REF! -> #REF! | AF96: =Q96 -> 0 | AG96: =R96 -> 0 | AH96: =S96 -> 0
A97: 31 | B97: Heena khan | C97: Sales | D97: 6000 | E97: 6000 | H97: Akbar Sir | I97: =E97/23*13 -> 3391.3043 | X97: =SUM(I97:V97) -> 3391.3043 | Z97: =I97 -> 3391.3043 | AA97: a | AF97: =Q97 -> 0 | AG97: =R97 -> 0 | AH97: =S97 -> 0 | AI97: =T97 -> 0 | AJ97: =U97 -> 0 | AK97: =V97 -> 0
A98: 31 | B98: Hajra Shaikh | C98: Sales | D98: 6000 | E98: 6000 | H98: Akbar Sir | I98: =E98/22*14 -> 3818.1818 | J98: =E98/22*11 -> 3000 | K98: 11 Leaves ( Last Date On 9 Feb) | X98: =SUM(I98:V98) -> 6818.1818 | Y98: ='[1]2022'!U21 -> #REF! | Z98: =I98 -> 3818.1818 | AA98: 3000 | AB98: hold | AC98: =N98 -> 0 | AD98: =O98 -> 0 | AE98: =P98 -> 0 | AF98: =Q98 -> 0 | AG98: =R98 -> 0 | AH98: =S98 -> 0 | AI98: =T98 -> 0 | AJ98: =U98 -> 0 | AK98: =V98 -> 0
A99: 42 | B99: Sidra Ansari | C99: SharePoint | D99: 35000 | E99: 0 | F99: 45329 | G99: 45511 | H99: Akbar Sir | I99: 10000 | J99: =10000/22*8.5 -> 3863.6364 | M99: Blog Submitted | X99: =SUM(I99:V99) -> 13863.636 | Y99: ='[1]2022'!U54 -> #REF!
A100: 51 | B100: Baseet Baig | C100: Uipath | D100: 6000 | E100: 10000 | F100: 44881 | G100: 45246 | H100: Akbar Sir | I100: =E100/23*17 -> 7391.3043 | J100: =E100/22*15 -> 6818.1818 | X100: =SUM(I100:V100) -> 14209.486 | Y100: #REF!
A102: Asmina | B102: Financial Force-PSA | C102: 20000 | D102: 5000 | E102: 9000 | F102: 45109 | G102: 4500 | H102: 7000 | I102: 0 | J102: 0 | K102: 0 | L102: 0 | M102: 0 | N102: NA | O102: NA | P102: NA | Q102: NA | R102: NA | S102: =SUM(G102:R102) -> 11500
...

Sheet Marketing Bouns sheet
A1: Target based on Old criteria
